Workbook

Sheet Balance de comprobación
B1: Saldo inicial | D1: De 01/01/2025 a 31/03/2026 | F1: Saldo final
B3: Debe | C3: Haber | D3: Debe | E3: Haber | F3: Debe | G3: Haber | I3: LIBRO MAYOR | J3: DIF
A4: 1211003 FACTURAS POR COBRAR DEL EXTERIOR | D4: 42.58 | E4: 42.58 | I4: 0
A5: 1212001 FACTURAS POR COBRAR NACIONALES M.N. | D5: 80303081 | E5: 76745669 | F5: 3557412.7 | I5: =+'12121xx1'!M2772 -> 3557412.7 | J5: =+F5-I5 -> -8.3819032e-09
A6: 1212002 FACTURAS POR COBRAR NACIONALES M.E. | D6: 294639.07 | E6: 195884.59 | F6: 98754.48 | I6: =+'1212xx2'!M98 -> 98754.48 | J6: =+F6-I6 -> 0
A7: 1212003 FACTURAS POR COBRAR DEL EXTERIOR | D7: 81530992 | E7: 71881450 | F7: 9649541.6 | I7: =+'1212xx3'!M82 -> 9649541.6 | J7: =+F7-I7 -> 0
A8: 1220001 ANTICIPOS CLIENTES NACIONAL M.N. | D8: 857993.19 | E8: 942331.14 | G8: 84337.95 | I8: =+'122xx1'!M99 -> -84337.95 | J8: =+G8+I8 -> 0
A9: 1220002 ANTICIPOS CLIENTES NACIONAL M.E. | D9: 84.59 | E9: 29089.79 | G9: 29005.2 | I9: =+'122xx2'!M5 -> -29005.2 | J9: =+G9+I9 -> 0
A10: 1220003 ANTICIPOS CLIENTES DEL EXTERIOR | D10: 10473235 | E10: 14306947 | G10: 3833712.5 | I10: =+'122xx3'!M130 -> -3833712.5 | J10: =+G10+I10 -> 0
A11: 1220004 ANTICIPOS VENTA DE DEPARTAMENTO PROY SB | D11: 134880.59 | E11: 237348.82 | G11: 102468.23 | I11: =+'122xx4'!M177 -> -102468.23 | J11: =+G11+I11 -> 0
A12: 1220005 ANTICIPOS VENTA - MARKETPLACE | D12: 131066.59 | E12: 189006.87 | G12: 57940.28 | I12: =+'122xx5'!M879 -> -57940.28 | J12: =+G12+I12 -> 0
A13: 1220006 ANTICIPOS VENTAS MN - SALDOS INICIALES | D13: 128978.39 | E13: 128978.39 | I13: 0
A14: 1220007 ANTICIPOS VENTAS ME - SALDOS INICIALES | D14: 1236491.5 | E14: 1236491.5 | I14: 0
A15: 1232001 LETRAS EN CARTERA NACIONAL M.N. | D15: 43581620 | E15: 42326586 | F15: 1255034.3 | I15: =+'1232xx1'!M136 -> 1255034.3 | J15: =+F15-I15 -> 0
A16: 1232002 LETRAS EN CARTERA NACIONAL M.E. | D16: 3956140.9 | E16: 3956140.9 | I16: 0
A17: 1233001 LETRAS EN COBRANZA NACIONAL M.N. | D17: 7623115.6 | E17: 6227841.4 | F17: 1395274.2 | I17: =+'1233xx1'!M98 -> 1395274.2 | J17: =+F17-I17 -> 0
A18: 1234001 LETRAS EN DESCUENTO NACIONAL M.N. | D18: 38471362 | E18: 34251057 | F18: 4220304.4 | I18: =+'1234xx1'!M586 -> 4220304.5 | J18: =+F18-I18 -> -9.3132257e-09
A19: 1234004 LETRAS PROTESTADAS NACIONAL M.N. | D19: 1130525 | E19: 1055020.4 | F19: 75504.64 | I19: =+'1234xx4'!M41 -> 75504.64 | J19: =+F19-I19 -> 0
A20: 1239001 LETRAS - SALDOS INICIALES | D20: 8310858 | E20: 8310858
A21: 1312001 FACTURAS POR COBRAR NACIONALES M.N. - EMITIDAS | D21: 5917509.7 | E21: 4111974.1 | F21: 1806544.5 | I21: =+'1312xx1'!M142 -> 1806544.5 | J21: =+F21-I21 -> 0
A22: 1312002 FACTURAS POR COBRAR NACIONALES M.E. - EMITIDAS | D22: 13118.67 | E22: 11375.67 | F22: 1743 | I22: =+'1312xx2'!M8 -> 1743 | J22: =+F22-I22 -> 0
A23: 1312003 FACTURAS POR COBRAR DEL EXTERIOR - EMITIDAS | D23: 33407134 | E23: 20872452 | F23: 12534682 | I23: =+'1312xx3'!J59 -> 12534682 | J23: =+F23-I23 -> 0.0032599978
A24: 1321001 ANTICIPOS CLIENTES NACIONAL M.N. | D24: 4402.98 | E24: 4481.83 | G24: 78.85 | I24: =+'1321xx1'!M5 -> -78.85 | J24: =+G24+I24 -> 3.6948222e-13
A25: 1321003 ANTICIPOS CLIENTES DEL EXTERIOR | D25: 2909244.9 | E25: 2909244.9
A26: 1331001 LETRAS EN CARTERA NACIONAL M.N. | D26: 12166.48 | F26: 12166.48 | I26: =+'1331xx1'!M11 -> 12166.48 | J26: =+F26-I26 -> 0
A27: 1332001 LETRAS EN COBRANZA NACIONAL M.N. | D27: 3180.62 | F27: 3180.62 | I27: =+'1332xx1'!M14 -> 3180.62 | J27: =+F27-I27 -> 0
A28: 1333004 LETRAS PROTESTADAS NACIONAL M.N. | D28: 73693.8 | F28: 73693.8 | I28: =+'133xx4'!M91 -> 73693.8 | J28: =+F28-I28 -> 0
A29: 1911001 FACTURAS, BOLETAS Y OTROS COMPROBANTES POR COBRAR M.N. | E29: 129937.94 | G29: 129937.94
A30: 1913001 LETRAS POR COBRAR M.N. | E30: 178937.66 | G30: 178937.66
A31: 4511002 RESPONSABILIDAD LETRAS DESCONTADAS MN | D31: 35360332 | E31: 39580637 | G31: 4220304.4

Sheet 12121xx1
A1: Asiento contable | B1: Número | C1: Fecha | D1: Fecha de vencimiento | E1: Cuenta | F1: Socio | G1: Etiqueta | H1: Referencia | I1: Moneda | J1: Importe en moneda | K1: Debe | L1: Haber | M1: Saldo | N1: Conciliación | O1: Creado por
A2: 1212001 FACTURAS POR COBRAR NACIONALES M.N. (29740)
A3: F F01-00005209 | B3: F F01-00005209 | C3: 46112 | D3: 46142 | E3: 1212001 FACTURAS POR COBRAR NACIONALES M.N. | F3: VETERINARIAS INTEGRADAS S.A.C. | G3: F F01-00005209 | I3: PEN | J3: 1318.06 | K3: 1318.06 | M3: 1318.06 | O3: PALIZA CAMAVILCA, JHOSSELYN JARUMY
A4: F F01-00005208 | B4: F F01-00005208 | C4: 46112 | D4: 46142 | E4: 1212001 FACTURAS POR COBRAR NACIONALES M.N. | F4: VETERINARIAS INTEGRADAS S.A.C. | G4: F F01-00005208 | I4: PEN | J4: 988.84 | K4: 988.84 | M4: 988.84 | O4: PALIZA CAMAVILCA, JHOSSELYN JARUMY
A5: F F01-00005207 | B5: F F01-00005207 | C5: 46112 | D5: 46142 | E5: 1212001 FACTURAS POR COBRAR NACIONALES M.N. | F5: SOLUCIONES Y DESARROLLO VETERINARIO SOCIEDAD ANONIMA CERRADA | G5: F F01-00005207 | I5: PEN | J5: 610.65 | K5: 610.65 | M5: 610.65 | N5: A156993 | O5: PALIZA CAMAVILCA, JHOSSELYN JARUMY
A6: F F01-00005206 | B6: F F01-00005206 | C6: 46112 | D6: 46142 | E6: 1212001 FACTURAS POR COBRAR NACIONALES M.N. | F6: MASCOTAS PERUANAS S.A.C. | G6: F F01-00005206 | I6: PEN | J6: 3149.35 | K6: 3149.35 | M6: 3149.35 | N6: A150553 | O6: PALIZA CAMAVILCA, JHOSSELYN JARUMY
A7: F F01-00005203 | B7: F F01-00005203 | C7: 46112 | D7: 46202 | E7: 1212001 FACTURAS POR COBRAR NACIONALES M.N. | F7: TIENDAS SUPERPET SOCIEDAD ANONIMA CERRADA - TIENDAS SUPERPET S.A.C. | G7: F F01-00005203 | I7: PEN | J7: 14876.89 | K7: 14876.89 | M7: 14876.89 | O7: PALIZA CAMAVILCA, JHOSSELYN JARUMY
A8: F F01-00005198 | B8: F F01-00005198 | C8: 46112 | D8: 46142 | E8: 1212001 FACTURAS POR COBRAR NACIONALES M.N. | F8: M & C VET S.A.C. | G8: F F01-00005198 | I8: PEN | J8: 1749.35 | K8: 1749.35 | M8: 1749.35 | N8: A149116 | O8: PALIZA CAMAVILCA, JHOSSELYN JARUMY
A9: F F01-00005193 | B9: F F01-00005193 | C9: 46112 | D9: 46172 | E9: 1212001 FACTURAS POR COBRAR NACIONALES M.N. | F9: REPRESENTACIONES DURAND S.A.C. | G9: F F01-00005193 | I9: PEN | J9: 3707.09 | K9: 3707.09 | M9: 3707.09 | N9: A145572 | O9: PALIZA CAMAVILCA, JHOSSELYN JARUMY
A10: F F01-00005187 | B10: F F01-00005187 | C10: 46112 | D10: 46112 | E10: 1212001 FACTURAS POR COBRAR NACIONALES M.N. | F10: TAI LOY S.A. | G10: F F01-00005187 | I10: PEN | J10: 71.91 | K10: 71.91 | M10: 71.91 | O10: PALIZA CAMAVILCA, JHOSSELYN JARUMY
A11: F F01-00005179 | B11: F F01-00005179 | C11: 46112 | D11: 46112 | E11: 1212001 FACTURAS POR COBRAR NACIONALES M.N. | F11: TAI LOY S.A. | G11: F F01-00005179 | I11: PEN | J11: 180.2 | K11: 180.2 | M11: 180.2 | O11: PALIZA CAMAVILCA, JHOSSELYN JARUMY
A12: F F01-00005175 | B12: F F01-00005175 | C12: 46112 | D12: 46112 | E12: 1212001 FACTURAS POR COBRAR NACIONALES M.N. | F12: GARCIA FIESTAS JOSE AURELIO-10105455629 | G12: F F01-00005175 | I12: PEN | J12: 860 | K12: 860 | M12: 860 | N12: A148148 | O12: PALIZA CAMAVILCA, JHOSSELYN JARUMY
A13: F F01-00005174 | B13: F F01-00005174 | C13: 46112 | D13: 46112 | E13: 1212001 FACTURAS POR COBRAR NACIONALES M.N. | F13: TAI LOY S.A. | G13: F F01-00005174 | I13: PEN | J13: 48.96 | K13: 48.96 | M13: 48.96 | O13: PALIZA CAMAVILCA, JHOSSELYN JARUMY
A14: F D01-00000263 | B14: F D01-00000263 | C14: 46112 | D14: 46112 | E14: 1212001 FACTURAS POR COBRAR NACIONALES M.N. | F14: LESCANO VALENCIA AMANDA ANGELICA | G14: F D01-00000263 | I14: PEN | J14: 100.92 | K14: 100.92 | M14: 100.92 | O14: MATTO ASTETE, AUGUSTO WALTER
A15: CAMBI/2026/03/1731 (AJUSTE POR DIFERENCIA DE CAMBIO MAR-2026) | B15: CAMBI/2026/03/1731 | C15: 46112 | E15: 1212001 FACTURAS POR COBRAR NACIONALES M.N. | G15: AJUSTE DF TC MAR-2026 | H15: AJUSTE POR DIFERENCIA DE CAMBIO MAR-2026 | I15: USD | K15: 8.9 | M15: 8.9 | N15: A159652 | O15: BACKOFIS
A16: B B01-00007574 | B16: B B01-00007574 | C16: 46112 | D16: 46112 | E16: 1212001 FACTURAS POR COBRAR NACIONALES M.N. | F16: PEDEMONTE CORDOVA, HILDE ALBERTH | G16: B B01-00007574 | I16: PEN | J16: 132.99 | K16: 132.99 | M16: 132.99 | N16: A158708 | O16: PALIZA CAMAVILCA, JHOSSELYN JARUMY
A17: B B01-00007573 | B17: B B01-00007573 | C17: 46112 | D17: 46112 | E17: 1212001 FACTURAS POR COBRAR NACIONALES M.N. | F17: ALMEYDA CANDIOTI, KEVIN ALEXANDER | G17: B B01-00007573 | I17: PEN | J17: 162.41 | K17: 162.41 | M17: 162.41 | N17: A158709 | O17: PALIZA CAMAVILCA, JHOSSELYN JARUMY
A18: B B01-00007572 | B18: B B01-00007572 | C18: 46112 | D18: 46112 | E18: 1212001 FACTURAS POR COBRAR NACIONALES M.N. | F18: GUZMAN DOMINGUEZ, PEDRO ARTURO | G18: B B01-00007572 | I18: PEN | J18: 279.17 | K18: 279.17 | M18: 279.17 | N18: A158710 | O18: PALIZA CAMAVILCA, JHOSSELYN JARUMY
A19: B B01-00007569 | B19: B B01-00007569 | C19: 46112 | D19: 46112 | E19: 1212001 FACTURAS POR COBRAR NACIONALES M.N. | F19: RAMIREZ CORDOVA, NELLY JUANITA | G19: B B01-00007569 | I19: PEN | J19: 229.5 | K19: 229.5 | M19: 229.5 | O19: PALIZA CAMAVILCA, JHOSSELYN JARUMY
A20: B B01-00007568 | B20: B B01-00007568 | C20: 46112 | D20: 46112 | E20: 1212001 FACTURAS POR COBRAR NACIONALES M.N. | F20: PILCO GOMEZ, LARISA VICTORIA | G20: B B01-00007568 | I20: PEN | J20: 561.68 | K20: 561.68 | M20: 561.68 | N20: A158711 | O20: PALIZA CAMAVILCA, JHOSSELYN JARUMY
A21: B B01-00007566 | B21: B B01-00007566 | C21: 46112 | D21: 46112 | E21: 1212001 FACTURAS POR COBRAR NACIONALES M.N. | F21: CUADROS LUTTERBACH, DIETLIND KAREN | G21: B B01-00007566 | I21: PEN | J21: 88.31 | K21: 88.31 | M21: 88.31 | N21: A158712 | O21: PALIZA CAMAVILCA, JHOSSELYN JARUMY
A22: F F01-00005170 | B22: F F01-00005170 | C22: 46111 | D22: 46186 | E22: 1212001 FACTURAS POR COBRAR NACIONALES M.N. | F22: TOP VETERINARIA S.A.C. | G22: F F01-00005170 | I22: PEN | J22: 147833.88 | K22: 147833.88 | M22: 147833.88 | N22: A148597 | O22: PALIZA CAMAVILCA, JHOSSELYN JARUMY
A23: F F01-00005168 | B23: F F01-00005168 | C23: 46111 | D23: 46201 | E23: 1212001 FACTURAS POR COBRAR NACIONALES M.N. | F23: AGROPEC SOCIEDAD COMERCIAL DE RESPONSABILIDAD LIMITADA | G23: F F01-00005168 | I23: PEN | J23: 12845.51 | K23: 12845.51 | M23: 12845.51 | N23: A144559 | O23: PALIZA CAMAVILCA, JHOSSELYN JARUMY
A24: F F01-00005167 | B24: F F01-00005167 | C24: 46111 | D24: 46201 | E24: 1212001 FACTURAS POR COBRAR NACIONALES M.N. | F24: TIENDAS SUPERPET SOCIEDAD ANONIMA CERRADA - TIENDAS SUPERPET S.A.C. | G24: F F01-00005167 | I24: PEN | J24: 31865.51 | K24: 31865.51 | M24: 31865.51 | O24: PALIZA CAMAVILCA, JHOSSELYN JARUMY
A25: F F01-00005162 | B25: F F01-00005162 | C25: 46111 | D25: 46171 | E25: 1212001 FACTURAS POR COBRAR NACIONALES M.N. | F25: DISTRIBUCIONES AGROVENS E.I.R.L. | G25: F F01-00005162 | I25: PEN | J25: 3071.33 | K25: 3071.33 | M25: 3071.33 | N25: A144205 | O25: PALIZA CAMAVILCA, JHOSSELYN JARUMY
A26: F F01-00005157 | B26: F F01-00005157 | C26: 46111 | D26: 46141 | E26: 1212001 FACTURAS POR COBRAR NACIONALES M.N. | F26: GROUP VET S.A.C. | G26: F F01-00005157 | I26: PEN | J26: 2582.78 | K26: 2582.78 | M26: 2582.78 | N26: A153156 | O26: PALIZA CAMAVILCA, JHOSSELYN JARUMY
A27: F F01-00005151 | B27: F F01-00005151 | C27: 46111 | D27: 46111 | E27: 1212001 FACTURAS POR COBRAR NACIONALES M.N. | F27: TAI LOY S.A. | G27: F F01-00005151 | I27: PEN | J27: 36.72 | K27: 36.72 | M27: 36.72 | O27: PALIZA CAMAVILCA, JHOSSELYN JARUMY
A28: F F01-00005148 | B28: F F01-00005148 | C28: 46111 | D28: 46111 | E28: 1212001 FACTURAS POR COBRAR NACIONALES M.N. | F28: LSPSICOTERAPIA E.I.R.L. | G28: F F01-00005148 | I28: PEN | J28: 131.04 | K28: 131.04 | M28: 131.04 | N28: A158696 | O28: PALIZA CAMAVILCA, JHOSSELYN JARUMY
A29: F F01-00005144 | B29: F F01-00005144 | C29: 46111 | D29: 46111 | E29: 1212001 FACTURAS POR COBRAR NACIONALES M.N. | F29: TAI LOY S.A. | G29: F F01-00005144 | I29: PEN | J29: 180.2 | K29: 180.2 | M29: 180.2 | O29: PALIZA CAMAVILCA, JHOSSELYN JARUMY
A30: F D01-00000262 | B30: F D01-00000262 | C30: 46111 | D30: 46111 | E30: 1212001 FACTURAS POR COBRAR NACIONALES M.N. | F30: H & P DISTRIBUCIONES Y REPRESENTACIONES SOCIEDAD ANONIMA CERRADA | G30: F D01-00000262 | I30: PEN | J30: 168.48 | K30: 168.48 | M30: 168.48 | N30: A158008 | O30: PALIZA CAMAVILCA, JHOSSELYN JARUMY
A31: B B01-00007557 | B31: B B01-00007557 | C31: 46111 | D31: 46111 | E31: 1212001 FACTURAS POR COBRAR NACIONALES M.N. | F31: ESPINOZA MELENDEZ, FRIDA SOFIA | G31: B B01-00007557 | I31: PEN | J31: 188.2 | K31: 188.2 | M31: 188.2 | N31: A158697 | O31: PALIZA CAMAVILCA, JHOSSELYN JARUMY
A32: B B01-00007536 | B32: B B01-00007536 | C32: 46111 | D32: 46111 | E32: 1212001 FACTURAS POR COBRAR NACIONALES M.N. | F32: BRACAMONTE FERNANDEZ, LUIS FERNANDO | G32: B B01-00007536 | I32: PEN | J32: 146.25 | K32: 146.25 | M32: 146.25 | N32: A159010 | O32: PALIZA CAMAVILCA, JHOSSELYN JARUMY
A33: B B01-00007528 | B33: B B01-00007528 | C33: 46111 | D33: 46111 | E33: 1212001 FACTURAS POR COBRAR NACIONALES M.N. | F33: CACERES AGUIRRE, ESTEFANNY TANIA | G33: B B01-00007528 | I33: PEN | J33: 55.6 | K33: 55.6 | M33: 55.6 | N33: A158698 | O33: PALIZA CAMAVILCA, JHOSSELYN JARUMY
A34: B B01-00007527 | B34: B B01-00007527 | C34: 46111 | D34: 46111 | E34: 1212001 FACTURAS POR COBRAR NACIONALES M.N. | F34: SANCHEZ HINOJOSA, MAYRA ALEJANDRA | G34: B B01-00007527 | I34: PEN | J34: 247.15 | K34: 247.15 | M34: 247.15 | N34: A158699 | O34: PALIZA CAMAVILCA, JHOSSELYN JARUMY
A35: B B01-00007526 | B35: B B01-00007526 | C35: 46111 | D35: 46111 | E35: 1212001 FACTURAS POR COBRAR NACIONALES M.N. | F35: BUSTAMANTE SOLANO, JAVIER ALVARO | G35: B B01-00007526 | I35: PEN | J35: 48.5 | K35: 48.5 | M35: 48.5 | N35: A158700 | O35: PALIZA CAMAVILCA, JHOSSELYN JARUMY
A36: B B01-00007524 | B36: B B01-00007524 | C36: 46111 | D36: 46111 | E36: 1212001 FACTURAS POR COBRAR NACIONALES M.N. | F36: CERPA SOLORZANO, CARLOS | G36: B B01-00007524 | I36: PEN | J36: 719.27 | K36: 719.27 | M36: 719.27 | N36: A158701 | O36: PALIZA CAMAVILCA, JHOSSELYN JARUMY
A37: B B01-00007522 | B37: B B01-00007522 | C37: 46111 | D37: 46111 | E37: 1212001 FACTURAS POR COBRAR NACIONALES M.N. | F37: SIFUENTES RODRIGUEZ, GUILLERMO DAVID | G37: B B01-00007522 | I37: PEN | J37: 209.43 | K37: 209.43 | M37: 209.43 | N37: A158702 | O37: PALIZA CAMAVILCA, JHOSSELYN JARUMY
A38: B B01-00007521 | B38: B B01-00007521 | C38: 46111 | D38: 46111 | E38: 1212001 FACTURAS POR COBRAR NACIONALES M.N. | F38: JERI LUCAS, LUIS EDUARDO | G38: B B01-00007521 | I38: PEN | J38: 169.11 | K38: 169.11 | M38: 169.11 | N38: A158703 | O38: PALIZA CAMAVILCA, JHOSSELYN JARUMY
A39: B B01-00007520 | B39: B B01-00007520 | C39: 46111 | D39: 46111 | E39: 1212001 FACTURAS POR COBRAR NACIONALES M.N. | F39: OLANO CORTEZ, LISSETTE NANCY | G39: B B01-00007520 | I39: PEN | J39: 107.2 | K39: 107.2 | M39: 107.2 | N39: A158704 | O39: PALIZA CAMAVILCA, JHOSSELYN JARUMY
A40: B B01-00007519 | B40: B B01-00007519 | C40: 46111 | D40: 46111 | E40: 1212001 FACTURAS POR COBRAR NACIONALES M.N. | F40: MENDOZA MARQUEZ, JONATHAN JEFF | G40: B B01-00007519 | I40: PEN | J40: 167.6 | K40: 167.6 | M40: 167.6 | N40: A158705 | O40: PALIZA CAMAVILCA, JHOSSELYN JARUMY
A41: B B01-00007518 | B41: B B01-00007518 | C41: 46111 | D41: 46111 | E41: 1212001 FACTURAS POR COBRAR NACIONALES M.N. | F41: IBAÑEZ CARRASCO, GRETHEL MARIA FERNANDA | G41: B B01-00007518 | I41: PEN | J41: 83.99 | K41: 83.99 | M41: 83.99 | O41: PALIZA CAMAVILCA, JHOSSELYN JARUMY
A42: B B01-00007517 | B42: B B01-00007517 | C42: 46111 | D42: 46111 | E42: 1212001 FACTURAS POR COBRAR NACIONALES M.N. | F42: ORDINOLA OSORIO, JUAN CARLOS | G42: B B01-00007517 | I42: PEN | J42: 128.25 | K42: 128.25 | M42: 128.25 | N42: A158706 | O42: PALIZA CAMAVILCA, JHOSSELYN JARUMY
A43: B B01-00007516 | B43: B B01-00007516 | C43: 46111 | D43: 46111 | E43: 1212001 FACTURAS POR COBRAR NACIONALES M.N. | F43: KALAFATOVICH CASTAÑEDA, NORMAN | G43: B B01-00007516 | I43: PEN | J43: 128.25 | K43: 128.25 | M43: 128.25 | N43: A158707 | O43: PALIZA CAMAVILCA, JHOSSELYN JARUMY
A44: B B01-00007515 | B44: B B01-00007515 | C44: 46111 | D44: 46111 | E44: 1212001 FACTURAS POR COBRAR NACIONALES M.N. | F44: CISNEROS LUJAN, NOELIA MILAGROS | G44: B B01-00007515 | I44: PEN | J44: 76.72 | K44: 76.72 | M44: 76.72 | N44: A159026 | O44: PALIZA CAMAVILCA, JHOSSELYN JARUMY
A45: B B01-00007514 | B45: B B01-00007514 | C45: 46111 | D45: 46111 | E45: 1212001 FACTURAS POR COBRAR NACIONALES M.N. | F45: YUIJAN OROPEZ, LUIS ANTONIO | G45: B B01-00007514 | I45: PEN | J45: 145.79 | K45: 145.79 | M45: 145.79 | N45: A159029 | O45: PALIZA CAMAVILCA, JHOSSELYN JARUMY
A46: B B01-00007513 | B46: B B01-00007513 | C46: 46111 | D46: 46111 | E46: 1212001 FACTURAS POR COBRAR NACIONALES M.N. | F46: GRANDA DE LA CRUZ, EVELYN PATRICIA | G46: B B01-00007513 | I46: PEN | J46: 67.94 | K46: 67.94 | M46: 67.94 | N46: A159033 | O46: PALIZA CAMAVILCA, JHOSSELYN JARUMY
A47: B B01-00007512 | B47: B B01-00007512 | C47: 46111 | D47: 46111 | E47: 1212001 FACTURAS POR COBRAR NACIONALES M.N. | F47: TOCTO VALLEJOS, FRANS ADOLFO | G47: B B01-00007512 | I47: PEN | J47: 53.9 | K47: 53.9 | M47: 53.9 | O47: PALIZA CAMAVILCA, JHOSSELYN JARUMY
A48: B B01-00007511 | B48: B B01-00007511 | C48: 46111 | D48: 46111 | E48: 1212001 FACTURAS POR COBRAR NACIONALES M.N. | F48: ROSELL VARGAS, ANGELICA MARIA | G48: B B01-00007511 | I48: PEN | J48: 107.2 | K48: 107.2 | M48: 107.2 | N48: A159035 | O48: PALIZA CAMAVILCA, JHOSSELYN JARUMY
A49: B B01-00007510 | B49: B B01-00007510 | C49: 46111 | D49: 46111 | E49: 1212001 FACTURAS POR COBRAR NACIONALES M.N. | F49: AGUINAGA CORTEZ, CAROLA IZAMAR | G49: B B01-00007510 | I49: PEN | J49: 163.51 | K49: 163.51 | M49: 163.51 | N49: A159038 | O49: PALIZA CAMAVILCA, JHOSSELYN JARUMY
A50: B B01-00007509 | B50: B B01-00007509 | C50: 46111 | D50: 46111 | E50: 1212001 FACTURAS POR COBRAR NACIONALES M.N. | F50: RAMIREZ CARLOS, LUIS ARTURO | G50: B B01-00007509 | I50: PEN | J50: 51.2 | K50: 51.2 | M50: 51.2 | N50: A159041 | O50: PALIZA CAMAVILCA, JHOSSELYN JARUMY
A51: B B01-00007508 | B51: B B01-00007508 | C51: 46111 | D51: 46111 | E51: 1212001 FACTURAS POR COBRAR NACIONALES M.N. | F51: CALDERON NAVARRO, MARIA DE LOS ANGELES | G51: B B01-00007508 | I51: PEN | J51: 75.83 | K51: 75.83 | M51: 75.83 | N51: A159044 | O51: PALIZA CAMAVILCA, JHOSSELYN JARUMY
A52: B B01-00007507 | B52: B B01-00007507 | C52: 46111 | D52: 46111 | E52: 1212001 FACTURAS POR COBRAR NACIONALES M.N. | F52: ISIDRO GASPAR, DAYAN THANERR | G52: B B01-00007507 | I52: PEN | J52: 85.51 | K52: 85.51 | M52: 85.51 | N52: A159047 | O52: PALIZA CAMAVILCA, JHOSSELYN JARUMY
A53: B B01-00007506 | B53: B B01-00007506 | C53: 46111 | D53: 46111 | E53: 1212001 FACTURAS POR COBRAR NACIONALES M.N. | F53: CAMPOS ROJAS, MILAGROS NATY | G53: B B01-00007506 | I53: PEN | J53: 53.9 | K53: 53.9 | M53: 53.9 | N53: A159049 | O53: PALIZA CAMAVILCA, JHOSSELYN JARUMY
A54: B B01-00007505 | B54: B B01-00007505 | C54: 46111 | D54: 46111 | E54: 1212001 FACTURAS POR COBRAR NACIONALES M.N. | F54: ISIDRO GASPAR, DAYAN THANERR | G54: B B01-00007505 | I54: PEN | J54: 62 | K54: 62 | M54: 62 | N54: A159052 | O54: PALIZA CAMAVILCA, JHOSSELYN JARUMY
A55: B B01-00007504 | B55: B B01-00007504 | C55: 46111 | D55: 46111 | E55: 1212001 FACTURAS POR COBRAR NACIONALES M.N. | F55: CASTRO DIAZ, ERICK CRISTHIAN | G55: B B01-00007504 | I55: PEN | J55: 117.1 | K55: 117.1 | M55: 117.1 | N55: A159054 | O55: PALIZA CAMAVILCA, JHOSSELYN JARUMY
A56: F F01-00005131 | B56: F F01-00005131 | C56: 46108 | D56: 46153 | E56: 1212001 FACTURAS POR COBRAR NACIONALES M.N. | F56: ADERVET S.A.C | G56: F F01-00005131 | I56: PEN | J56: 8640.43 | K56: 8640.43 | M56: 8640.43 | N56: A153417 | O56: PALIZA CAMAVILCA, JHOSSELYN JARUMY
A57: B B01-00007486 | B57: B B01-00007486 | C57: 46108 | D57: 46108 | E57: 1212001 FACTURAS POR COBRAR NACIONALES M.N. | F57: ASCENZO BATTISTINI, VANESSA MARGARITA | G57: B B01-00007486 | I57: PEN | J57: 93.49 | K57: 93.49 | M57: 93.49 | N57: A159007 | O57: PALIZA CAMAVILCA, JHOSSELYN JARUMY
A58: B B01-00007485 | B58: B B01-00007485 | C58: 46108 | D58: 46108 | E58: 1212001 FACTURAS POR COBRAR NACIONALES M.N. | F58: SOLANO VASQUEZ, MARIA DEL PILAR | G58: B B01-00007485 | I58: PEN | J58: 325.46 | K58: 325.46 | M58: 325.46 | N58: A158579 | O58: PALIZA CAMAVILCA, JHOSSELYN JARUMY
A59: B B01-00007483 | B59: B B01-00007483 | C59: 46108 | D59: 46108 | E59: 1212001 FACTURAS POR COBRAR NACIONALES M.N. | F59: HIGA HENNA, MITSUO ANDRES | G59: B B01-00007483 | I59: PEN | J59: 128.25 | K59: 128.25 | M59: 128.25 | N59: A158588 | O59: PALIZA CAMAVILCA, JHOSSELYN JARUMY
A60: B B01-00007481 | B60: B B01-00007481 | C60: 46108 | D60: 46108 | E60: 1212001 FACTURAS POR COBRAR NACIONALES M.N. | F60: CHAPILLIQUEN HUAMAN, VANESSA ELIZABETH | G60: B B01-00007481 | I60: PEN | J60: 54.52 | K60: 54.52 | M60: 54.52 | O60: PALIZA CAMAVILCA, JHOSSELYN JARUMY
A61: F F01-00005122 | B61: F F01-00005122 | C61: 46107 | D61: 46182 | E61: 1212001 FACTURAS POR COBRAR NACIONALES M.N. | F61: AGROPEC SOCIEDAD COMERCIAL DE RESPONSABILIDAD LIMITADA | G61: F F01-00005122 | I61: PEN | J61: 8027.72 | K61: 8027.72 | M61: 8027.72 | N61: A144560 | O61: PALIZA CAMAVILCA, JHOSSELYN JARUMY
A62: F F01-00005121 | B62: F F01-00005121 | C62: 46107 | D62: 46137 | E62: 1212001 FACTURAS POR COBRAR NACIONALES M.N. | F62: ROFRAN E.I.R.L. | G62: F F01-00005121 | I62: PEN | J62: 2001.87 | K62: 2001.87 | M62: 2001.87 | N62: A147015 | O62: PALIZA CAMAVILCA, JHOSSELYN JARUMY
A63: F F01-00005117 | B63: F F01-00005117 | C63: 46107 | D63: 46137 | E63: 1212001 FACTURAS POR COBRAR NACIONALES M.N. | F63: AGROPECUARIA LA PROVIDENCIA SAC | G63: F F01-00005117 | I63: PEN | J63: 3853.43 | K63: 3853.43 | M63: 3853.43 | N63: A147395 | O63: PALIZA CAMAVILCA, JHOSSELYN JARUMY
A64: F F01-00005112 | B64: F F01-00005112 | C64: 46107 | D64: 46137 | E64: 1212001 FACTURAS POR COBRAR NACIONALES M.N. | F64: GRANJAS AMAZONICAS S.A.C | G64: F F01-00005112 | I64: PEN | J64: 1223.98 | K64: 1223.98 | M64: 1223.98 | N64: A145505 | O64: PALIZA CAMAVILCA, JHOSSELYN JARUMY
A65: F F01-00005111 | B65: F F01-00005111 | C65: 46107 | D65: 46107 | E65: 1212001 FACTURAS POR COBRAR NACIONALES M.N. | F65: BALAREZO DEL VALLE RAY ERICK | G65: F F01-00005111 | I65: PEN | J65: 65.7 | K65: 65.7 | M65: 65.7 | N65: A158570 | O65: PALIZA CAMAVILCA, JHOSSELYN JARUMY
A66: F F01-00005108 | B66: F F01-00005108 | C66: 46107 | D66: 46137 | E66: 1212001 FACTURAS POR COBRAR NACIONALES M.N. | F66: GRANJAS AMAZONICAS S.A.C | G66: F F01-00005108 | I66: PEN | J66: 4129.06 | K66: 4129.06 | M66: 4129.06 | N66: A145504 | O66: PALIZA CAMAVILCA, JHOSSELYN JARUMY
A67: F F01-00005101 | B67: F F01-00005101 | C67: 46107 | D67: 46137 | E67: 1212001 FACTURAS POR COBRAR NACIONALES M.N. | F67: GRUPO VETERINARIO ADF S.A.C. | G67: F F01-00005101 | I67: PEN | J67: 1174.1 | K67: 1174.1 | M67: 1174.1 | N67: A147016 | O67: PALIZA CAMAVILCA, JHOSSELYN JARUMY
A68: F F01-00005099 | B68: F F01-00005099 | C68: 46107 | D68: 46107 | E68: 1212001 FACTURAS POR COBRAR NACIONALES M.N. | F68: TAI LOY S.A. | G68: F F01-00005099 | I68: PEN | J68: 71.83 | K68: 71.83 | M68: 71.83 | O68: PALIZA CAMAVILCA, JHOSSELYN JARUMY
A69: F F01-00005098 | B69: F F01-00005098 | C69: 46107 | D69: 46122 | E69: 1212001 FACTURAS POR COBRAR NACIONALES M.N. | F69: FIR LOGISTICS S.A.C. | G69: F F01-00005098 | I69: USD | J69: 494.42 | K69: 1714.65 | M69: 1714.65 | N69: A156077 | O69: PALIZA CAMAVILCA, JHOSSELYN JARUMY
A70: BBVA1/2025/05434 | B70: BBVA1/2025/05434 | C70: 46107 | E70: 1212001 FACTURAS POR COBRAR NACIONALES M.N. | F70: HUAMANI CARRASCO, ESTEFANI MILAGROS | G70: B B01-00007716 | I70: PEN | J70: -19.47 | L70: 19.47 | M70: -19.47 | N70: A144294 | O70: BARCENA BRAGA, KATTYA ADELAIDA
A71: B B01-00007465 | B71: B B01-00007465 | C71: 46107 | D71: 46107 | E71: 1212001 FACTURAS POR COBRAR NACIONALES M.N. | F71: VELIZ SERQUEN, MARIBEL MARGOT | G71: B B01-00007465 | I71: PEN | J71: 53.9 | K71: 53.9 | M71: 53.9 | N71: A158995 | O71: PALIZA CAMAVILCA, JHOSSELYN JARUMY
A72: B B01-00007464 | B72: B B01-00007464 | C72: 46107 | D72: 46107 | E72: 1212001 FACTURAS POR COBRAR NACIONALES M.N. | F72: ANTAURCO JARA, MARCOS WALDIR | G72: B B01-00007464 | I72: PEN | J72: 533.68 | K72: 533.68 | M72: 533.68 | N72: A158572 | O72: PALIZA CAMAVILCA, JHOSSELYN JARUMY
A73: B B01-00007463 | B73: B B01-00007463 | C73: 46107 | D73: 46107 | E73: 1212001 FACTURAS POR COBRAR NACIONALES M.N. | F73: HAMADA JACINTO, CAROLYN HIROMI | G73: B B01-00007463 | I73: PEN | J73: 107.2 | K73: 107.2 | M73: 107.2 | N73: A158997 | O73: PALIZA CAMAVILCA, JHOSSELYN JARUMY
A74: B B01-00007462 | B74: B B01-00007462 | C74: 46107 | D74: 46107 | E74: 1212001 FACTURAS POR COBRAR NACIONALES M.N. | F74: HUAMANCHUMO TORRES, JOSE RICARDO | G74: B B01-00007462 | I74: PEN | J74: 62 | K74: 62 | M74: 62 | N74: A158999 | O74: PALIZA CAMAVILCA, JHOSSELYN JARUMY
A75: B B01-00007458 | B75: B B01-00007458 | C75: 46107 | D75: 46107 | E75: 1212001 FACTURAS POR COBRAR NACIONALES M.N. | F75: ZUBIA GONZALES, JOSE DIEGO | G75: B B01-00007458 | I75: PEN | J75: 39.51 | K75: 39.51 | M75: 39.51 | N75: A158573 | O75: PALIZA CAMAVILCA, JHOSSELYN JARUMY
A76: B B01-00007456 | B76: B B01-00007456 | C76: 46107 | D76: 46107 | E76: 1212001 FACTURAS POR COBRAR NACIONALES M.N. | F76: NAVARRETE RIVERA, LUIS RODRIGO | G76: B B01-00007456 | I76: PEN | J76: 53.91 | K76: 53.91 | M76: 53.91 | N76: A158575 | O76: PALIZA CAMAVILCA, JHOSSELYN JARUMY
A77: B B01-00007455 | B77: B B01-00007455 | C77: 46107 | D77: 46107 | E77: 1212001 FACTURAS POR COBRAR NACIONALES M.N. | F77: CHIAN LEE, SOFIA VICTORIA MELISSA | G77: B B01-00007455 | I77: PEN | J77: 48.41 | K77: 48.41 | M77: 48.41 | O77: PALIZA CAMAVILCA, JHOSSELYN JARUMY
A78: B B01-00007454 | B78: B B01-00007454 | C78: 46107 | D78: 46107 | E78: 1212001 FACTURAS POR COBRAR NACIONALES M.N. | F78: ROSILLO MENDOZA, ORNELLA JULLIANA | G78: B B01-00007454 | I78: PEN | J78: 106.65 | K78: 106.65 | M78: 106.65 | N78: A159001 | O78: PALIZA CAMAVILCA, JHOSSELYN JARUMY
A79: B B01-00007453 | B79: B B01-00007453 | C79: 46107 | D79: 46107 | E79: 1212001 FACTURAS POR COBRAR NACIONALES M.N. | F79: PILLACA TANTA, GINA FIORELA | G79: B B01-00007453 | I79: PEN | J79: 198.9 | K79: 198.9 | M79: 198.9 | N79: A159002 | O79: PALIZA CAMAVILCA, JHOSSELYN JARUMY
A80: B B01-00007452 | B80: B B01-00007452 | C80: 46107 | D80: 46107 | E80: 1212001 FACTURAS POR COBRAR NACIONALES M.N. | F80: CARRASCO CRIADO, SERGIO FERNANDO | G80: B B01-00007452 | I80: PEN | J80: 85.51 | K80: 85.51 | M80: 85.51 | N80: A159004 | O80: PALIZA CAMAVILCA, JHOSSELYN JARUMY
A81: F F01-00005096 | B81: F F01-00005096 | C81: 46106 | D81: 46196 | E81: 1212001 FACTURAS POR COBRAR NACIONALES M.N. | F81: ACVET PERU E.I.R.L. | G81: F F01-00005096 | I81: PEN | J81: 1593.15 | K81: 1593.15 | M81: 1593.15 | O81: PALIZA CAMAVILCA, JHOSSELYN JARUMY
A82: F F01-00005094 | B82: F F01-00005094 | C82: 46106 | D82: 46136 | E82: 1212001 FACTURAS POR COBRAR NACIONALES M.N. | F82: FIDO`S VET SRL | G82: F F01-00005094 | I82: PEN | J82: 2919.91 | K82: 2919.91 | M82: 2919.91 | N82: A149131 | O82: PALIZA CAMAVILCA, JHOSSELYN JARUMY
A83: F F01-00005088 | B83: F F01-00005088 | C83: 46106 | D83: 46136 | E83: 1212001 FACTURAS POR COBRAR NACIONALES M.N. | F83: GRUPO VETERINARIO ADF S.A.C. | G83: F F01-00005088 | I83: PEN | J83: 3584.84 | K83: 3584.84 | M83: 3584.84 | N83: A147026 | O83: PALIZA CAMAVILCA, JHOSSELYN JARUMY
A84: F F01-00005087 | B84: F F01-00005087 | C84: 46106 | D84: 46136 | E84: 1212001 FACTURAS POR COBRAR NACIONALES M.N. | F84: VITAL PETS SOCIEDAD ANONIMA CERRADA - VITAL PETS S.A.C. | G84: F F01-00005087 | I84: PEN | J84: 1408.92 | K84: 1408.92 | M84: 1408.92 | N84: A146614 | O84: PALIZA CAMAVILCA, JHOSSELYN JARUMY
A85: F F01-00005086 | B85: F F01-00005086 | C85: 46106 | D85: 46166 | E85: 1212001 FACTURAS POR COBRAR NACIONALES M.N. | F85: DISTRIBUCIONES AGROVET GRANDEZ TARAPOTO S.R.L. | G85: F F01-00005086 | I85: PEN | J85: 4014.15 | K85: 4014.15 | M85: 4014.15 | N85: A140116 | O85: PALIZA CAMAVILCA, JHOSSELYN JARUMY
A86: F F01-00005085 | B86: F F01-00005085 | C86: 46106 | D86: 46136 | E86: 1212001 FACTURAS POR COBRAR NACIONALES M.N. | F86: MASCOTAS PERUANAS S.A.C. | G86: F F01-00005085 | I86: PEN | J86: 3651.15 | K86: 3651.15 | M86: 3651.15 | N86: A147014 | O86: PALIZA CAMAVILCA, JHOSSELYN JARUMY
A87: F F01-00005080 | B87: F F01-00005080 | C87: 46106 | D87: 46151 | E87: 1212001 FACTURAS POR COBRAR NACIONALES M.N. | F87: PET´S PLACE VETERINARIAS S.A.C | G87: F F01-00005080 | I87: PEN | J87: 1257.88 | K87: 1257.88 | M87: 1257.88 | N87: A149272 | O87: PALIZA CAMAVILCA, JHOSSELYN JARUMY
A88: F F01-00005078 | B88: F F01-00005078 | C88: 46106 | D88: 46151 | E88: 1212001 FACTURAS POR COBRAR NACIONALES M.N. | F88: SERVICIOS VETERINARIOS ESPECIALIZADOS S.A.C. | G88: F F01-00005078 | I88: PEN | J88: 1373.52 | K88: 1373.52 | M88: 1373.52 | N88: A151146 | O88: PALIZA CAMAVILCA, JHOSSELYN JARUMY
A89: F F01-00005076 | B89: F F01-00005076 | C89: 46106 | D89: 46136 | E89: 1212001 FACTURAS POR COBRAR NACIONALES M.N. | F89: MAPEVAS SOCIEDAD ANONIMA CERRADA - MAPEVAS S.A.C. | G89: F F01-00005076 | I89: PEN | J89: 1408.92 | K89: 1408.92 | M89: 1408.92 | N89: A149119 | O89: PALIZA CAMAVILCA, JHOSSELYN JARUMY
A90: F F01-00005071 | B90: F F01-00005071 | C90: 46106 | D90: 46136 | E90: 1212001 FACTURAS POR COBRAR NACIONALES M.N. | F90: DERMIVET S.A.C. | G90: F F01-00005071 | I90: PEN | J90: 792.37 | K90: 792.37 | M90: 792.37 | N90: A147868 | O90: PALIZA CAMAVILCA, JHOSSELYN JARUMY
A91: F F01-00005070 | B91: F F01-00005070 | C91: 46106 | D91: 46106 | E91: 1212001 FACTURAS POR COBRAR NACIONALES M.N. | F91: BIDASSOA S.A.C. | G91: F F01-00005070 | I91: PEN | J91: 71.9 | K91: 71.9 | M91: 71.9 | N91: A158988 | O91: PALIZA CAMAVILCA, JHOSSELYN JARUMY
A92: E B01-00000351 | B92: E B01-00000351 | C92: 46106 | D92: 46106 | E92: 1212001 FACTURAS POR COBRAR NACIONALES M.N. | F92: VARIOS | G92: E B01-00000351 | I92: PEN | J92: 118 | K92: 118 | M92: 118 | N92: A150763 | O92: PALIZA CAMAVILCA, JHOSSELYN JARUMY
A93: B B01-00007443 | B93: B B01-00007443 | C93: 46106 | D93: 46106 | E93: 1212001 FACTURAS POR COBRAR NACIONALES M.N. | F93: REYES BARRIENTOS, ARIANA FRANCESCA | G93: B B01-00007443 | I93: PEN | J93: 128.24 | K93: 128.24 | M93: 128.24 | N93: A158990 | O93: PALIZA CAMAVILCA, JHOSSELYN JARUMY
A94: B B01-00007439 | B94: B B01-00007439 | C94: 46106 | D94: 46106 | E94: 1212001 FACTURAS POR COBRAR NACIONALES M.N. | F94: VALENZUELA GARCIA, ANTHONNY RHODAZ | G94: B B01-00007439 | I94: PEN | J94: 107.2 | K94: 107.2 | M94: 107.2 | N94: A158992 | O94: PALIZA CAMAVILCA, JHOSSELYN JARUMY
A95: B B01-00007434 (151034115739) | B95: B B01-00007434 | C95: 46106 | D95: 46106 | E95: 1212001 FACTURAS POR COBRAR NACIONALES M.N. | F95: ROQUEZ MATOS, ANDREA GABRIELA | G95: B B01-00007434 | H95: 151034115739 | I95: PEN | J95: 204.35 | K95: 204.35 | M95: 204.35 | N95: A158566 | O95: PALIZA CAMAVILCA, JHOSSELYN JARUMY
A96: B B01-00007433 (2000012199222051-656693277) | B96: B B01-00007433 | C96: 46106 | D96: 46106 | E96: 1212001 FACTURAS POR COBRAR NACIONALES M.N. | F96: LA ROSA MASSA, GONZALO | G96: B B01-00007433 | H96: 2000012199222051-656693277 | I96: PEN | J96: 107.81 | K96: 107.81 | M96: 107.81 | N96: A158568 | O96: PALIZA CAMAVILCA, JHOSSELYN JARUMY
A97: B B01-00007432 | B97: B B01-00007432 | C97: 46106 | D97: 46106 | E97: 1212001 FACTURAS POR COBRAR NACIONALES M.N. | F97: ALVARADO BATTISTOLO, CARLOS ABEL | G97: B B01-00007432 | I97: PEN | J97: 106.65 | K97: 106.65 | M97: 106.65 | N97: A158994 | O97: PALIZA CAMAVILCA, JHOSSELYN JARUMY
A98: B B01-00007431 | B98: B B01-00007431 | C98: 46106 | D98: 46106 | E98: 1212001 FACTURAS POR COBRAR NACIONALES M.N. | F98: YATACO YATACO, JUSTIN JUNIOR | G98: B B01-00007431 | I98: PEN | J98: 74.8 | K98: 74.8 | M98: 74.8 | N98: A158327 | O98: PALIZA CAMAVILCA, JHOSSELYN JARUMY
A99: B B01-00007430 (2000012196576955-656693277) | B99: B B01-00007430 | C99: 46106 | D99: 46106 | E99: 1212001 FACTURAS POR COBRAR NACIONALES M.N. | F99: LAZARTE GOMEZ, SANDRA MONICA | G99: B B01-00007430 | H99: 2000012196576955-656693277 | I99: PEN | J99: 64 | K99: 64 | M99: 64 | N99: A158569 | O99: PALIZA CAMAVILCA, JHOSSELYN JARUMY
A100: F F01-00005066 | B100: F F01-00005066 | C100: 46105 | D100: 46150 | E100: 1212001 FACTURAS POR COBRAR NACIONALES M.N. | F100: CAVERO & COCHELLA INVERSIONES S.A.C. | G100: F F01-00005066 | I100: PEN | J100: 1021.88 | K100: 1021.88 | M100: 1021.88 | N100: A150590 | O100: PALIZA CAMAVILCA, JHOSSELYN JARUMY
...

Sheet 1212xx2
A1: Asiento contable | B1: Número | C1: Fecha | D1: Fecha de vencimiento | E1: Cuenta | F1: Socio | G1: Etiqueta | H1: Referencia | I1: Moneda | J1: Importe en moneda | K1: Debe | L1: Haber | M1: Saldo | N1: Conciliación | O1: Creado por
A2: 1212002 FACTURAS POR COBRAR NACIONALES M.E. (94)
A3: CAMBI/2026/03/1722 (Ajuste diferencia cambio No realizada) | B3: CAMBI/2026/03/1722 | C3: 46112 | E3: 1212002 FACTURAS POR COBRAR NACIONALES M.E. | G3: Ajuste diferencia cambio No realizada | H3: Ajuste diferencia cambio No realizada | I3: USD | L3: 7705.43 | M3: -7705.43 | N3: A158607 | O3: BACKOFIS
A4: CAMBI/2026/03/1225 (Ajuste diferencia cambio No realizada) | B4: CAMBI/2026/03/1225 | C4: 46082 | E4: 1212002 FACTURAS POR COBRAR NACIONALES M.E. | G4: Ajuste diferencia cambio No realizada | H4: Ajuste diferencia cambio No realizada | I4: USD | K4: 11558.16 | M4: 11558.16 | N4: A152905 | O4: BACKOFIS
A5: CAMBI/2026/02/1233 (Ajuste diferencia cambio No realizada) | B5: CAMBI/2026/02/1233 | C5: 46081 | E5: 1212002 FACTURAS POR COBRAR NACIONALES M.E. | G5: Ajuste diferencia cambio No realizada | H5: Ajuste diferencia cambio No realizada | I5: USD | L5: 11558.16 | M5: -11558.16 | N5: A152905 | O5: BACKOFIS
A6: BCP02/2025/02242 | B6: BCP02/2025/02242 | C6: 46073 | E6: 1212002 FACTURAS POR COBRAR NACIONALES M.E. | F6: SCHRYVER LOGISTICS DEL PERU S.A.C | G6: F F01-00003105 | I6: USD | J6: -760.82 | L6: 2560.92 | M6: -2560.92 | N6: A127181 | O6: BARCENA BRAGA, KATTYA ADELAIDA
A7: CAMBI/2026/02/1066 (Ajuste diferencia cambio No realizada) | B7: CAMBI/2026/02/1066 | C7: 46054 | E7: 1212002 FACTURAS POR COBRAR NACIONALES M.E. | G7: Ajuste diferencia cambio No realizada | H7: Ajuste diferencia cambio No realizada | I7: USD | K7: 11570.34 | M7: 11570.34 | N7: A143767 | O7: BACKOFIS
A8: CAMBI/2026/01/3238 (Ajuste diferencia cambio No realizada) | B8: CAMBI/2026/01/3238 | C8: 46053 | E8: 1212002 FACTURAS POR COBRAR NACIONALES M.E. | G8: Ajuste diferencia cambio No realizada | H8: Ajuste diferencia cambio No realizada | I8: USD | L8: 11570.34 | M8: -11570.34 | N8: A143767 | O8: BACKOFIS
A9: CAMBI/2026/01/1026 (Ajuste diferencia cambio No realizada) | B9: CAMBI/2026/01/1026 | C9: 46023 | E9: 1212002 FACTURAS POR COBRAR NACIONALES M.E. | G9: Ajuste diferencia cambio No realizada | H9: Ajuste diferencia cambio No realizada | I9: USD | K9: 11337.62 | M9: 11337.62 | N9: A129931 | O9: ISMAEL AVILA
A10: CAMBI/2025/12/2426 (Ajuste diferencia cambio No realizada) | B10: CAMBI/2025/12/2426 | C10: 46022 | E10: 1212002 FACTURAS POR COBRAR NACIONALES M.E. | G10: Ajuste diferencia cambio No realizada | H10: Ajuste diferencia cambio No realizada | I10: USD | L10: 11337.62 | M10: -11337.62 | N10: A129931 | O10: ISMAEL AVILA
A11: PAPANT/2025/06381 (F F01-00003961) | B11: PAPANT/2025/06381 | C11: 46021 | D11: 46021 | E11: 1212002 FACTURAS POR COBRAR NACIONALES M.E. | F11: GARCIA FIESTAS JOSE AURELIO-10105455629 | G11: Pago de cliente $ 860.00 - GARCIA FIESTAS JOSE AURELIO-10105455629 - 30/12/2025 | H11: F F01-00003961 | I11: USD | J11: -860 | L11: 2899.92 | M11: -2899.92 | N11: A113746 | O11: ISMAEL AVILA
A12: F F01-00003961 | B12: F F01-00003961 | C12: 46021 | D12: 46021 | E12: 1212002 FACTURAS POR COBRAR NACIONALES M.E. | F12: GARCIA FIESTAS JOSE AURELIO-10105455629 | G12: F F01-00003961 | I12: USD | J12: 860 | K12: 2899.92 | M12: 2899.92 | N12: A113746 | O12: MATTO ASTETE, AUGUSTO WALTER
A13: CAMBI/2025/12/2425 (Ajuste diferencia cambio No realizada) | B13: CAMBI/2025/12/2425 | C13: 45992 | E13: 1212002 FACTURAS POR COBRAR NACIONALES M.E. | G13: Ajuste diferencia cambio No realizada | H13: Ajuste diferencia cambio No realizada | I13: USD | K13: 11366.71 | M13: 11366.71 | N13: A129874 | O13: ISMAEL AVILA
A14: PAPANT/2025/06375 (F F01-00003399) | B14: PAPANT/2025/06375 | C14: 45991 | D14: 45991 | E14: 1212002 FACTURAS POR COBRAR NACIONALES M.E. | F14: GARCIA FIESTAS JOSE AURELIO-10105455629 | G14: Pago de cliente $ 860.00 - GARCIA FIESTAS JOSE AURELIO-10105455629 - 30/11/2025 | H14: F F01-00003399 | I14: USD | J14: -860 | L14: 2896.48 | M14: -2896.48 | N14: A113733 | O14: ISMAEL AVILA
A15: F F01-00003399 | B15: F F01-00003399 | C15: 45991 | D15: 45991 | E15: 1212002 FACTURAS POR COBRAR NACIONALES M.E. | F15: GARCIA FIESTAS JOSE AURELIO-10105455629 | G15: F F01-00003399 | I15: USD | J15: 860 | K15: 2896.48 | M15: 2896.48 | N15: A113733 | O15: PALIZA CAMAVILCA, JHOSSELYN JARUMY
A16: CAMBI/2025/11/1649 (Ajuste diferencia cambio No realizada) | B16: CAMBI/2025/11/1649 | C16: 45991 | E16: 1212002 FACTURAS POR COBRAR NACIONALES M.E. | G16: Ajuste diferencia cambio No realizada | H16: Ajuste diferencia cambio No realizada | I16: USD | L16: 11366.71 | M16: -11366.71 | N16: A129874 | O16: ISMAEL AVILA
A17: F F01-00003105 | B17: F F01-00003105 | C17: 45973 | D17: 46003 | E17: 1212002 FACTURAS POR COBRAR NACIONALES M.E. | F17: SCHRYVER LOGISTICS DEL PERU S.A.C | G17: F F01-00003105 | I17: USD | J17: 760.82 | K17: 2560.92 | M17: 2560.92 | N17: A127181 | O17: PALIZA CAMAVILCA, JHOSSELYN JARUMY
A18: CAMBI/2025/11/1548 (Ajuste diferencia cambio No realizada) | B18: CAMBI/2025/11/1548 | C18: 45962 | E18: 1212002 FACTURAS POR COBRAR NACIONALES M.E. | G18: Ajuste diferencia cambio No realizada | H18: Ajuste diferencia cambio No realizada | I18: USD | K18: 10934.93 | M18: 10934.93 | N18: A128787 | O18: ISMAEL AVILA
A19: CAMBI/2025/10/2481 (Ajuste diferencia cambio No realizada) | B19: CAMBI/2025/10/2481 | C19: 45961 | E19: 1212002 FACTURAS POR COBRAR NACIONALES M.E. | G19: Ajuste diferencia cambio No realizada | H19: Ajuste diferencia cambio No realizada | I19: USD | L19: 10934.93 | M19: -10934.93 | N19: A128787 | O19: ISMAEL AVILA
A20: PAPANT/2025/04984 (F F01-00002970) | B20: PAPANT/2025/04984 | C20: 45960 | D20: 45960 | E20: 1212002 FACTURAS POR COBRAR NACIONALES M.E. | F20: GARCIA FIESTAS JOSE AURELIO-10105455629 | G20: Pago de cliente $ 860.00 - GARCIA FIESTAS JOSE AURELIO-10105455629 - 30/10/2025 | H20: F F01-00002970 | I20: USD | J20: -860 | L20: 2918.84 | M20: -2918.84 | N20: A113848 | O20: ISMAEL AVILA
A21: F F01-00002970 | B21: F F01-00002970 | C21: 45960 | D21: 45960 | E21: 1212002 FACTURAS POR COBRAR NACIONALES M.E. | F21: GARCIA FIESTAS JOSE AURELIO-10105455629 | G21: F F01-00002970 | I21: USD | J21: 860 | K21: 2918.84 | M21: 2918.84 | N21: A113848 | O21: PALIZA CAMAVILCA, JHOSSELYN JARUMY
A22: CAMBI/2025/10/1938 (Ajuste diferencia cambio No realizada) | B22: CAMBI/2025/10/1938 | C22: 45931 | E22: 1212002 FACTURAS POR COBRAR NACIONALES M.E. | G22: Ajuste diferencia cambio No realizada | H22: Ajuste diferencia cambio No realizada | I22: USD | K22: 8328.67 | M22: 8328.67 | N22: A121029 | O22: ISMAEL AVILA
A23: PAPANT/2025/04334 (F F01-00002539) | B23: PAPANT/2025/04334 | C23: 45930 | D23: 45930 | E23: 1212002 FACTURAS POR COBRAR NACIONALES M.E. | F23: GARCIA FIESTAS JOSE AURELIO-10105455629 | G23: Pago de cliente $ 860.00 - GARCIA FIESTAS JOSE AURELIO-10105455629 - 30/09/2025 | H23: F F01-00002539 | I23: USD | J23: -860 | L23: 3005.7 | M23: -3005.7 | N23: A113847 | O23: ISMAEL AVILA
A24: F F01-00002539 | B24: F F01-00002539 | C24: 45930 | D24: 45930 | E24: 1212002 FACTURAS POR COBRAR NACIONALES M.E. | F24: GARCIA FIESTAS JOSE AURELIO-10105455629 | G24: F F01-00002539 | I24: USD | J24: 860 | K24: 3005.7 | M24: 3005.7 | N24: A113847 | O24: PALIZA CAMAVILCA, JHOSSELYN JARUMY
A25: CAMBI/2025/09/2074 (Ajuste diferencia cambio No realizada) | B25: CAMBI/2025/09/2074 | C25: 45930 | E25: 1212002 FACTURAS POR COBRAR NACIONALES M.E. | G25: Ajuste diferencia cambio No realizada | H25: Ajuste diferencia cambio No realizada | I25: USD | L25: 8328.67 | M25: -8328.67 | N25: A121029 | O25: ISMAEL AVILA
A26: CAMBI/2025/09/1961 (EXTORNO DIFERENCIA DE CAMBIO AGOSTO) | B26: CAMBI/2025/09/1961 | C26: 45901 | E26: 1212002 FACTURAS POR COBRAR NACIONALES M.E. | G26: EXTORNO DIFERENCIA DE CAMBIO AGOSTO | H26: EXTORNO DIFERENCIA DE CAMBIO AGOSTO | I26: USD | K26: 33.48 | M26: 33.48 | N26: A119725 | O26: ISMAEL AVILA
A27: CAMBI/2025/09/1797 (Ajuste diferencia cambio No realizada) | B27: CAMBI/2025/09/1797 | C27: 45901 | E27: 1212002 FACTURAS POR COBRAR NACIONALES M.E. | G27: Ajuste diferencia cambio No realizada | H27: Ajuste diferencia cambio No realizada | I27: USD | K27: 6425.48 | M27: 6425.48 | N27: A118927 | O27: ISMAEL AVILA
A28: CAMBI/2025/08/2388 (AJUSTE DE DIFERENCIA DE CAMBIO AGOSTO) | B28: CAMBI/2025/08/2388 | C28: 45900 | E28: 1212002 FACTURAS POR COBRAR NACIONALES M.E. | G28: AJUSTE DE DIFERENCIA DE CAMBIO AGOSTO | H28: AJUSTE DE DIFERENCIA DE CAMBIO AGOSTO | I28: USD | L28: 33.48 | M28: -33.48 | N28: A119725 | O28: ISMAEL AVILA
A29: CAMBI/2025/08/2378 (Ajuste diferencia cambio No realizada) | B29: CAMBI/2025/08/2378 | C29: 45900 | E29: 1212002 FACTURAS POR COBRAR NACIONALES M.E. | G29: Ajuste diferencia cambio No realizada | H29: Ajuste diferencia cambio No realizada | I29: USD | L29: 6425.48 | M29: -6425.48 | N29: A118927 | O29: ISMAEL AVILA
A30: PAPANT/2025/03696 (F F01-00002123) | B30: PAPANT/2025/03696 | C30: 45895 | D30: 45895 | E30: 1212002 FACTURAS POR COBRAR NACIONALES M.E. | F30: GARCIA FIESTAS JOSE AURELIO-10105455629 | G30: Pago de cliente $ 860.00 - GARCIA FIESTAS JOSE AURELIO-10105455629 - 26/08/2025 | H30: F F01-00002123 | I30: USD | J30: -860 | L30: 3036.66 | M30: -3036.66 | N30: A113846 | O30: ISMAEL AVILA
A31: F F01-00002123 | B31: F F01-00002123 | C31: 45895 | D31: 45895 | E31: 1212002 FACTURAS POR COBRAR NACIONALES M.E. | F31: GARCIA FIESTAS JOSE AURELIO-10105455629 | G31: F F01-00002123 | I31: USD | J31: 860 | K31: 3036.66 | M31: 3036.66 | N31: A113846 | O31: PALIZA CAMAVILCA, JHOSSELYN JARUMY
A32: CAMBI/2025/08/1883 (Ajuste diferencia cambio No realizada) | B32: CAMBI/2025/08/1883 | C32: 45870 | E32: 1212002 FACTURAS POR COBRAR NACIONALES M.E. | G32: Ajuste diferencia cambio No realizada | H32: Ajuste diferencia cambio No realizada | I32: USD | K32: 5003 | M32: 5003 | N32: A114311 | O32: ISMAEL AVILA
A33: CAMBI/2025/07/1286 (Ajuste diferencia cambio No realizada) | B33: CAMBI/2025/07/1286 | C33: 45869 | E33: 1212002 FACTURAS POR COBRAR NACIONALES M.E. | G33: Ajuste diferencia cambio No realizada | H33: Ajuste diferencia cambio No realizada | I33: USD | L33: 5003 | M33: -5003 | N33: A114311 | O33: ISMAEL AVILA
A34: PAPANT/2025/03688 (F F01-00001775) | B34: PAPANT/2025/03688 | C34: 45862 | D34: 45862 | E34: 1212002 FACTURAS POR COBRAR NACIONALES M.E. | F34: GARCIA FIESTAS JOSE AURELIO-10105455629 | G34: Pago de cliente $ 860.00 - GARCIA FIESTAS JOSE AURELIO-10105455629 - 24/07/2025 | H34: F F01-00001775 | I34: USD | J34: -860 | L34: 3062.46 | M34: -3062.46 | N34: A113841 | O34: ISMAEL AVILA
A35: F F01-00001775 | B35: F F01-00001775 | C35: 45862 | D35: 45862 | E35: 1212002 FACTURAS POR COBRAR NACIONALES M.E. | F35: GARCIA FIESTAS JOSE AURELIO-10105455629 | G35: F F01-00001775 | I35: USD | J35: 860 | K35: 3062.46 | M35: 3062.46 | N35: A113841 | O35: PALIZA CAMAVILCA, JHOSSELYN JARUMY
A36: CAMBI/2025/07/1421 (EXTORNO DIFERENCIA DE CAMBIO JUNIO) | B36: CAMBI/2025/07/1421 | C36: 45839 | E36: 1212002 FACTURAS POR COBRAR NACIONALES M.E. | G36: EXTORNO DIFERENCIA DE CAMBIO JUNIO | H36: EXTORNO DIFERENCIA DE CAMBIO JUNIO | I36: USD | K36: 299.64 | M36: 299.64 | N36: A122050 | O36: ISMAEL AVILA
A37: CAMBI/2025/07/1193 (Ajuste diferencia cambio No realizada) | B37: CAMBI/2025/07/1193 | C37: 45839 | E37: 1212002 FACTURAS POR COBRAR NACIONALES M.E. | G37: Ajuste diferencia cambio No realizada | H37: Ajuste diferencia cambio No realizada | I37: USD | K37: 6046.01 | M37: 6046.01 | N37: A114443 | O37: ISMAEL AVILA
A38: CAMBI/2025/06/2287 (AJUSTE DE DIFERENCIA DE CAMBIO JUNIO) | B38: CAMBI/2025/06/2287 | C38: 45838 | E38: 1212002 FACTURAS POR COBRAR NACIONALES M.E. | G38: AJUSTE DE DIFERENCIA DE CAMBIO JUNIO | H38: AJUSTE DE DIFERENCIA DE CAMBIO JUNIO | I38: USD | L38: 299.64 | M38: -299.64 | N38: A122050 | O38: ISMAEL AVILA
A39: CAMBI/2025/06/2154 (Ajuste diferencia cambio No realizada) | B39: CAMBI/2025/06/2154 | C39: 45838 | E39: 1212002 FACTURAS POR COBRAR NACIONALES M.E. | G39: Ajuste diferencia cambio No realizada | H39: Ajuste diferencia cambio No realizada | I39: USD | L39: 6046.01 | M39: -6046.01 | N39: A114443 | O39: ISMAEL AVILA
A40: PAPANT/2025/03679 (F F01-00001545) | B40: PAPANT/2025/03679 | C40: 45835 | D40: 45835 | E40: 1212002 FACTURAS POR COBRAR NACIONALES M.E. | F40: GARCIA FIESTAS JOSE AURELIO-10105455629 | G40: Pago de cliente $ 860.00 - GARCIA FIESTAS JOSE AURELIO-10105455629 - 27/06/2025 | H40: F F01-00001545 | I40: USD | J40: -860 | L40: 3071.92 | M40: -3071.92 | N40: A113804 | O40: ISMAEL AVILA
A41: F F01-00001545 | B41: F F01-00001545 | C41: 45835 | D41: 45835 | E41: 1212002 FACTURAS POR COBRAR NACIONALES M.E. | F41: GARCIA FIESTAS JOSE AURELIO-10105455629 | G41: F F01-00001545 | I41: USD | J41: 860 | K41: 3071.92 | M41: 3071.92 | N41: A113804 | O41: PALIZA CAMAVILCA, JHOSSELYN JARUMY
A42: CAMBI/2025/06/2285 (EXTORNO DE DIFERENCIA DE CAMBIO MAYO) | B42: CAMBI/2025/06/2285 | C42: 45809 | E42: 1212002 FACTURAS POR COBRAR NACIONALES M.E. | G42: EXTORNO DE DIFERENCIA DE CAMBIO MAYO | H42: EXTORNO DE DIFERENCIA DE CAMBIO MAYO | I42: USD | K42: 107.58 | M42: 107.58 | N42: A122004 | O42: ISMAEL AVILA
A43: CAMBI/2025/06/1914 (Ajuste diferencia cambio No realizada) | B43: CAMBI/2025/06/1914 | C43: 45809 | E43: 1212002 FACTURAS POR COBRAR NACIONALES M.E. | G43: Ajuste diferencia cambio No realizada | H43: Ajuste diferencia cambio No realizada | I43: USD | K43: 3773.46 | M43: 3773.46 | N43: A114347 | O43: ISMAEL AVILA
A44: CAMBI/2025/05/1306 (AJUSTE DE DIFERENCIA DE CAMBIO MAYO) | B44: CAMBI/2025/05/1306 | C44: 45808 | E44: 1212002 FACTURAS POR COBRAR NACIONALES M.E. | G44: AJUSTE DE DIFERENCIA DE CAMBIO MAYO | H44: AJUSTE DE DIFERENCIA DE CAMBIO MAYO | I44: USD | L44: 107.58 | M44: -107.58 | N44: A122004 | O44: ISMAEL AVILA
A45: CAMBI/2025/05/1256 (Ajuste diferencia cambio No realizada) | B45: CAMBI/2025/05/1256 | C45: 45808 | E45: 1212002 FACTURAS POR COBRAR NACIONALES M.E. | G45: Ajuste diferencia cambio No realizada | H45: Ajuste diferencia cambio No realizada | I45: USD | L45: 3773.46 | M45: -3773.46 | N45: A114347 | O45: ISMAEL AVILA
A46: PAPANT/2025/03676 (F F01-00001231) | B46: PAPANT/2025/03676 | C46: 45805 | D46: 45805 | E46: 1212002 FACTURAS POR COBRAR NACIONALES M.E. | F46: GARCIA FIESTAS JOSE AURELIO-10105455629 | G46: Pago de cliente $ 1,720.00 - GARCIA FIESTAS JOSE AURELIO-10105455629 - 28/05/2025 | H46: F F01-00001231 | I46: USD | J46: -1720 | L46: 6278 | M46: -6278 | N46: A113840 | O46: ISMAEL AVILA
A47: PAPANT/2025/03675 (F F01-00001230) | B47: PAPANT/2025/03675 | C47: 45805 | D47: 45805 | E47: 1212002 FACTURAS POR COBRAR NACIONALES M.E. | F47: GARCIA FIESTAS JOSE AURELIO-10105455629 | G47: Pago de cliente $ 860.00 - GARCIA FIESTAS JOSE AURELIO-10105455629 - 28/05/2025 | H47: F F01-00001230 | I47: USD | J47: -860 | L47: 3139 | M47: -3139 | N47: A113838 | O47: ISMAEL AVILA
A48: F F01-00001231 | B48: F F01-00001231 | C48: 45805 | D48: 45805 | E48: 1212002 FACTURAS POR COBRAR NACIONALES M.E. | F48: GARCIA FIESTAS JOSE AURELIO-10105455629 | G48: F F01-00001231 | I48: USD | J48: 1720 | K48: 6278 | M48: 6278 | N48: A113840 | O48: PALIZA CAMAVILCA, JHOSSELYN JARUMY
A49: F F01-00001230 | B49: F F01-00001230 | C49: 45805 | D49: 45805 | E49: 1212002 FACTURAS POR COBRAR NACIONALES M.E. | F49: GARCIA FIESTAS JOSE AURELIO-10105455629 | G49: F F01-00001230 | I49: USD | J49: 860 | K49: 3139 | M49: 3139 | N49: A113838 | O49: PALIZA CAMAVILCA, JHOSSELYN JARUMY
A50: PAPANT/2025/03670 (F F01-00001034) | B50: PAPANT/2025/03670 | C50: 45783 | D50: 45783 | E50: 1212002 FACTURAS POR COBRAR NACIONALES M.E. | F50: GARCIA FIESTAS JOSE AURELIO-10105455629 | G50: Pago de cliente $ 860.00 - GARCIA FIESTAS JOSE AURELIO-10105455629 - 06/05/2025 | H50: F F01-00001034 | I50: USD | J50: -860 | L50: 3149.32 | M50: -3149.32 | N50: A113835 | O50: ISMAEL AVILA
A51: F F01-00001034 | B51: F F01-00001034 | C51: 45783 | D51: 45783 | E51: 1212002 FACTURAS POR COBRAR NACIONALES M.E. | F51: GARCIA FIESTAS JOSE AURELIO-10105455629 | G51: F F01-00001034 | I51: USD | J51: 860 | K51: 3149.32 | M51: 3149.32 | N51: A113835 | O51: MATTO ASTETE, AUGUSTO WALTER
A52: CAMBI/2025/05/1308 (EXTORNO DE DIFERENCIA DE CAMBIO ABRIL) | B52: CAMBI/2025/05/1308 | C52: 45778 | E52: 1212002 FACTURAS POR COBRAR NACIONALES M.E. | G52: EXTORNO DE DIFERENCIA DE CAMBIO ABRIL | H52: EXTORNO DE DIFERENCIA DE CAMBIO ABRIL | I52: USD | K52: 6.1 | M52: 6.1 | N52: A122041 | O52: ISMAEL AVILA
A53: CAMBI/2025/05/1006 (Ajuste diferencia cambio No realizada) | B53: CAMBI/2025/05/1006 | C53: 45778 | E53: 1212002 FACTURAS POR COBRAR NACIONALES M.E. | G53: Ajuste diferencia cambio No realizada | H53: Ajuste diferencia cambio No realizada | I53: USD | K53: 2458.49 | M53: 2458.49 | N53: A110329 | O53: ISMAEL AVILA
A54: CAMBI/2025/04/1687 (AJUSTE DE DIFERENCIA DE CAMBIO ABRIL) | B54: CAMBI/2025/04/1687 | C54: 45777 | E54: 1212002 FACTURAS POR COBRAR NACIONALES M.E. | G54: AJUSTE DE DIFERENCIA DE CAMBIO ABRIL | H54: AJUSTE DE DIFERENCIA DE CAMBIO ABRIL | I54: USD | L54: 6.1 | M54: -6.1 | N54: A122041 | O54: ISMAEL AVILA
A55: CAMBI/2025/04/1651 (Ajuste diferencia cambio No realizada) | B55: CAMBI/2025/04/1651 | C55: 45777 | E55: 1212002 FACTURAS POR COBRAR NACIONALES M.E. | G55: Ajuste diferencia cambio No realizada | H55: Ajuste diferencia cambio No realizada | I55: USD | L55: 2458.49 | M55: -2458.49 | N55: A110329 | O55: ISMAEL AVILA
A56: CAMBI/2025/04/1685 (EXTORNO DE DIFERENCIA DE CAMBIO MARZO) | B56: CAMBI/2025/04/1685 | C56: 45748 | E56: 1212002 FACTURAS POR COBRAR NACIONALES M.E. | G56: EXTORNO DE DIFERENCIA DE CAMBIO MARZO | H56: EXTORNO DE DIFERENCIA DE CAMBIO MARZO | I56: USD | K56: 28.42 | M56: 28.42 | N56: A121996 | O56: ISMAEL AVILA
A57: CAMBI/2025/04/1627 (Ajuste diferencia cambio No realizada) | B57: CAMBI/2025/04/1627 | C57: 45748 | E57: 1212002 FACTURAS POR COBRAR NACIONALES M.E. | G57: Ajuste diferencia cambio No realizada | H57: Ajuste diferencia cambio No realizada | I57: USD | K57: 2747.79 | M57: 2747.79 | N57: A110328 | O57: ISMAEL AVILA
A58: PAPANT/2025/03663 (F F01-00000696) | B58: PAPANT/2025/03663 | C58: 45747 | D58: 45747 | E58: 1212002 FACTURAS POR COBRAR NACIONALES M.E. | F58: GARCIA FIESTAS JOSE AURELIO-10105455629 | G58: Pago de cliente $ 860.00 - GARCIA FIESTAS JOSE AURELIO-10105455629 - 31/03/2025 | H58: F F01-00000696 | I58: USD | J58: -860 | L58: 3142.44 | M58: -3142.44 | N58: A113827 | O58: ISMAEL AVILA
A59: F F01-00000696 | B59: F F01-00000696 | C59: 45747 | D59: 45747 | E59: 1212002 FACTURAS POR COBRAR NACIONALES M.E. | F59: GARCIA FIESTAS JOSE AURELIO-10105455629 | G59: F F01-00000696 | I59: USD | J59: 860 | K59: 3142.44 | M59: 3142.44 | N59: A113827 | O59: MATTO ASTETE, AUGUSTO WALTER
A60: CAMBI/2025/03/1457 (AJUSTE DE DIFERENCIA DE CAMBIO MARZO) | B60: CAMBI/2025/03/1457 | C60: 45747 | E60: 1212002 FACTURAS POR COBRAR NACIONALES M.E. | G60: AJUSTE DE DIFERENCIA DE CAMBIO MARZO | H60: AJUSTE DE DIFERENCIA DE CAMBIO MARZO | I60: USD | L60: 28.42 | M60: -28.42 | N60: A121996 | O60: ISMAEL AVILA
A61: CAMBI/2025/03/1398 (Ajuste diferencia cambio No realizada) | B61: CAMBI/2025/03/1398 | C61: 45747 | E61: 1212002 FACTURAS POR COBRAR NACIONALES M.E. | G61: Ajuste diferencia cambio No realizada | H61: Ajuste diferencia cambio No realizada | I61: USD | L61: 2747.79 | M61: -2747.79 | N61: A110328 | O61: ISMAEL AVILA
A62: CAMBI/2025/03/1459 (EXTORNO DE DIFERENCIA DE CAMBIO FEBRERO) | B62: CAMBI/2025/03/1459 | C62: 45717 | E62: 1212002 FACTURAS POR COBRAR NACIONALES M.E. | G62: EXTORNO DE DIFERENCIA DE CAMBIO FEBRERO | H62: EXTORNO DE DIFERENCIA DE CAMBIO FEBRERO | I62: USD | K62: 6.1 | M62: 6.1 | N62: A122042 | O62: ISMAEL AVILA
A63: CAMBI/2025/03/1396 (Ajuste diferencia cambio No realizada) | B63: CAMBI/2025/03/1396 | C63: 45717 | E63: 1212002 FACTURAS POR COBRAR NACIONALES M.E. | G63: Ajuste diferencia cambio No realizada | H63: Ajuste diferencia cambio No realizada | I63: USD | K63: 2458.49 | M63: 2458.49 | N63: A96154 | O63: ISMAEL AVILA
A64: PAPANT/2025/03654 (F F01-00000377) | B64: PAPANT/2025/03654 | C64: 45716 | D64: 45716 | E64: 1212002 FACTURAS POR COBRAR NACIONALES M.E. | F64: GARCIA FIESTAS JOSE AURELIO-10105455629 | G64: Pago de cliente $ 1,014.80 - GARCIA FIESTAS JOSE AURELIO-10105455629 - 28/02/2025 | H64: F F01-00000377 | I64: USD | J64: -1014.8 | L64: 3728.38 | M64: -3728.38 | N64: A113793 | O64: ISMAEL AVILA
A65: F F01-00000377 | B65: F F01-00000377 | C65: 45716 | D65: 45716 | E65: 1212002 FACTURAS POR COBRAR NACIONALES M.E. | F65: GARCIA FIESTAS JOSE AURELIO-10105455629 | G65: F F01-00000377 | I65: USD | J65: 1014.8 | K65: 3728.38 | M65: 3728.38 | N65: A113793 | O65: RIMARACHIN GALVEZ, JOEL JOSEPH
A66: CAMBI/2025/02/1494 (AJUSTE DE DIFERENCIA DE CAMBIO FEBRERO) | B66: CAMBI/2025/02/1494 | C66: 45716 | E66: 1212002 FACTURAS POR COBRAR NACIONALES M.E. | G66: AJUSTE DE DIFERENCIA DE CAMBIO FEBRERO | H66: AJUSTE DE DIFERENCIA DE CAMBIO FEBRERO | I66: USD | L66: 6.1 | M66: -6.1 | N66: A122042 | O66: ISMAEL AVILA
A67: CAMBI/2025/02/1481 (Ajuste diferencia cambio No realizada) | B67: CAMBI/2025/02/1481 | C67: 45716 | E67: 1212002 FACTURAS POR COBRAR NACIONALES M.E. | G67: Ajuste diferencia cambio No realizada | H67: Ajuste diferencia cambio No realizada | I67: USD | L67: 2458.49 | M67: -2458.49 | N67: A96154 | O67: ISMAEL AVILA
A68: F C01-00000064 | B68: F C01-00000064 | C68: 45709 | D68: 45709 | E68: 1212002 FACTURAS POR COBRAR NACIONALES M.E. | F68: HANKA OPERADOR LOGISTICO S.A.C. | I68: USD | J68: -281.78 | L68: 1065.41 | M68: -1065.41 | N68: A5344 | O68: MATTO ASTETE, AUGUSTO WALTER
A69: CAMBI/2025/02/0567 | B69: CAMBI/2025/02/0567 | C69: 45709 | E69: 1212002 FACTURAS POR COBRAR NACIONALES M.E. | F69: HANKA OPERADOR LOGISTICO S.A.C. | G69: Diferencia en tipo de cambio de moneda | I69: USD | K69: 6.48 | M69: 6.48 | N69: A5344 | O69: BARCENA BRAGA, KATTYA ADELAIDA
A70: PAPANT/2025/03548 (B B01-00000357) | B70: PAPANT/2025/03548 | C70: 45702 | D70: 45702 | E70: 1212002 FACTURAS POR COBRAR NACIONALES M.E. | F70: TAUCA TORRES, ALAN ARMANDO | G70: Pago de cliente $ 6,500.00 - TAUCA TORRES, ALAN ARMANDO - 14/02/2025 | H70: B B01-00000357 | I70: USD | J70: -6500 | L70: 24173.5 | M70: -24173.5 | N70: A58164 | O70: BARCENA BRAGA, KATTYA ADELAIDA
A71: B B01-00000357 | B71: B B01-00000357 | C71: 45702 | D71: 45702 | E71: 1212002 FACTURAS POR COBRAR NACIONALES M.E. | F71: TAUCA TORRES, ALAN ARMANDO | G71: B B01-00000357 | I71: USD | J71: 6500 | K71: 24173.5 | M71: 24173.5 | N71: A58164 | O71: MATTO ASTETE, AUGUSTO WALTER
A72: CAMBI/2025/02/1480 (Ajuste diferencia cambio No realizada) | B72: CAMBI/2025/02/1480 | C72: 45689 | E72: 1212002 FACTURAS POR COBRAR NACIONALES M.E. | G72: Ajuste diferencia cambio No realizada | H72: Ajuste diferencia cambio No realizada | I72: USD | K72: 1230.24 | M72: 1230.24 | N72: A110327 | O72: ISMAEL AVILA
A73: CAMBI/2025/01/0583 (Ajuste diferencia cambio No realizada) | B73: CAMBI/2025/01/0583 | C73: 45688 | E73: 1212002 FACTURAS POR COBRAR NACIONALES M.E. | G73: Ajuste diferencia cambio No realizada | H73: Ajuste diferencia cambio No realizada | I73: USD | L73: 1230.24 | M73: -1230.24 | N73: A110327 | O73: ISMAEL AVILA
A74: B C01-00000002 | B74: B C01-00000002 | C74: 45688 | D74: 45688 | E74: 1212002 FACTURAS POR COBRAR NACIONALES M.E. | F74: TAUCA TORRES, ALAN ARMANDO | I74: USD | J74: -6500 | L74: 24329.5 | M74: -24329.5 | N74: A29921 | O74: MATTO ASTETE, AUGUSTO WALTER
A75: B B01-00000091 | B75: B B01-00000091 | C75: 45686 | D75: 45686 | E75: 1212002 FACTURAS POR COBRAR NACIONALES M.E. | F75: TAUCA TORRES, ALAN ARMANDO | G75: B B01-00000091 | I75: USD | J75: 6500 | K75: 24329.5 | M75: 24329.5 | N75: A29921 | O75: MATTO ASTETE, AUGUSTO WALTER
A76: F010-00026476 | B76: F010-00026476 | C76: 45658 | D76: 45608 | E76: 1212002 FACTURAS POR COBRAR NACIONALES M.E. | F76: HANKA OPERADOR LOGISTICO S.A.C. | G76: F010-00026476 | I76: USD | J76: 281.78 | K76: 1058.93 | M76: 1058.93 | N76: A5344 | O76: BARCENA BRAGA, KATTYA ADELAIDA
A77: B010-00006448 | B77: B010-00006448 | C77: 45658 | D77: 43799 | E77: 1212002 FACTURAS POR COBRAR NACIONALES M.E. | F77: CALDERON OJEDA, JESUS WILFREDO | G77: B010-00006448 | I77: USD | J77: 789.42 | K77: 2966.64 | M77: 2966.64 | O77: BARCENA BRAGA, KATTYA ADELAIDA
A78: B010-00006447 | B78: B010-00006447 | C78: 45658 | D78: 43799 | E78: 1212002 FACTURAS POR COBRAR NACIONALES M.E. | F78: CALDERON OJEDA, JORGE UMBERTO | G78: B010-00006447 | I78: USD | J78: 1841.97 | K78: 6922.12 | M78: 6922.12 | O78: BARCENA BRAGA, KATTYA ADELAIDA
A79: B010-00006308 | B79: B010-00006308 | C79: 45658 | D79: 43769 | E79: 1212002 FACTURAS POR COBRAR NACIONALES M.E. | F79: CALDERON OJEDA, JORGE UMBERTO | G79: B010-00006308 | I79: USD | J79: 1873.72 | K79: 7041.44 | M79: 7041.44 | O79: BARCENA BRAGA, KATTYA ADELAIDA
A80: B010-00006307 | B80: B010-00006307 | C80: 45658 | D80: 43769 | E80: 1212002 FACTURAS POR COBRAR NACIONALES M.E. | F80: CALDERON OJEDA, JESUS WILFREDO | G80: B010-00006307 | I80: USD | J80: 803.03 | K80: 3017.79 | M80: 3017.79 | O80: BARCENA BRAGA, KATTYA ADELAIDA
A81: B010-00006158 | B81: B010-00006158 | C81: 45658 | D81: 43738 | E81: 1212002 FACTURAS POR COBRAR NACIONALES M.E. | F81: CALDERON OJEDA, JORGE UMBERTO | G81: B010-00006158 | I81: USD | J81: 1905.32 | K81: 7160.19 | M81: 7160.19 | O81: BARCENA BRAGA, KATTYA ADELAIDA
A82: B010-00006157 | B82: B010-00006157 | C82: 45658 | D82: 43738 | E82: 1212002 FACTURAS POR COBRAR NACIONALES M.E. | F82: CALDERON OJEDA, JESUS WILFREDO | G82: B010-00006157 | I82: USD | J82: 816.56 | K82: 3068.63 | M82: 3068.63 | O82: BARCENA BRAGA, KATTYA ADELAIDA
A83: B010-00005998 | B83: B010-00005998 | C83: 45658 | D83: 43708 | E83: 1212002 FACTURAS POR COBRAR NACIONALES M.E. | F83: CALDERON OJEDA, JORGE UMBERTO | G83: B010-00005998 | I83: USD | J83: 1936.76 | K83: 7278.34 | M83: 7278.34 | O83: BARCENA BRAGA, KATTYA ADELAIDA
A84: B010-00005997 | B84: B010-00005997 | C84: 45658 | D84: 43708 | E84: 1212002 FACTURAS POR COBRAR NACIONALES M.E. | F84: CALDERON OJEDA, JESUS WILFREDO | G84: B010-00005997 | I84: USD | J84: 830.04 | K84: 3119.29 | M84: 3119.29 | O84: BARCENA BRAGA, KATTYA ADELAIDA
A85: B010-00005857 | B85: B010-00005857 | C85: 45658 | D85: 43677 | E85: 1212002 FACTURAS POR COBRAR NACIONALES M.E. | F85: CALDERON OJEDA, JORGE UMBERTO | G85: B010-00005857 | I85: USD | J85: 1968.05 | K85: 7395.93 | M85: 7395.93 | O85: BARCENA BRAGA, KATTYA ADELAIDA
A86: B010-00005856 | B86: B010-00005856 | C86: 45658 | D86: 43677 | E86: 1212002 FACTURAS POR COBRAR NACIONALES M.E. | F86: CALDERON OJEDA, JESUS WILFREDO | G86: B010-00005856 | I86: USD | J86: 843.45 | K86: 3169.69 | M86: 3169.69 | O86: BARCENA BRAGA, KATTYA ADELAIDA
A87: B010-00005625 | B87: B010-00005625 | C87: 45658 | D87: 43644 | E87: 1212002 FACTURAS POR COBRAR NACIONALES M.E. | F87: CALDERON OJEDA, JESUS WILFREDO | G87: B010-00005625 | I87: USD | J87: 856.8 | K87: 3219.85 | M87: 3219.85 | O87: BARCENA BRAGA, KATTYA ADELAIDA
A88: B010-00005624 | B88: B010-00005624 | C88: 45658 | D88: 43644 | E88: 1212002 FACTURAS POR COBRAR NACIONALES M.E. | F88: CALDERON OJEDA, JORGE UMBERTO | G88: B010-00005624 | I88: USD | J88: 1999.19 | K88: 7512.96 | M88: 7512.96 | O88: BARCENA BRAGA, KATTYA ADELAIDA
... A96: B010-00005016 | B96: B010-00005016 | C96: 45658 | D96: 43524 | E96: 1212002 FACTURAS POR COBRAR NACIONALES M.E. | F96: CALDERON OJEDA, JESUS WILFREDO | G96: B010-00005016 | I96: USD | J96: 909.54 | K96: 3418.05 | M96: 3418.05 | O96: BARCENA BRAGA, KATTYA ADELAIDA
I98: USD | J98: =SUM(J3:J97) -> 28328.88 | M98: =SUM(M3:M97) -> 98754.48
I99: TC | J99: 3.486 | L99: =+J100-M98 -> -0.00432
I100: MN | J100: =+J98*J99 -> 98754.476

Sheet 1212xx3
A1: Asiento contable | B1: Número | C1: Fecha | D1: Fecha de vencimiento | E1: Cuenta | F1: Socio | G1: Etiqueta | H1: Referencia | I1: Moneda | J1: Importe en moneda | K1: Debe | L1: Haber | M1: Saldo | N1: Conciliación | O1: Creado por
A2: 1212003 FACTURAS POR COBRAR DEL EXTERIOR (2208)
A3: F F15-00000353 | B3: F F15-00000353 | C3: 46112 | D3: 46112 | E3: 1212003 FACTURAS POR COBRAR DEL EXTERIOR | F3: MONTECO S.A | G3: F F15-00000353 | I3: USD | J3: 207.38 | K3: 724.79 | M3: 724.79 | N3: A144647 | O3: PALIZA CAMAVILCA, JHOSSELYN JARUMY
A4: CAMBI/2026/03/1722 (Ajuste diferencia cambio No realizada) | B4: CAMBI/2026/03/1722 | C4: 46112 | E4: 1212003 FACTURAS POR COBRAR DEL EXTERIOR | G4: Ajuste diferencia cambio No realizada | H4: Ajuste diferencia cambio No realizada | I4: USD | K4: 296591.53 | M4: 296591.53 | N4: A158608 | O4: BACKOFIS
A5: F BILL/2026/03/1846 (APLICACION DE FT MKT COMO SALDO A FAVOR DE [...]) | B5: F BILL/2026/03/1846 | C5: 46107 | E5: 1212003 FACTURAS POR COBRAR DEL EXTERIOR | F5: MONTECO ANIMAL HEALTH S.A. DE C.V. | G5: F F15-00000287 | H5: APLICACION DE FT MKT COMO SALDO A FAVOR DE FT POR COBRAR DE MONTECO SV | I5: USD | J5: -38425.9 | L5: 133261.02 | M5: -133261.02 | O5: MONTERO VILCAS, JOSE GORGE
A6: CAMBI/2026/03/0903 | B6: CAMBI/2026/03/0903 | C6: 46107 | E6: 1212003 FACTURAS POR COBRAR DEL EXTERIOR | F6: MONTECO ANIMAL HEALTH S.A. DE C.V. | G6: Diferencia en tipo de cambio de moneda | I6: USD | K6: 3688.88 | M6: 3688.88 | O6: MONTERO VILCAS, JOSE GORGE
A7: F F15-00000347 | B7: F F15-00000347 | C7: 46098 | D7: 46143 | E7: 1212003 FACTURAS POR COBRAR DEL EXTERIOR | F7: GLOBALVET | G7: F F15-00000347 | I7: USD | J7: 9200 | K7: 31638.8 | M7: 31638.8 | O7: PARKER MENDOZA, VANESSA ALEXANDRA
A8: F D15-00000043 | B8: F D15-00000043 | C8: 46098 | D8: 46098 | E8: 1212003 FACTURAS POR COBRAR DEL EXTERIOR | F8: GLOBALVET | G8: F D15-00000043 | I8: USD | J8: 750 | K8: 2579.25 | M8: 2579.25 | O8: PALIZA CAMAVILCA, JHOSSELYN JARUMY
A9: F F15-00000345 | B9: F F15-00000345 | C9: 46094 | D9: 46184 | E9: 1212003 FACTURAS POR COBRAR DEL EXTERIOR | F9: GRUPO GRANDES ROMAN S.A. | G9: F F15-00000345 | I9: USD | J9: 157038.36 | K9: 541625.34 | M9: 541625.34 | O9: PARKER MENDOZA, VANESSA ALEXANDRA
A10: E B01-00000324 | B10: E B01-00000324 | C10: 46091 | D10: 46091 | E10: 1212003 FACTURAS POR COBRAR DEL EXTERIOR | F10: DYNTEC SPOL. S.R.O | G10: E B01-00000345 | I10: USD | J10: 9799.71 | K10: 34230.39 | M10: 34230.39 | N10: A158917 | O10: PALIZA CAMAVILCA, JHOSSELYN JARUMY
A11: F F15-00000340 | B11: F F15-00000340 | C11: 46087 | D11: 46132 | E11: 1212003 FACTURAS POR COBRAR DEL EXTERIOR | F11: MONTECO ANIMAL HEALTH S.A. DE C.V. | G11: F F15-00000340 | I11: USD | J11: 6873.6 | K11: 23590.2 | M11: 23590.2 | N11: A150402 | O11: PARKER MENDOZA, VANESSA ALEXANDRA
A12: F D15-00000042 | B12: F D15-00000042 | C12: 46087 | D12: 46087 | E12: 1212003 FACTURAS POR COBRAR DEL EXTERIOR | F12: MONTECO ANIMAL HEALTH S.A. DE C.V. | G12: F D15-00000042 | I12: USD | J12: 750 | K12: 2574 | M12: 2574 | N12: A150403 | O12: PALIZA CAMAVILCA, JHOSSELYN JARUMY
A13: E 001-00000430 | B13: E 001-00000430 | C13: 46073 | D13: 46073 | E13: 1212003 FACTURAS POR COBRAR DEL EXTERIOR | F13: MILIFAR SHPK | G13: E 001-00000430 | I13: USD | J13: 2 | K13: 6.73 | M13: 6.73 | O13: PARKER MENDOZA, VANESSA ALEXANDRA
A14: E 001-00000425 | B14: E 001-00000425 | C14: 46070 | D14: 46070 | E14: 1212003 FACTURAS POR COBRAR DEL EXTERIOR | F14: MY PETS VETERINARY CENTER W.L.L | G14: E 001-00000425 | I14: USD | J14: 4 | K14: 13.43 | M14: 13.43 | O14: PARKER MENDOZA, VANESSA ALEXANDRA
A15: CAMBI/2026/02/0132 | B15: CAMBI/2026/02/0132 | C15: 46056 | E15: 1212003 FACTURAS POR COBRAR DEL EXTERIOR | F15: UNIVET S.R.L. | G15: Diferencia en tipo de cambio de moneda | I15: USD | L15: 11.03 | M15: -11.03 | O15: MONTERO VILCAS, JOSE GORGE
A16: BCP02/2025/02147 | B16: BCP02/2025/02147 | C16: 46056 | E16: 1212003 FACTURAS POR COBRAR DEL EXTERIOR | F16: UNIVET S.R.L. | G16: F F15-00000285 | I16: USD | J16: -3675.71 | L16: 12383.47 | M16: -12383.47 | O16: MONTERO VILCAS, JOSE GORGE
A17: F F15-00000323 | B17: F F15-00000323 | C17: 46051 | D17: 46156 | E17: 1212003 FACTURAS POR COBRAR DEL EXTERIOR | F17: GRUPO COMERCIAL MONTECO S.A. | G17: F F15-00000323 | I17: USD | J17: 45315.6 | K17: 151580.68 | M17: 151580.68 | N17: A158872 | O17: PARKER MENDOZA, VANESSA ALEXANDRA
A18: F F15-00000323 | B18: F F15-00000323 | C18: 46051 | D18: 46171 | E18: 1212003 FACTURAS POR COBRAR DEL EXTERIOR | F18: GRUPO COMERCIAL MONTECO S.A. | G18: F F15-00000323 | I18: USD | J18: 45315.6 | K18: 151580.68 | M18: 151580.68 | O18: PARKER MENDOZA, VANESSA ALEXANDRA
A19: F F15-00000320 | B19: F F15-00000320 | C19: 46042 | D19: 46042 | E19: 1212003 FACTURAS POR COBRAR DEL EXTERIOR | F19: MONTECO S.A | G19: F F15-00000320 | I19: USD | J19: 19656 | K19: 66162.1 | M19: 66162.1 | O19: PARKER MENDOZA, VANESSA ALEXANDRA
A20: F F15-00000316 | B20: F F15-00000316 | C20: 46042 | D20: 46087 | E20: 1212003 FACTURAS POR COBRAR DEL EXTERIOR | F20: GRUPO GRANDES ROMAN S.A. | G20: F F15-00000316 | I20: USD | J20: 33566.8 | K20: 112985.87 | M20: 112985.87 | N20: A143463 | O20: PARKER MENDOZA, VANESSA ALEXANDRA
A21: F C15-00000040 | B21: F C15-00000040 | C21: 46024 | D21: 46024 | E21: 1212003 FACTURAS POR COBRAR DEL EXTERIOR | F21: GRUPO GRANDES ROMAN S.A. | I21: USD | J21: -296.4 | L21: 998.28 | M21: -998.28 | O21: PALIZA CAMAVILCA, JHOSSELYN JARUMY
A22: CAMBI/2026/01/0975 | B22: CAMBI/2026/01/0975 | C22: 46024 | E22: 1212003 FACTURAS POR COBRAR DEL EXTERIOR | F22: GRUPO GRANDES ROMAN S.A. | G22: Diferencia en tipo de cambio de moneda | I22: USD | L22: 1.18 | M22: -1.18 | O22: MONTERO VILCAS, JOSE GORGE
A23: F F15-00000307 | B23: F F15-00000307 | C23: 46022 | D23: 46142 | E23: 1212003 FACTURAS POR COBRAR DEL EXTERIOR | F23: UNIVET S.R.L. | G23: F F15-00000307 | I23: USD | J23: 355.2 | K23: 1196.67 | M23: 1196.67 | O23: PARKER MENDOZA, VANESSA ALEXANDRA
A24: F F15-00000307 | B24: F F15-00000307 | C24: 46022 | D24: 46127 | E24: 1212003 FACTURAS POR COBRAR DEL EXTERIOR | F24: UNIVET S.R.L. | G24: F F15-00000307 | I24: USD | J24: 355.2 | K24: 1196.67 | M24: 1196.67 | O24: PARKER MENDOZA, VANESSA ALEXANDRA
A25: F F15-00000299 | B25: F F15-00000299 | C25: 46021 | D25: 46141 | E25: 1212003 FACTURAS POR COBRAR DEL EXTERIOR | F25: GRUPO GRANDES ROMAN S.A. | G25: F F15-00000299 | I25: USD | J25: 158803.96 | K25: 535486.97 | M25: 535486.97 | O25: PARKER MENDOZA, VANESSA ALEXANDRA
A26: F F15-00000299 | B26: F F15-00000299 | C26: 46021 | D26: 46126 | E26: 1212003 FACTURAS POR COBRAR DEL EXTERIOR | F26: GRUPO GRANDES ROMAN S.A. | G26: F F15-00000299 | I26: USD | J26: 158803.97 | K26: 535486.97 | M26: 535486.97 | O26: PARKER MENDOZA, VANESSA ALEXANDRA
A27: F F15-00000297 | B27: F F15-00000297 | C27: 46021 | D27: 46096 | E27: 1212003 FACTURAS POR COBRAR DEL EXTERIOR | F27: GLOBALVET | G27: F F15-00000297 | I27: USD | J27: 88652 | K27: 298934.54 | M27: 298934.54 | N27: A159297 | O27: PARKER MENDOZA, VANESSA ALEXANDRA
A28: F F15-00000289 | B28: F F15-00000289 | C28: 46021 | D28: 46141 | E28: 1212003 FACTURAS POR COBRAR DEL EXTERIOR | F28: GRUPO COMERCIAL MONTECO S.A. | G28: F F15-00000289 | I28: USD | J28: 158333.02 | K28: 533898.93 | M28: 533898.93 | O28: PARKER MENDOZA, VANESSA ALEXANDRA
A29: F F15-00000289 | B29: F F15-00000289 | C29: 46021 | D29: 46126 | E29: 1212003 FACTURAS POR COBRAR DEL EXTERIOR | F29: GRUPO COMERCIAL MONTECO S.A. | G29: F F15-00000289 | I29: USD | J29: 158333.02 | K29: 533898.94 | M29: 533898.94 | N29: A158871 | O29: PARKER MENDOZA, VANESSA ALEXANDRA
A30: F F15-00000287 | B30: F F15-00000287 | C30: 46021 | D30: 46141 | E30: 1212003 FACTURAS POR COBRAR DEL EXTERIOR | F30: MONTECO ANIMAL HEALTH S.A. DE C.V. | G30: F F15-00000287 | I30: USD | J30: 183418.15 | K30: 618486.02 | M30: 618486.02 | O30: PARKER MENDOZA, VANESSA ALEXANDRA
A31: F F15-00000287 | B31: F F15-00000287 | C31: 46021 | D31: 46126 | E31: 1212003 FACTURAS POR COBRAR DEL EXTERIOR | F31: MONTECO ANIMAL HEALTH S.A. DE C.V. | G31: F F15-00000287 | I31: USD | J31: 183418.15 | K31: 618486.02 | M31: 618486.02 | O31: PARKER MENDOZA, VANESSA ALEXANDRA
A32: F F15-00000285 | B32: F F15-00000285 | C32: 46021 | D32: 46126 | E32: 1212003 FACTURAS POR COBRAR DEL EXTERIOR | F32: UNIVET S.R.L. | G32: F F15-00000285 | I32: USD | J32: 270165.02 | K32: 910996.43 | M32: 910996.43 | O32: PARKER MENDOZA, VANESSA ALEXANDRA
A33: F F15-00000283 | B33: F F15-00000283 | C33: 46021 | D33: 46066 | E33: 1212003 FACTURAS POR COBRAR DEL EXTERIOR | F33: CYCLOVET - SARL. | G33: F F15-00000283 | I33: USD | J33: 72429.6 | K33: 244232.61 | M33: 244232.61 | N33: A148869 | O33: PARKER MENDOZA, VANESSA ALEXANDRA
A34: F F15-00000282 | B34: F F15-00000282 | C34: 46021 | D34: 46066 | E34: 1212003 FACTURAS POR COBRAR DEL EXTERIOR | F34: CYCLOVET - SARL. | G34: F F15-00000282 | I34: USD | J34: 63580.68 | K34: 214394.05 | M34: 214394.05 | N34: A148868 | O34: PARKER MENDOZA, VANESSA ALEXANDRA
A35: F F15-00000281 | B35: F F15-00000281 | C35: 46021 | D35: 46066 | E35: 1212003 FACTURAS POR COBRAR DEL EXTERIOR | F35: CYCLOVET - SARL. | G35: F F15-00000281 | I35: USD | J35: 40000 | K35: 134880 | M35: 134880 | N35: A148867 | O35: PARKER MENDOZA, VANESSA ALEXANDRA
A36: F F15-00000279 | B36: F F15-00000279 | C36: 46021 | D36: 46021 | E36: 1212003 FACTURAS POR COBRAR DEL EXTERIOR | F36: MONTECO S.A | G36: F F15-00000279 | I36: USD | J36: 537900.9 | K36: 1813801.8 | M36: 1813801.8 | O36: PARKER MENDOZA, VANESSA ALEXANDRA
A37: F D15-00000036 | B37: F D15-00000036 | C37: 46021 | D37: 46021 | E37: 1212003 FACTURAS POR COBRAR DEL EXTERIOR | F37: SOCIEDAD NACIONAL PECUARIA S.A. | G37: F D15-00000036 | I37: USD | J37: 500 | K37: 1686 | M37: 1686 | N37: A142982 | O37: PALIZA CAMAVILCA, JHOSSELYN JARUMY
A38: PAPANT/2025/05849 (F D15-00000035) | B38: PAPANT/2025/05849 | C38: 46014 | D38: 46014 | E38: 1212003 FACTURAS POR COBRAR DEL EXTERIOR | F38: BREMER LANKA (PVT) LTD. | G38: Pago de cliente $ 600.00 - BREMER LANKA (PVT) LTD. - 23/12/2025 | H38: F D15-00000035 | I38: USD | J38: -600 | L38: 2023.2 | M38: -2023.2 | N38: A142959 | O38: MONTERO VILCAS, JOSE GORGE
A39: F D15-00000035 | B39: F D15-00000035 | C39: 46014 | D39: 46014 | E39: 1212003 FACTURAS POR COBRAR DEL EXTERIOR | F39: BREMER LANKA (PVT) LTD. | G39: F D15-00000035 | I39: USD | J39: 750 | K39: 2529 | M39: 2529 | N39: A142959 | O39: PALIZA CAMAVILCA, JHOSSELYN JARUMY
A40: CAMBI/2026/03/0085 | B40: CAMBI/2026/03/0085 | C40: 46083 | E40: 1212003 FACTURAS POR COBRAR DEL EXTERIOR | F40: SOCIEDAD NACIONAL PECUARIA S.A. | G40: Diferencia en tipo de cambio de moneda | I40: USD | L40: 99.76 | M40: -99.76 | N40: A142981 | O40: MONTERO VILCAS, JOSE GORGE
A41: BCP03/2025/00499 | B41: BCP03/2025/00499 | C41: 46083 | E41: 1212003 FACTURAS POR COBRAR DEL EXTERIOR | F41: SOCIEDAD NACIONAL PECUARIA S.A. | G41: F F15-00000280 | I41: USD | J41: -9070 | L41: 30484.27 | M41: -30484.27 | N41: A142981 | O41: MONTERO VILCAS, JOSE GORGE
A42: F F15-00000280 | B42: F F15-00000280 | C42: 46021 | D42: 46066 | E42: 1212003 FACTURAS POR COBRAR DEL EXTERIOR | F42: SOCIEDAD NACIONAL PECUARIA S.A. | G42: F F15-00000280 | I42: USD | J42: 23068.8 | K42: 77787.98 | M42: 77787.98 | N42: A142981 | O42: PARKER MENDOZA, VANESSA ALEXANDRA
A43: CAMBI/2026/03/0897 | B43: CAMBI/2026/03/0897 | C43: 46111 | E43: 1212003 FACTURAS POR COBRAR DEL EXTERIOR | F43: GLOBALVET | G43: Diferencia en tipo de cambio de moneda | I43: USD | K43: 1850.67 | M43: 1850.67 | N43: A145775 | O43: MONTERO VILCAS, JOSE GORGE
A44: BCP03/2025/00530 | B44: BCP03/2025/00530 | C44: 46111 | E44: 1212003 FACTURAS POR COBRAR DEL EXTERIOR | F44: GLOBALVET | G44: F F15-00000296 | I44: USD | J44: -16234 | L44: 56591.72 | M44: -56591.72 | N44: A145775 | O44: MONTERO VILCAS, JOSE GORGE
A45: F F15-00000296 | B45: F F15-00000296 | C45: 46021 | D45: 46081 | E45: 1212003 FACTURAS POR COBRAR DEL EXTERIOR | F45: GLOBALVET | G45: F F15-00000296 | I45: USD | J45: 36264.8 | K45: 122284.91 | M45: 122284.91 | N45: A145775 | O45: PARKER MENDOZA, VANESSA ALEXANDRA
A46: F C15-00000041 | B46: F C15-00000041 | C46: 46043 | D46: 46043 | E46: 1212003 FACTURAS POR COBRAR DEL EXTERIOR | F46: GLOBALVET | I46: USD | J46: -23.3 | L46: 78.36 | M46: -78.36 | N46: A145776 | O46: PALIZA CAMAVILCA, JHOSSELYN JARUMY
A47: CAMBI/2026/01/0978 | B47: CAMBI/2026/01/0978 | C47: 46043 | E47: 1212003 FACTURAS POR COBRAR DEL EXTERIOR | F47: GLOBALVET | G47: Diferencia en tipo de cambio de moneda | I47: USD | L47: 0.07 | M47: -0.07 | N47: A145776 | O47: MONTERO VILCAS, JOSE GORGE
A48: F F15-00000313 | B48: F F15-00000313 | C48: 46038 | D48: 46113 | E48: 1212003 FACTURAS POR COBRAR DEL EXTERIOR | F48: GLOBALVET | G48: F F15-00000313 | I48: USD | J48: 163.1 | K48: 548.99 | M48: 548.99 | N48: A145776 | O48: PARKER MENDOZA, VANESSA ALEXANDRA
A49: F D15-00000032 | B49: F D15-00000032 | C49: 45989 | D49: 45989 | E49: 1212003 FACTURAS POR COBRAR DEL EXTERIOR | F49: METROPOLITAN VETERINARY MARKETING CO.L.L.C. | G49: F D15-00000032 | I49: USD | J49: 622 | K49: 2096.76 | M49: 2096.76 | O49: PALIZA CAMAVILCA, JHOSSELYN JARUMY
A50: CAMBI/2026/03/0923 | B50: CAMBI/2026/03/0923 | C50: 46112 | E50: 1212003 FACTURAS POR COBRAR DEL EXTERIOR | F50: MONTECO S.A | G50: Diferencia en tipo de cambio de moneda | I50: USD | K50: 19.89 | M50: 19.89 | N50: A148186 | O50: MONTERO VILCAS, JOSE GORGE
A51: BCP03/2025/00532 | B51: BCP03/2025/00532 | C51: 46112 | E51: 1212003 FACTURAS POR COBRAR DEL EXTERIOR | F51: MONTECO S.A | G51: F F15-00000240 | I51: USD | J51: -191.3 | L51: 668.59 | M51: -668.59 | N51: A148186 | O51: MONTERO VILCAS, JOSE GORGE
A52: F F15-00000240 | B52: F F15-00000240 | C52: 45985 | D52: 46090 | E52: 1212003 FACTURAS POR COBRAR DEL EXTERIOR | F52: MONTECO S.A | G52: F F15-00000240 | I52: USD | J52: 106694.05 | K52: 361799.53 | M52: 361799.53 | N52: A148186 | O52: PARKER MENDOZA, VANESSA ALEXANDRA
A53: MISC/2026/02/0015 (Aplicacion de FT Provedor MT PNM) | B53: MISC/2026/02/0015 | C53: 46063 | E53: 1212003 FACTURAS POR COBRAR DEL EXTERIOR | F53: GRUPO COMERCIAL MONTECO S.A. | G53: F F15-00000288 | H53: Aplicacion de FT Provedor MT PNM | I53: USD | J53: -4500 | L53: 15133.5 | M53: -15133.5 | N53: A152489 | O53: MONTERO VILCAS, JOSE GORGE
A54: CAMBI/2026/02/0191 | B54: CAMBI/2026/02/0191 | C54: 46063 | E54: 1212003 FACTURAS POR COBRAR DEL EXTERIOR | F54: GRUPO COMERCIAL MONTECO S.A. | G54: Diferencia en tipo de cambio de moneda | I54: USD | L54: 40.5 | M54: -40.5 | N54: A152489 | O54: MONTERO VILCAS, JOSE GORGE
A55: F F15-00000288 | B55: F F15-00000288 | C55: 46021 | D55: 46111 | E55: 1212003 FACTURAS POR COBRAR DEL EXTERIOR | F55: GRUPO COMERCIAL MONTECO S.A. | G55: F F15-00000288 | I55: USD | J55: 143704.32 | K55: 484570.97 | M55: 484570.97 | N55: A152489 | O55: PARKER MENDOZA, VANESSA ALEXANDRA
A56: F F15-00000240 | B56: F F15-00000240 | C56: 45985 | D56: 46105 | E56: 1212003 FACTURAS POR COBRAR DEL EXTERIOR | F56: MONTECO S.A | G56: F F15-00000240 | I56: USD | J56: 106694.05 | K56: 361799.53 | M56: 361799.53 | N56: A152747 | O56: PARKER MENDOZA, VANESSA ALEXANDRA
A57: CAMBI/2025/11/0943 | B57: CAMBI/2025/11/0943 | C57: 45980 | E57: 1212003 FACTURAS POR COBRAR DEL EXTERIOR | F57: METROPOLITAN VETERINARY MARKETING CO.L.L.C. | G57: Diferencia en tipo de cambio de moneda | I57: USD | K57: 494.35 | M57: 494.35 | O57: MONTERO VILCAS, JOSE GORGE
A58: CAMBI/2025/11/0916 | B58: CAMBI/2025/11/0916 | C58: 45980 | E58: 1212003 FACTURAS POR COBRAR DEL EXTERIOR | F58: VYPHAVET CO., LTD. | G58: Diferencia en tipo de cambio de moneda | I58: USD | L58: 704.77 | M58: -704.77 | O58: MONTERO VILCAS, JOSE GORGE
A59: BCP03/2025/00380 | B59: BCP03/2025/00380 | C59: 45980 | E59: 1212003 FACTURAS POR COBRAR DEL EXTERIOR | F59: METROPOLITAN VETERINARY MARKETING CO.L.L.C. | G59: F F15-00000226 | I59: USD | J59: -82391.79 | L59: 277825.12 | M59: -277825.12 | O59: MONTERO VILCAS, JOSE GORGE
A60: BCP02/2025/01715 | B60: BCP02/2025/01715 | C60: 45980 | E60: 1212003 FACTURAS POR COBRAR DEL EXTERIOR | F60: VYPHAVET CO., LTD. | G60: F050-00001585 | I60: USD | J60: -1825.82 | L60: 6156.66 | M60: -6156.66 | O60: MONTERO VILCAS, JOSE GORGE
A61: F F15-00000226 | B61: F F15-00000226 | C61: 45973 | D61: 46123 | E61: 1212003 FACTURAS POR COBRAR DEL EXTERIOR | F61: METROPOLITAN VETERINARY MARKETING CO.L.L.C. | G61: F F15-00000226 | I61: USD | J61: 82400.86 | K61: 277361.3 | M61: 277361.3 | O61: PARKER MENDOZA, VANESSA ALEXANDRA
A62: F F15-00000212 | B62: F F15-00000212 | C62: 45953 | D62: 45953 | E62: 1212003 FACTURAS POR COBRAR DEL EXTERIOR | F62: VYPHAVET CO., LTD. | G62: F F15-00000212 | I62: USD | J62: 119.44 | K62: 406.22 | M62: 406.22 | O62: PALIZA CAMAVILCA, JHOSSELYN JARUMY
A63: CAMBI/2025/09/0763 | B63: CAMBI/2025/09/0763 | C63: 45905 | E63: 1212003 FACTURAS POR COBRAR DEL EXTERIOR | F63: BILI AGRO BUSINESS PLC | G63: Diferencia en tipo de cambio de moneda | I63: USD | L63: 5.55 | M63: -5.55 | O63: MONTERO VILCAS, JOSE GORGE
A64: BCP02/2025/01211 | B64: BCP02/2025/01211 | C64: 45905 | E64: 1212003 FACTURAS POR COBRAR DEL EXTERIOR | F64: BILI AGRO BUSINESS PLC | G64: F D15-00000017 | I64: USD | J64: -264.1 | L64: 934.65 | M64: -934.65 | O64: MONTERO VILCAS, JOSE GORGE
A65: F F15-00000117 | B65: F F15-00000117 | C65: 45870 | D65: 45870 | E65: 1212003 FACTURAS POR COBRAR DEL EXTERIOR | F65: EMPRESA MELO S.A. | G65: F F15-00000117 | I65: USD | J65: 56.93 | K65: 204.26 | M65: 204.26 | O65: PALIZA CAMAVILCA, JHOSSELYN JARUMY
A66: CAMBI/2025/07/1140 | B66: CAMBI/2025/07/1140 | C66: 45868 | E66: 1212003 FACTURAS POR COBRAR DEL EXTERIOR | F66: EMPRESA MELO S.A. | G66: Diferencia en tipo de cambio de moneda | I66: USD | L66: 16813.06 | M66: -16813.06 | O66: MONTERO VILCAS, JOSE GORGE
A67: BCP02/2025/00964 | B67: BCP02/2025/00964 | C67: 45868 | E67: 1212003 FACTURAS POR COBRAR DEL EXTERIOR | F67: EMPRESA MELO S.A. | G67: F F15-00000037 | I67: USD | J67: -129331.12 | L67: 459384.14 | M67: -459384.14 | O67: MONTERO VILCAS, JOSE GORGE
A68: F D15-00000017 | B68: F D15-00000017 | C68: 45855 | D68: 45855 | E68: 1212003 FACTURAS POR COBRAR DEL EXTERIOR | F68: BILI AGRO BUSINESS PLC | G68: F D15-00000017 | I68: USD | J68: 750 | K68: 2670 | M68: 2670 | O68: PALIZA CAMAVILCA, JHOSSELYN JARUMY
A69: F F15-00000092 | B69: F F15-00000092 | C69: 45845 | D69: 45845 | E69: 1212003 FACTURAS POR COBRAR DEL EXTERIOR | F69: BIOVETA A.S. | G69: F F15-00000092 | I69: USD | J69: 19400.33 | K69: 68987.57 | M69: 68987.57 | N69: A158432 | O69: PALIZA CAMAVILCA, JHOSSELYN JARUMY
A70: PAPANT/2025/02567 (F F15-00000051) | B70: PAPANT/2025/02567 | C70: 45814 | D70: 45814 | E70: 1212003 FACTURAS POR COBRAR DEL EXTERIOR | F70: GRUPO GRANDES ROMAN S.A. | G70: Pago de cliente $ 51,956.45 - GRUPO GRANDES ROMAN S.A. - 06/06/2025 | H70: F F15-00000051 | I70: USD | J70: -51956.45 | L70: 188498 | M70: -188498 | O70: MONTERO VILCAS, JOSE GORGE
A71: F F15-00000051 | B71: F F15-00000051 | C71: 45814 | D71: 45815 | E71: 1212003 FACTURAS POR COBRAR DEL EXTERIOR | F71: GRUPO GRANDES ROMAN S.A. | G71: F F15-00000051 | I71: USD | J71: 51956.45 | K71: 188498 | M71: 188498 | O71: PARKER MENDOZA, VANESSA ALEXANDRA
A72: F F15-00000037 | B72: F F15-00000037 | C72: 45792 | D72: 45882 | E72: 1212003 FACTURAS POR COBRAR DEL EXTERIOR | F72: EMPRESA MELO S.A. | G72: F F15-00000037 | I72: USD | J72: 131830.2 | K72: 485398.81 | M72: 485398.81 | O72: PARKER MENDOZA, VANESSA ALEXANDRA
A73: F050-00001585 | B73: F050-00001585 | C73: 45658 | D73: 45569 | E73: 1212003 FACTURAS POR COBRAR DEL EXTERIOR | F73: VYPHAVET CO., LTD. | G73: F050-00001585 | I73: USD | J73: 2419.85 | K73: 9093.8 | M73: 9093.8 | O73: BARCENA BRAGA, KATTYA ADELAIDA
A74: F050-00001348 | B74: F050-00001348 | C74: 45658 | D74: 45290 | E74: 1212003 FACTURAS POR COBRAR DEL EXTERIOR | F74: VETLINE | G74: F050-00001348 | I74: USD | J74: 35.4 | K74: 133.03 | M74: 133.03 | O74: BARCENA BRAGA, KATTYA ADELAIDA
A75: F050-00000640 | B75: F050-00000640 | C75: 45658 | D75: 44649 | E75: 1212003 FACTURAS POR COBRAR DEL EXTERIOR | F75: SEUMEDS LIMITED | G75: F050-00000640 | I75: USD | J75: 61.6 | K75: 231.49 | M75: 231.49 | O75: BARCENA BRAGA, KATTYA ADELAIDA
A76: F010-00000880 | B76: F010-00000880 | C76: 45658 | D76: 45415 | E76: 1212003 FACTURAS POR COBRAR DEL EXTERIOR | F76: VETLINE | G76: F010-00000880 | I76: USD | J76: 136 | K76: 511.09 | M76: 511.09 | O76: BARCENA BRAGA, KATTYA ADELAIDA
A77: F010-00000780 | B77: F010-00000780 | C77: 45658 | D77: 44747 | E77: 1212003 FACTURAS POR COBRAR DEL EXTERIOR | F77: DERIBAL SOCIEDAD ANONIMA | G77: F010-00000780 | I77: USD | J77: 148 | K77: 556.18 | M77: 556.18 | O77: BARCENA BRAGA, KATTYA ADELAIDA
A78: F010-00000503 | B78: F010-00000503 | C78: 45658 | D78: 43894 | E78: 1212003 FACTURAS POR COBRAR DEL EXTERIOR | F78: SADIN INTERNATIONAL TRADING CO. L.L.C. | G78: F010-00000358 | I78: USD | J78: -1045 | L78: 3939.65 | M78: -3939.65 | O78: BARCENA BRAGA, KATTYA ADELAIDA
A79: F010-00000359 | B79: F010-00000359 | C79: 45658 | D79: 43894 | E79: 1212003 FACTURAS POR COBRAR DEL EXTERIOR | F79: SADIN INTERNATIONAL TRADING CO. L.L.C. | G79: F010-00000359 | I79: USD | J79: -1090 | L79: 4109.3 | M79: -4109.3 | O79: BARCENA BRAGA, KATTYA ADELAIDA
A80: F010-00000358 | B80: F010-00000358 | C80: 45658 | D80: 44575 | E80: 1212003 FACTURAS POR COBRAR DEL EXTERIOR | F80: BEIJING YI LONG XIANG TECHNOLOGY CO.LTD | G80: F010-00000503 | I80: USD | J80: -1799 | L80: 6782.23 | M80: -6782.23 | O80: BARCENA BRAGA, KATTYA ADELAIDA
J82: =SUM(J3:J80) -> 2768084.2 | M82: =SUM(M3:M80) -> 9649541.6
J83: 3.486
J84: =+J82*J83 -> 9649541.6 | L84: =+J84-M82 -> -0.0039399974

Sheet 122xx1
A1: Asiento contable | B1: Número | C1: Fecha | D1: Fecha de vencimiento | E1: Cuenta | F1: Socio | G1: Etiqueta | H1: Referencia | I1: Moneda | J1: Importe en moneda | K1: Debe | L1: Haber | M1: Saldo | N1: Conciliación | O1: Creado por
A2: 1220001 ANTICIPOS CLIENTES NACIONAL M.N. (412)
A3: BCP01/2025/15559 | B3: BCP01/2025/15559 | C3: 46112 | E3: 1220001 ANTICIPOS CLIENTES NACIONAL M.N. | F3: CAMPOS ALONZO ANDRES EDUARDO | G3: ABONO | I3: PEN | J3: -92.9 | L3: 92.9 | M3: -92.9 | N3: A149375 | O3: BARCENA BRAGA, KATTYA ADELAIDA
A4: BCP01/2025/15501 | B4: BCP01/2025/15501 | C4: 46111 | E4: 1220001 ANTICIPOS CLIENTES NACIONAL M.N. | F4: CONSTRUCTORA Y MULTISERVICIOS AGROVET J&S SOCIEDAD ANONIMA CERRADA | G4: SALDO | I4: PEN | J4: -10 | L4: 10 | M4: -10 | O4: BARCENA BRAGA, KATTYA ADELAIDA
A5: BCP01/2025/15499 | B5: BCP01/2025/15499 | C5: 46111 | E5: 1220001 ANTICIPOS CLIENTES NACIONAL M.N. | F5: AGRIMEC VETERINARIA E.I.R.L. - AGRIMEC VET E.I.R.L. | G5: DE AGRIMEC VET EIRL | I5: PEN | J5: -15276.28 | L5: 15276.28 | M5: -15276.28 | O5: BARCENA BRAGA, KATTYA ADELAIDA
A6: BBVA1/2025/05541 | B6: BBVA1/2025/05541 | C6: 46111 | E6: 1220001 ANTICIPOS CLIENTES NACIONAL M.N. | F6: AGROVETERINARIA Y MULTISERVICIOS "DAGA" SOCIEDAD COMERCIAL DE RESPONSABILIDAD LIMITADA | G6: ABONO | I6: PEN | J6: -7241.93 | L6: 7241.93 | M6: -7241.93 | O6: BARCENA BRAGA, KATTYA ADELAIDA
A7: BCP01/2025/15370 | B7: BCP01/2025/15370 | C7: 46106 | E7: 1220001 ANTICIPOS CLIENTES NACIONAL M.N. | F7: GONZALES MEDINA JOHANNA PATRICIA | G7: SALDO | I7: PEN | J7: -43.89 | L7: 43.89 | M7: -43.89 | O7: BARCENA BRAGA, KATTYA ADELAIDA
A8: BCP01/2025/15268 | B8: BCP01/2025/15268 | C8: 46101 | E8: 1220001 ANTICIPOS CLIENTES NACIONAL M.N. | F8: VARIOS | G8: ABONO NO IDENTIFICADOS | I8: PEN | J8: -5017.87 | L8: 5017.87 | M8: -5017.87 | O8: BARCENA BRAGA, KATTYA ADELAIDA
A9: BCP01/2025/15265 | B9: BCP01/2025/15265 | C9: 46101 | E9: 1220001 ANTICIPOS CLIENTES NACIONAL M.N. | F9: PHARMAVET MARKET E.I.R.L. | G9: ABONO | I9: PEN | J9: -15284.04 | L9: 15284.04 | M9: -15284.04 | N9: A144252 | O9: BARCENA BRAGA, KATTYA ADELAIDA
A10: BBVA1/2025/05284 | B10: BBVA1/2025/05284 | C10: 46099 | E10: 1220001 ANTICIPOS CLIENTES NACIONAL M.N. | F10: VARIOS | G10: ABONO NO IDENTIFICADO | I10: PEN | J10: -133 | L10: 133 | M10: -133 | O10: BARCENA BRAGA, KATTYA ADELAIDA
A11: IBK02/2025/03473 | B11: IBK02/2025/03473 | C11: 46098 | E11: 1220001 ANTICIPOS CLIENTES NACIONAL M.N. | F11: VARIOS | G11: ABONO NO IDENTIFICADO | I11: PEN | J11: -400 | L11: 400 | M11: -400 | O11: BARCENA BRAGA, KATTYA ADELAIDA
A12: BCP01/2025/15154 | B12: BCP01/2025/15154 | C12: 46098 | E12: 1220001 ANTICIPOS CLIENTES NACIONAL M.N. | F12: VARIOS | G12: ABONO NO IDENTIFICADO | I12: PEN | J12: -1335 | L12: 1335 | M12: -1335 | O12: BARCENA BRAGA, KATTYA ADELAIDA
A13: BCP01/2025/14815 | B13: BCP01/2025/14815 | C13: 46097 | E13: 1220001 ANTICIPOS CLIENTES NACIONAL M.N. | F13: CONSTRUCTORA Y MULTISERVICIOS AGROVET J&S SOCIEDAD ANONIMA CERRADA | G13: SALDO A FVAOR PE | I13: PEN | J13: 348.59 | K13: 348.59 | M13: 348.59 | O13: BARCENA BRAGA, KATTYA ADELAIDA
A14: BCP01/2025/14260 | B14: BCP01/2025/14260 | C14: 46076 | E14: 1220001 ANTICIPOS CLIENTES NACIONAL M.N. | F14: VARIOS | G14: SALDO | I14: PEN | J14: -73 | L14: 73 | M14: -73 | O14: BARCENA BRAGA, KATTYA ADELAIDA
A15: BCP01/2025/14105 | B15: BCP01/2025/14105 | C15: 46071 | E15: 1220001 ANTICIPOS CLIENTES NACIONAL M.N. | F15: PHARMAVET MARKET E.I.R.L. | G15: Saldo pendiente: S/ 12,909.50 | I15: PEN | J15: -199.97 | L15: 199.97 | M15: -199.97 | O15: BARCENA BRAGA, KATTYA ADELAIDA
A16: BCP01/2025/13699 | B16: BCP01/2025/13699 | C16: 46064 | E16: 1220001 ANTICIPOS CLIENTES NACIONAL M.N. | F16: EMPRESA COMERCIALIZADORA DE INSUMOS Y PRODUCTOS AGROPECUARIOS Y TRANSPORTES S.R.L. | G16: SALDO A FAVOR | I16: PEN | J16: 170.57 | K16: 170.57 | M16: 170.57 | O16: BARCENA BRAGA, KATTYA ADELAIDA
A17: BCP01/2025/13693 | B17: BCP01/2025/13693 | C17: 46064 | E17: 1220001 ANTICIPOS CLIENTES NACIONAL M.N. | F17: FUMIGACIONES DEL SUR E.I.R.L. | G17: SALDO PE | I17: PEN | J17: -600 | L17: 600 | M17: -600 | O17: BARCENA BRAGA, KATTYA ADELAIDA
A18: BCP01/2025/13593 | B18: BCP01/2025/13593 | C18: 46059 | E18: 1220001 ANTICIPOS CLIENTES NACIONAL M.N. | F18: SUPERMERCADOS PARA MASCOTAS DEL PERU S.A.C. | G18: SALDO A FAVOR | I18: PEN | J18: -35.4 | L18: 35.4 | M18: -35.4 | O18: PEREIRA FUENTES, EIGLY YARITZA
A19: BCP01/2025/13510 | B19: BCP01/2025/13510 | C19: 46057 | E19: 1220001 ANTICIPOS CLIENTES NACIONAL M.N. | F19: PETS SHOP LA MOLINA SOCIEDAD ANONIMA CERRADA | G19: SALDO A FAVOR | I19: PEN | J19: -683.32 | L19: 683.32 | M19: -683.32 | O19: PEREIRA FUENTES, EIGLY YARITZA
A20: BBVA1/2025/04579 | B20: BBVA1/2025/04579 | C20: 46051 | E20: 1220001 ANTICIPOS CLIENTES NACIONAL M.N. | F20: AGROVETERINARIA Y MULTISERVICIOS "DAGA" SOCIEDAD COMERCIAL DE RESPONSABILIDAD LIMITADA | G20: SALDO A FAVOR | I20: PEN | J20: -3406.33 | L20: 3406.33 | M20: -3406.33 | O20: PEREIRA FUENTES, EIGLY YARITZA
A21: BCP01/2025/13309 | B21: BCP01/2025/13309 | C21: 46049 | E21: 1220001 ANTICIPOS CLIENTES NACIONAL M.N. | F21: PHARMAVET MARKET E.I.R.L. | G21: saldo a favor | I21: PEN | J21: -640.5 | L21: 640.5 | M21: -640.5 | O21: MONTERO VILCAS, JOSE GORGE
A22: BCP01/2025/13304 | B22: BCP01/2025/13304 | C22: 46049 | E22: 1220001 ANTICIPOS CLIENTES NACIONAL M.N. | F22: PHARMAVET MARKET E.I.R.L. | G22: saldo a favor por FT F F01-00004319 | I22: PEN | J22: -1708 | L22: 1708 | M22: -1708 | O22: MONTERO VILCAS, JOSE GORGE
A23: PAPANT/2025/06651 (F F01-00004168) | B23: PAPANT/2025/06651 | C23: 46042 | D23: 46042 | E23: 1220001 ANTICIPOS CLIENTES NACIONAL M.N. | F23: AGUIVET S.A.C. | G23: Pago de cliente S/ 6,553.18 - AGUIVET S.A.C. - 20/01/2026 | H23: F F01-00004168 | I23: PEN | J23: 6553.18 | K23: 6553.18 | M23: 6553.18 | O23: MONTERO VILCAS, JOSE GORGE
A24: BCP01/2025/12997 | B24: BCP01/2025/12997 | C24: 46037 | E24: 1220001 ANTICIPOS CLIENTES NACIONAL M.N. | F24: AGRIVET E INVERSIONES S.A.C. | G24: DE AGRIVET E INVERSION SALDO | I24: PEN | J24: -371.29 | L24: 371.29 | M24: -371.29 | O24: BARCENA BRAGA, KATTYA ADELAIDA
A25: PAPANT/2025/06663 (F F01-00004004) | B25: PAPANT/2025/06663 | C25: 46029 | D25: 46029 | E25: 1220001 ANTICIPOS CLIENTES NACIONAL M.N. | F25: VETERINARIA SAN PABLO E.I.R.L. | G25: Pago de cliente S/ 208.65 - VETERINARIA SAN PABLO E.I.R.L. - 07/01/2026 | H25: F F01-00004004 | I25: PEN | J25: 208.65 | K25: 208.65 | M25: 208.65 | O25: MONTERO VILCAS, JOSE GORGE
A26: BCP01/2025/12118 | B26: BCP01/2025/12118 | C26: 46028 | E26: 1220001 ANTICIPOS CLIENTES NACIONAL M.N. | F26: GALIANO FRANCO, LESLI GIANINA | G26: SALDO A FAVOR | I26: PEN | J26: -4.02 | L26: 4.02 | M26: -4.02 | O26: PEREIRA FUENTES, EIGLY YARITZA
A27: PAPANT/2025/08273 (B B01-00004471) | B27: PAPANT/2025/08273 | C27: 46023 | D27: 46023 | E27: 1220001 ANTICIPOS CLIENTES NACIONAL M.N. | F27: SANCHEZ YEPEZ CARLA STEFANY | G27: Pago de cliente S/ 75.00 - SANCHEZ YEPEZ CARLA STEFANY - 01/01/2026 | H27: B B01-00004471 | I27: PEN | J27: 75 | K27: 75 | M27: 75 | O27: BARCENA BRAGA, KATTYA ADELAIDA
A28: BCP01/2025/11893 | B28: BCP01/2025/11893 | C28: 46017 | E28: 1220001 ANTICIPOS CLIENTES NACIONAL M.N. | F28: AGRIVET E INVERSIONES S.A.C. | G28: SALDO A FAVOR | I28: PEN | J28: -200.86 | L28: 200.86 | M28: -200.86 | O28: PEREIRA FUENTES, EIGLY YARITZA
A29: BCP01/2025/11888 | B29: BCP01/2025/11888 | C29: 46017 | E29: 1220001 ANTICIPOS CLIENTES NACIONAL M.N. | F29: VETERINARIA SAN PABLO E.I.R.L. | G29: SALDO A FAVOR | I29: PEN | J29: -96.83 | L29: 96.83 | M29: -96.83 | O29: PEREIRA FUENTES, EIGLY YARITZA
A30: BCP01/2025/11770 | B30: BCP01/2025/11770 | C30: 46013 | E30: 1220001 ANTICIPOS CLIENTES NACIONAL M.N. | F30: IDROGO MEDINA JUAN CARLOS | G30: saldo a favor | I30: PEN | J30: -151.31 | L30: 151.31 | M30: -151.31 | O30: MONTERO VILCAS, JOSE GORGE
A31: BBVA1/2025/04024 | B31: BBVA1/2025/04024 | C31: 46010 | E31: 1220001 ANTICIPOS CLIENTES NACIONAL M.N. | F31: INVERSIONES PROAVET E.I.R.L. | G31: SALDO A FAVOR | I31: PEN | J31: -190.5 | L31: 190.5 | M31: -190.5 | O31: PEREIRA FUENTES, EIGLY YARITZA
A32: BCP01/2025/11310 | B32: BCP01/2025/11310 | C32: 46006 | E32: 1220001 ANTICIPOS CLIENTES NACIONAL M.N. | F32: AGUIVET S.A.C. | G32: SALDO A FAVOR | I32: PEN | J32: -6521.91 | L32: 6521.91 | M32: -6521.91 | O32: PEREIRA FUENTES, EIGLY YARITZA
A33: BBVA1/2025/03966 | B33: BBVA1/2025/03966 | C33: 46006 | E33: 1220001 ANTICIPOS CLIENTES NACIONAL M.N. | F33: VETERINARIA PIURA SOCIEDAD ANONIMA CERRADA | G33: SALDO A FAVOR | I33: PEN | J33: -10 | L33: 10 | M33: -10 | O33: PEREIRA FUENTES, EIGLY YARITZA
A34: BCP01/2025/11285 | B34: BCP01/2025/11285 | C34: 46003 | E34: 1220001 ANTICIPOS CLIENTES NACIONAL M.N. | F34: CASA DEL BUEN CRIADOR E.I.R.L. | G34: SALDO FT 3651 | I34: PEN | J34: -245.7 | L34: 245.7 | M34: -245.7 | O34: BARCENA BRAGA, KATTYA ADELAIDA
A35: BCP01/2025/11162 | B35: BCP01/2025/11162 | C35: 45996 | E35: 1220001 ANTICIPOS CLIENTES NACIONAL M.N. | F35: HOSPITAL VETERINARIO S.A.C. | G35: SALDO A FAVOR PE S10920 | I35: PEN | J35: -97.94 | L35: 97.94 | M35: -97.94 | O35: PEREIRA FUENTES, EIGLY YARITZA
A36: BCP01/2025/10319 | B36: BCP01/2025/10319 | C36: 45975 | E36: 1220001 ANTICIPOS CLIENTES NACIONAL M.N. | F36: AGRIVET E INVERSIONES S.A.C. | G36: SALDO A FAVOR | I36: PEN | J36: -723.27 | L36: 723.27 | M36: -723.27 | O36: PEREIRA FUENTES, EIGLY YARITZA
A37: BCP01/2025/10162 | B37: BCP01/2025/10162 | C37: 45972 | E37: 1220001 ANTICIPOS CLIENTES NACIONAL M.N. | F37: AGRO QUIMICA SILVA S.A.C. | G37: DE AGRO QUIMICA SILVA SALDO | I37: PEN | J37: -2466.47 | L37: 2466.47 | M37: -2466.47 | O37: BARCENA BRAGA, KATTYA ADELAIDA
A38: BCP01/2025/09744 | B38: BCP01/2025/09744 | C38: 45954 | E38: 1220001 ANTICIPOS CLIENTES NACIONAL M.N. | F38: DOG CAT E.I.R.L. | G38: saldo a favor | I38: PEN | J38: -4.27 | L38: 4.27 | M38: -4.27 | O38: MONTERO VILCAS, JOSE GORGE
A39: BCP01/2025/09677 | B39: BCP01/2025/09677 | C39: 45952 | E39: 1220001 ANTICIPOS CLIENTES NACIONAL M.N. | F39: AGRO QUIMICA SILVA S.A.C. | G39: Saldo pendiente: S/ 41.95 - TRAN.CTAS.TERC.BM SALDO A FAVOR | I39: PEN | J39: 41.95 | K39: 41.95 | M39: 41.95 | O39: PEREIRA FUENTES, EIGLY YARITZA
A40: BCP01/2025/09576 | B40: BCP01/2025/09576 | C40: 45947 | E40: 1220001 ANTICIPOS CLIENTES NACIONAL M.N. | F40: MISTER PET S.A.C. | G40: DE MISTER PET SAC - ABONO | I40: PEN | J40: -21.97 | L40: 21.97 | M40: -21.97 | O40: BARCENA BRAGA, KATTYA ADELAIDA
A41: BCP01/2025/09075 | B41: BCP01/2025/09075 | C41: 45943 | E41: 1220001 ANTICIPOS CLIENTES NACIONAL M.N. | F41: COUCOU AMI S.A.C. | G41: SALDO A FAVOR PE S08677 | I41: PEN | J41: -24.75 | L41: 24.75 | M41: -24.75 | O41: PEREIRA FUENTES, EIGLY YARITZA
A42: SCT01/2025/01317 | B42: SCT01/2025/01317 | C42: 45936 | E42: 1220001 ANTICIPOS CLIENTES NACIONAL M.N. | F42: ALIAGA HERMOZA RAQUEL REBECA | G42: SALDO A FAVOR PE S08338 | I42: PEN | J42: -37.36 | L42: 37.36 | M42: -37.36 | O42: PEREIRA FUENTES, EIGLY YARITZA
A43: BCP01/2025/08820 | B43: BCP01/2025/08820 | C43: 45932 | E43: 1220001 ANTICIPOS CLIENTES NACIONAL M.N. | F43: PRIVET E.I.R.L. - PRIVET | G43: SALDO A FAVOR PE S08194 | I43: PEN | J43: -52.99 | L43: 52.99 | M43: -52.99 | O43: PEREIRA FUENTES, EIGLY YARITZA
A44: IBK02/2025/02097 | B44: IBK02/2025/02097 | C44: 45930 | E44: 1220001 ANTICIPOS CLIENTES NACIONAL M.N. | F44: EMPRESA COMERCIALIZADORA DE INSUMOS Y PRODUCTOS AGROPECUARIOS Y TRANSPORTES S.R.L. | G44: SALDO PE | I44: PEN | J44: -577.83 | L44: 577.83 | M44: -577.83 | O44: BARCENA BRAGA, KATTYA ADELAIDA
A45: BCP01/2025/08726 | B45: BCP01/2025/08726 | C45: 45929 | E45: 1220001 ANTICIPOS CLIENTES NACIONAL M.N. | F45: FLORES REYNA DE ROMERO YOLANDA ELIZABETH | G45: saldo a favor PE S08106 | I45: PEN | J45: -51.27 | L45: 51.27 | M45: -51.27 | O45: PEREIRA FUENTES, EIGLY YARITZA
A46: BCP01/2025/11715 | B46: BCP01/2025/11715 | C46: 46009 | E46: 1220001 ANTICIPOS CLIENTES NACIONAL M.N. | F46: VARIOS | G46: ABONO NO IDENTIFICADO | I46: PEN | J46: -313.88 | L46: 313.88 | M46: -313.88 | N46: A159468 | O46: PEREIRA FUENTES, EIGLY YARITZA
A47: BCP01/2025/08639 | B47: BCP01/2025/08639 | C47: 45927 | E47: 1220001 ANTICIPOS CLIENTES NACIONAL M.N. | F47: CONSTRUCTORA Y MULTISERVICIOS AGROVET J&S SOCIEDAD ANONIMA CERRADA | G47: SALDO A FVAOR PE | I47: PEN | J47: -403.81 | L47: 403.81 | M47: -403.81 | O47: PEREIRA FUENTES, EIGLY YARITZA
A48: BCP01/2025/11192 | B48: BCP01/2025/11192 | C48: 46001 | E48: 1220001 ANTICIPOS CLIENTES NACIONAL M.N. | F48: VARIOS | G48: ABONO NO IDENTIFICADO | I48: PEN | J48: -1400 | L48: 1400 | M48: -1400 | N48: A159468 | O48: PEREIRA FUENTES, EIGLY YARITZA
A49: BBVA1/2025/03810 | B49: BBVA1/2025/03810 | C49: 45989 | E49: 1220001 ANTICIPOS CLIENTES NACIONAL M.N. | F49: VARIOS | G49: ABONO NO ID | I49: PEN | J49: -1525.55 | L49: 1525.55 | M49: -1525.55 | N49: A159468 | O49: BARCENA BRAGA, KATTYA ADELAIDA
A50: BBVA1/2025/03725 | B50: BBVA1/2025/03725 | C50: 45985 | E50: 1220001 ANTICIPOS CLIENTES NACIONAL M.N. | F50: VARIOS | G50: ABONO NO ID | I50: PEN | J50: -2304.66 | L50: 2304.66 | M50: -2304.66 | N50: A159468 | O50: BARCENA BRAGA, KATTYA ADELAIDA
A51: BCP01/2025/10433 | B51: BCP01/2025/10433 | C51: 45979 | E51: 1220001 ANTICIPOS CLIENTES NACIONAL M.N. | F51: VARIOS | G51: ABONO NO IDENTIFICADO | I51: PEN | J51: -210 | L51: 210 | M51: -210 | N51: A159468 | O51: PEREIRA FUENTES, EIGLY YARITZA
A52: BBVA1/2025/03460 | B52: BBVA1/2025/03460 | C52: 45964 | E52: 1220001 ANTICIPOS CLIENTES NACIONAL M.N. | F52: VARIOS | G52: ABONO NO ID | I52: PEN | J52: -1433.98 | L52: 1433.98 | M52: -1433.98 | N52: A159468 | O52: BARCENA BRAGA, KATTYA ADELAIDA
A53: BCP01/2025/08431 | B53: BCP01/2025/08431 | C53: 45920 | E53: 1220001 ANTICIPOS CLIENTES NACIONAL M.N. | F53: DISTRIBUCIONES AGROVET GRANDEZ TARAPOTO S.R.L. | G53: SALDO A FAVOR | I53: PEN | J53: -30.5 | L53: 30.5 | M53: -30.5 | O53: PEREIRA FUENTES, EIGLY YARITZA
A54: BCP01/2025/08483 | B54: BCP01/2025/08483 | C54: 45919 | E54: 1220001 ANTICIPOS CLIENTES NACIONAL M.N. | F54: VETERINARIAS TORRES AREVALO E.I.R.L. | G54: SALDO PE | I54: PEN | J54: -20 | L54: 20 | M54: -20 | O54: BARCENA BRAGA, KATTYA ADELAIDA
A55: BBVA1/2025/02681 | B55: BBVA1/2025/02681 | C55: 45901 | E55: 1220001 ANTICIPOS CLIENTES NACIONAL M.N. | F55: VARIOS | G55: DEP PB 011 N.00007514 DISP 0 ABONO NO ID | I55: PEN | J55: -2949 | L55: 2949 | M55: -2949 | N55: A159468 | O55: BARCENA BRAGA, KATTYA ADELAIDA
A56: BNDET/2025/00004 | B56: BNDET/2025/00004 | C56: 45755 | E56: 1220001 ANTICIPOS CLIENTES NACIONAL M.N. | F56: VARIOS | G56: NOT.ABON - DETR - NO RECONOCIDA | I56: PEN | J56: -791 | L56: 791 | M56: -791 | N56: A159468 | O56: BARCENA BRAGA, KATTYA ADELAIDA
A57: BNDET/2025/00003 | B57: BNDET/2025/00003 | C57: 45755 | E57: 1220001 ANTICIPOS CLIENTES NACIONAL M.N. | F57: VARIOS | G57: NOT.ABON - ABONO NO RECONOC | I57: PEN | J57: -727 | L57: 727 | M57: -727 | N57: A159468 | O57: BARCENA BRAGA, KATTYA ADELAIDA
A58: BBVA1/2025/00839 | B58: BBVA1/2025/00839 | C58: 45745 | E58: 1220001 ANTICIPOS CLIENTES NACIONAL M.N. | F58: VARIOS | G58: ABONO NO IDENTIFICADO | I58: PEN | J58: -82 | L58: 82 | M58: -82 | N58: A159468 | O58: BARCENA BRAGA, KATTYA ADELAIDA
A59: BBVA1/2025/00618 | B59: BBVA1/2025/00618 | C59: 45730 | E59: 1220001 ANTICIPOS CLIENTES NACIONAL M.N. | F59: VARIOS | G59: CHRISTIAN ABRAHAM ABARCA - ABONO NO ID. | I59: PEN | J59: -85 | L59: 85 | M59: -85 | N59: A159468 | O59: BARCENA BRAGA, KATTYA ADELAIDA
A60: SCT01/2025/00075 | B60: SCT01/2025/00075 | C60: 45691 | E60: 1220001 ANTICIPOS CLIENTES NACIONAL M.N. | F60: VARIOS | G60: ABONO NO IDENTIFICADO | I60: PEN | J60: -1000 | L60: 1000 | M60: -1000 | N60: A159468 | O60: BARCENA BRAGA, KATTYA ADELAIDA
A61: PAPANT/2025/04977 (F D01-00000177) | B61: PAPANT/2025/04977 | C61: 45904 | D61: 45904 | E61: 1220001 ANTICIPOS CLIENTES NACIONAL M.N. | F61: ACVET PERU E.I.R.L. | G61: Pago de cliente S/ 17.85 - ACVET PERU E.I.R.L. - 04/09/2025 | H61: F D01-00000177 | I61: PEN | J61: 17.85 | K61: 17.85 | M61: 17.85 | O61: BARCENA BRAGA, KATTYA ADELAIDA
A62: IBK02/2025/01823 | B62: IBK02/2025/01823 | C62: 45901 | E62: 1220001 ANTICIPOS CLIENTES NACIONAL M.N. | F62: ACVET PERU E.I.R.L. | G62: SALDO A FAVOR PE S06734 | I62: PEN | J62: -23.63 | L62: 23.63 | M62: -23.63 | O62: PEREIRA FUENTES, EIGLY YARITZA
A63: BCP01/2025/07528 | B63: BCP01/2025/07528 | C63: 45894 | E63: 1220001 ANTICIPOS CLIENTES NACIONAL M.N. | F63: HUAMANI CONSA YOLANDA | G63: SALDO A FAVOR | I63: PEN | J63: -129.8 | L63: 129.8 | M63: -129.8 | O63: PEREIRA FUENTES, EIGLY YARITZA
A64: BCP01/2025/07444 | B64: BCP01/2025/07444 | C64: 45891 | E64: 1220001 ANTICIPOS CLIENTES NACIONAL M.N. | F64: EMPRESA COMERCIALIZADORA DE INSUMOS Y PRODUCTOS AGROPECUARIOS Y TRANSPORTES S.R.L. | G64: SALDO A FAVOR | I64: PEN | J64: -670.73 | L64: 670.73 | M64: -670.73 | O64: PEREIRA FUENTES, EIGLY YARITZA
A65: BBVA1/2025/02501 | B65: BBVA1/2025/02501 | C65: 45882 | E65: 1220001 ANTICIPOS CLIENTES NACIONAL M.N. | F65: AGROVETERINARIA Y MULTISERVICIOS "DAGA" SOCIEDAD COMERCIAL DE RESPONSABILIDAD LIMITADA | G65: Saldo a favor | I65: PEN | J65: -9 | L65: 9 | M65: -9 | O65: MONTERO VILCAS, JOSE GORGE
A66: BBVA1/2025/02309 | B66: BBVA1/2025/02309 | C66: 45868 | E66: 1220001 ANTICIPOS CLIENTES NACIONAL M.N. | F66: CORPORACION AGROINDUSTRIAL SAN BERNARDO SAC - AGROCORP SAN BERNARDO | G66: SALDO A FAVOR | I66: PEN | J66: -363.99 | L66: 363.99 | M66: -363.99 | O66: MONTERO VILCAS, JOSE GORGE
A67: BCP01/2025/04942 | B67: BCP01/2025/04942 | C67: 45831 | E67: 1220001 ANTICIPOS CLIENTES NACIONAL M.N. | F67: PUBLIRUTS 78 S.A.C. | G67: ABONO POR IDENTIFICAR A FAVOR | I67: PEN | J67: -17 | L67: 17 | M67: -17 | O67: PEREIRA FUENTES, EIGLY YARITZA
A68: IBK02/2025/01209 | B68: IBK02/2025/01209 | C68: 45824 | E68: 1220001 ANTICIPOS CLIENTES NACIONAL M.N. | F68: SOLUTION WASI E.I.R.L. | G68: saldo a favor | I68: PEN | J68: -14.12 | L68: 14.12 | M68: -14.12 | O68: MONTERO VILCAS, JOSE GORGE
A69: BCP01/2025/04270 | B69: BCP01/2025/04270 | C69: 45813 | E69: 1220001 ANTICIPOS CLIENTES NACIONAL M.N. | F69: ESPECIALIDADES VETERINARIAS E.I.R.L. | G69: ADELANTO PEDIDO SHARON | I69: PEN | J69: -1417.47 | L69: 1417.47 | M69: -1417.47 | O69: BARCENA BRAGA, KATTYA ADELAIDA
A70: BCP01/2025/04121 | B70: BCP01/2025/04121 | C70: 45806 | E70: 1220001 ANTICIPOS CLIENTES NACIONAL M.N. | F70: CASA DEL BUEN CRIADOR E.I.R.L. | G70: SALDO A FAVOR | I70: PEN | J70: -158.62 | L70: 158.62 | M70: -158.62 | O70: PEREIRA FUENTES, EIGLY YARITZA
A71: PAPANT/2025/02388 (F F01-00001235) | B71: PAPANT/2025/02388 | C71: 45805 | D71: 45805 | E71: 1220001 ANTICIPOS CLIENTES NACIONAL M.N. | F71: VETERINARIA SAN PABLO E.I.R.L. | G71: Pago de cliente S/ 3,613.31 - VETERINARIA SAN PABLO E.I.R.L. - 28/05/2025 | H71: F F01-00001235 | I71: PEN | J71: 3613.31 | K71: 3613.31 | M71: 3613.31 | O71: MONTERO VILCAS, JOSE GORGE
A72: BCP01/2025/04078 | B72: BCP01/2025/04078 | C72: 45805 | E72: 1220001 ANTICIPOS CLIENTES NACIONAL M.N. | F72: SERVISVET`S EL MINISTER.DE GANADERIA EIR | G72: SALDO A FAVOR | I72: PEN | J72: -128.45 | L72: 128.45 | M72: -128.45 | O72: PEREIRA FUENTES, EIGLY YARITZA
A73: PAPANT/2025/02173 (F F01-00001127) | B73: PAPANT/2025/02173 | C73: 45800 | D73: 45800 | E73: 1220001 ANTICIPOS CLIENTES NACIONAL M.N. | F73: BIOGENESIS PERU E.I.R.L. | G73: Pago de cliente S/ 258.53 - BIOGENESIS PERU E.I.R.L. - 23/05/2025 | H73: F F01-00001127 | I73: PEN | J73: 258.53 | K73: 258.53 | M73: 258.53 | O73: PEREIRA FUENTES, EIGLY YARITZA
A74: BCP01/2025/03041 | B74: BCP01/2025/03041 | C74: 45792 | E74: 1220001 ANTICIPOS CLIENTES NACIONAL M.N. | F74: IDROGO MEDINA JUAN CARLOS | G74: saldo a favor del cliente | I74: PEN | J74: -173.38 | L74: 173.38 | M74: -173.38 | O74: MONTERO VILCAS, JOSE GORGE
A75: BCP01/2025/02506 | B75: BCP01/2025/02506 | C75: 45783 | E75: 1220001 ANTICIPOS CLIENTES NACIONAL M.N. | F75: VETERINARIA SAN PABLO E.I.R.L. | G75: SALDO A FAVOR | I75: PEN | J75: -5537.79 | L75: 5537.79 | M75: -5537.79 | O75: PEREIRA FUENTES, EIGLY YARITZA
A76: BCP01/2025/02226 | B76: BCP01/2025/02226 | C76: 45771 | E76: 1220001 ANTICIPOS CLIENTES NACIONAL M.N. | F76: BIOGENESIS PERU E.I.R.L. | G76: SALDO PE 2944 | I76: PEN | J76: -291.21 | L76: 291.21 | M76: -291.21 | O76: PEREIRA FUENTES, EIGLY YARITZA
A77: BCP01/2025/01890 | B77: BCP01/2025/01890 | C77: 45754 | E77: 1220001 ANTICIPOS CLIENTES NACIONAL M.N. | F77: AGROVET LOS ANDES SOCIEDAD COMERCIAL DE RESPONSABILIDAD LIMITADA - AGROVET LOS ANDES S.R.L. | G77: ABONO DE LOS ANDES SIN IDENT | I77: PEN | J77: -700 | L77: 700 | M77: -700 | O77: BARCENA BRAGA, KATTYA ADELAIDA
A78: BCP01/2025/01410 | B78: BCP01/2025/01410 | C78: 45733 | E78: 1220001 ANTICIPOS CLIENTES NACIONAL M.N. | F78: IDROGO MEDINA JUAN CARLOS | G78: IDROGO MEDINA JUAN CARLOS - S01911 | I78: PEN | J78: -3001.11 | L78: 3001.11 | M78: -3001.11 | O78: MONTERO VILCAS, JOSE GORGE
A79: BCP01/2025/01222 | B79: BCP01/2025/01222 | C79: 45726 | E79: 1220001 ANTICIPOS CLIENTES NACIONAL M.N. | F79: AGROVET LOS ANDES SOCIEDAD COMERCIAL DE RESPONSABILIDAD LIMITADA - AGROVET LOS ANDES S.R.L. | G79: AGROVET LOS ANDES ABONO NO IDE. | I79: PEN | J79: -600 | L79: 600 | M79: -600 | O79: BARCENA BRAGA, KATTYA ADELAIDA
A80: BCP01/2025/01003 | B80: BCP01/2025/01003 | C80: 45715 | E80: 1220001 ANTICIPOS CLIENTES NACIONAL M.N. | F80: SALAZAR ORTIZ DE EDUARDO DANITZA C. | G80: SALDO DE PE S01221 | I80: PEN | J80: -270 | L80: 270 | M80: -270 | O80: MONTERO VILCAS, JOSE GORGE
A81: BCP01/2025/00996 | B81: BCP01/2025/00996 | C81: 45715 | E81: 1220001 ANTICIPOS CLIENTES NACIONAL M.N. | F81: AGRIVET E INVERSIONES S.A.C. | G81: SALDO PE S01305 | I81: PEN | J81: -285.32 | L81: 285.32 | M81: -285.32 | O81: BARCENA BRAGA, KATTYA ADELAIDA
A82: BCP01/2025/00652 | B82: BCP01/2025/00652 | C82: 45702 | E82: 1220001 ANTICIPOS CLIENTES NACIONAL M.N. | F82: HERRERA CASTRO, RICK GOLDER PAULO | G82: SALDO A FAVOR | I82: PEN | J82: -12 | L82: 12 | M82: -12 | O82: BARCENA BRAGA, KATTYA ADELAIDA
A83: BCP01/2025/00617 | B83: BCP01/2025/00617 | C83: 45701 | E83: 1220001 ANTICIPOS CLIENTES NACIONAL M.N. | F83: DISTRIBUIDORA EL ESTABLO E. I. R. L. | G83: SALDO PE S00872 | I83: PEN | J83: -153.84 | L83: 153.84 | M83: -153.84 | O83: BARCENA BRAGA, KATTYA ADELAIDA
A84: BCP01/2025/00090 | B84: BCP01/2025/00090 | C84: 45665 | E84: 1220001 ANTICIPOS CLIENTES NACIONAL M.N. | F84: SANTO MARTIN S.A.C. | G84: Saldo pendiente: S/ 1,347.20 - DE SANTO MARTIN SAC | I84: PEN | J84: -72.89 | L84: 72.89 | M84: -72.89 | O84: PEREIRA FUENTES, EIGLY YARITZA
A85: DAP/2025/01/0003 (SALDOS INICIALES) | B85: DAP/2025/01/0003 | C85: 45658 | E85: 1220001 ANTICIPOS CLIENTES NACIONAL M.N. | F85: FARMACIAS VETERINARIAS DEL PERU S.A.C. | G85: PE 7243 | H85: SALDOS INICIALES | I85: PEN | J85: -1164.73 | L85: 1164.73 | M85: -1164.73 | O85: BARCENA BRAGA, KATTYA ADELAIDA
A86: DAP/2025/01/0003 (SALDOS INICIALES) | B86: DAP/2025/01/0003 | C86: 45658 | E86: 1220001 ANTICIPOS CLIENTES NACIONAL M.N. | F86: VETERINARIA SULLANA S.R.L. | G86: ABONO PE 5547 - VETERINARIA SULLANA | H86: SALDOS INICIALES | I86: PEN | J86: -1104.19 | L86: 1104.19 | M86: -1104.19 | O86: BARCENA BRAGA, KATTYA ADELAIDA
A87: DAP/2025/01/0003 (SALDOS INICIALES) | B87: DAP/2025/01/0003 | C87: 45658 | E87: 1220001 ANTICIPOS CLIENTES NACIONAL M.N. | F87: NOBLEJAS FLORIDO WENDY GISSELA | G87: ABONO PE 5152 - WENDY NOBLEJAS | H87: SALDOS INICIALES | I87: PEN | J87: -1048.26 | L87: 1048.26 | M87: -1048.26 | O87: BARCENA BRAGA, KATTYA ADELAIDA
A88: DAP/2025/01/0003 (SALDOS INICIALES) | B88: DAP/2025/01/0003 | C88: 45658 | E88: 1220001 ANTICIPOS CLIENTES NACIONAL M.N. | F88: CORPORACION AGROINDUSTRIAL SAN BERNARDO SAC - AGROCORP SAN BERNARDO | G88: PE 6183 | H88: SALDOS INICIALES | I88: PEN | J88: -238.36 | L88: 238.36 | M88: -238.36 | O88: BARCENA BRAGA, KATTYA ADELAIDA
A89: DAP/2025/01/0003 (SALDOS INICIALES) | B89: DAP/2025/01/0003 | C89: 45658 | E89: 1220001 ANTICIPOS CLIENTES NACIONAL M.N. | F89: AGRONEGOCIOS MUNDO RURAL EMPRESA INDIVIDUAL DE RESPONSABILIDAD LIMITADA | G89: PE 2934 AGRONEGOCIOS MUNDO RURAL EMPRESA INDIVIDUA | H89: SALDOS INICIALES | I89: PEN | J89: -232.58 | L89: 232.58 | M89: -232.58 | O89: BARCENA BRAGA, KATTYA ADELAIDA
A90: DAP/2025/01/0003 (SALDOS INICIALES) | B90: DAP/2025/01/0003 | C90: 45658 | E90: 1220001 ANTICIPOS CLIENTES NACIONAL M.N. | F90: DISTRIBUCIONES VETERINARIAS LA TORRE S.A.C. | G90: PE 3006 | H90: SALDOS INICIALES | I90: PEN | J90: -94.43 | L90: 94.43 | M90: -94.43 | O90: BARCENA BRAGA, KATTYA ADELAIDA
A91: DAP/2025/01/0003 (SALDOS INICIALES) | B91: DAP/2025/01/0003 | C91: 45658 | E91: 1220001 ANTICIPOS CLIENTES NACIONAL M.N. | F91: AGROVET EL NORTEÑO E.I.R.L. | G91: PE 7114 | H91: SALDOS INICIALES | I91: PEN | J91: -90 | L91: 90 | M91: -90 | O91: BARCENA BRAGA, KATTYA ADELAIDA
A92: DAP/2025/01/0003 (SALDOS INICIALES) | B92: DAP/2025/01/0003 | C92: 45658 | E92: 1220001 ANTICIPOS CLIENTES NACIONAL M.N. | F92: GRUPO CONSORCIO VETERINARIO S.A.C. | G92: ABONO DE PROTESTO QUEDO A FAVOR | H92: SALDOS INICIALES | I92: PEN | J92: -82.8 | L92: 82.8 | M92: -82.8 | O92: BARCENA BRAGA, KATTYA ADELAIDA
A93: DAP/2025/01/0003 (SALDOS INICIALES) | B93: DAP/2025/01/0003 | C93: 45658 | E93: 1220001 ANTICIPOS CLIENTES NACIONAL M.N. | F93: SERVISVET`S EL MINISTER.DE GANADERIA EIR | G93: PE 7287 | H93: SALDOS INICIALES | I93: PEN | J93: -59.44 | L93: 59.44 | M93: -59.44 | O93: BARCENA BRAGA, KATTYA ADELAIDA
A94: DAP/2025/01/0003 (SALDOS INICIALES) | B94: DAP/2025/01/0003 | C94: 45658 | E94: 1220001 ANTICIPOS CLIENTES NACIONAL M.N. | F94: AGUIVET S.A.C. | G94: PE 2131 AGUIVET S.A.C. | H94: SALDOS INICIALES | I94: PEN | J94: -53.35 | L94: 53.35 | M94: -53.35 | O94: BARCENA BRAGA, KATTYA ADELAIDA
A95: DAP/2025/01/0003 (SALDOS INICIALES) | B95: DAP/2025/01/0003 | C95: 45658 | E95: 1220001 ANTICIPOS CLIENTES NACIONAL M.N. | F95: SANTO MARTIN S.A.C. | G95: PE 6354 | H95: SALDOS INICIALES | I95: PEN | J95: -43.68 | L95: 43.68 | M95: -43.68 | O95: BARCENA BRAGA, KATTYA ADELAIDA
A96: DAP/2025/01/0003 (SALDOS INICIALES) | B96: DAP/2025/01/0003 | C96: 45658 | E96: 1220001 ANTICIPOS CLIENTES NACIONAL M.N. | F96: HUAMANI CONSA YOLANDA | G96: PE 2898 HUAMANI CONSA YOLANDA | H96: SALDOS INICIALES | I96: PEN | J96: -35.52 | L96: 35.52 | M96: -35.52 | O96: BARCENA BRAGA, KATTYA ADELAIDA
... A98: DAP/2025/01/0003 (SALDOS INICIALES) | B98: DAP/2025/01/0003 | C98: 45658 | E98: 1220001 ANTICIPOS CLIENTES NACIONAL M.N. | F98: BIOGENESIS PERU E.I.R.L. | G98: PE 7180 | H98: SALDOS INICIALES | I98: PEN | J98: -12.55 | L98: 12.55 | M98: -12.55 | O98: BARCENA BRAGA, KATTYA ADELAIDA
M99: =SUM(M3:M98) -> -84337.95

Sheet 122xx2
A1: Asiento contable | B1: Número | C1: Fecha | D1: Fecha de vencimiento | E1: Cuenta | F1: Socio | G1: Etiqueta | H1: Referencia | I1: Moneda | J1: Importe en moneda | K1: Debe | L1: Haber | M1: Saldo | N1: Conciliación | O1: Creado por
A2: 1220002 ANTICIPOS CLIENTES NACIONAL M.E. (4)
A3: IBK01/2025/01119 | B3: IBK01/2025/01119 | C3: 46097 | E3: 1220002 ANTICIPOS CLIENTES NACIONAL M.E. | F3: OLEA ESTRADA CESAR AUGUSTO | G3: ABONO COMPRA DE VEH. | I3: USD | J3: -8400 | L3: 29005.2 | M3: -29005.2 | N3: A151999 | O3: BARCENA BRAGA, KATTYA ADELAIDA
M5: =SUM(M3:M4) -> -29005.2

Sheet 122xx3
A1: Asiento contable | B1: Número | C1: Fecha | D1: Fecha de vencimiento | E1: Cuenta | F1: Socio | G1: Etiqueta | H1: Referencia | I1: Moneda | J1: Importe en moneda | K1: Debe | L1: Haber | M1: Saldo | N1: Conciliación | O1: Creado por
A2: 1220003 ANTICIPOS CLIENTES DEL EXTERIOR (442)
A3: BCP03/2025/00524 | B3: BCP03/2025/00524 | C3: 46106 | E3: 1220003 ANTICIPOS CLIENTES DEL EXTERIOR | F3: INVERSIONES MONTECO DE CARTAGO S.A. | G3: saldo a favor | I3: USD | J3: -3779.99 | L3: 13093.88 | M3: -13093.88 | O3: MONTERO VILCAS, JOSE GORGE
A4: BCP03/2025/00517 | B4: BCP03/2025/00517 | C4: 46098 | E4: 1220003 ANTICIPOS CLIENTES DEL EXTERIOR | F4: GANESHA AGROFARMA | G4: saldo a favor | I4: USD | J4: -28900 | L4: 99387.1 | M4: -99387.1 | O4: MONTERO VILCAS, JOSE GORGE
A5: BCP03/2025/00515 | B5: BCP03/2025/00515 | C5: 46098 | E5: 1220003 ANTICIPOS CLIENTES DEL EXTERIOR | F5: GANESHA AGROFARMA | G5: saldo a favor | I5: USD | J5: -36960 | L5: 127105.44 | M5: -127105.44 | O5: MONTERO VILCAS, JOSE GORGE
A6: BCP02/2025/02356 | B6: BCP02/2025/02356 | C6: 46098 | E6: 1220003 ANTICIPOS CLIENTES DEL EXTERIOR | F6: STICHTING ANIMAL HEALTH MISSION SURINAME (S.A.H.M.S) | G6: saldo a favor | I6: USD | J6: -9124.23 | L6: 31378.23 | M6: -31378.23 | O6: MONTERO VILCAS, JOSE GORGE
A7: PAPANT/2025/07168 (F F15-00000333) | B7: PAPANT/2025/07168 | C7: 46073 | D7: 46073 | E7: 1220003 ANTICIPOS CLIENTES DEL EXTERIOR | F7: ISV - INSUMOS Y SANIDAD VETERINARIA SRL | G7: Pago de cliente $ 45,381.50 - ISV - INSUMOS Y SANIDAD VETERINARIA SRL - 20/02/2026 | H7: F F15-00000333 | I7: USD | J7: 45381.5 | K7: 152754.13 | M7: 152754.13 | O7: MONTERO VILCAS, JOSE GORGE
A8: CAMBI/2026/02/0813 | B8: CAMBI/2026/02/0813 | C8: 46073 | E8: 1220003 ANTICIPOS CLIENTES DEL EXTERIOR | F8: ISV - INSUMOS Y SANIDAD VETERINARIA SRL | G8: Diferencia en tipo de cambio de moneda | I8: USD | L8: 191.35 | M8: -191.35 | O8: MONTERO VILCAS, JOSE GORGE
A9: CAMBI/2026/02/0812 | B9: CAMBI/2026/02/0812 | C9: 46073 | E9: 1220003 ANTICIPOS CLIENTES DEL EXTERIOR | F9: ISV - INSUMOS Y SANIDAD VETERINARIA SRL | G9: Diferencia en tipo de cambio de moneda | I9: USD | K9: 20 | M9: 20 | O9: MONTERO VILCAS, JOSE GORGE
A10: CAMBI/2026/02/0811 | B10: CAMBI/2026/02/0811 | C10: 46073 | E10: 1220003 ANTICIPOS CLIENTES DEL EXTERIOR | F10: ISV - INSUMOS Y SANIDAD VETERINARIA SRL | G10: Diferencia en tipo de cambio de moneda | I10: USD | L10: 140 | M10: -140 | O10: MONTERO VILCAS, JOSE GORGE
A11: CAMBI/2026/02/0810 | B11: CAMBI/2026/02/0810 | C11: 46073 | E11: 1220003 ANTICIPOS CLIENTES DEL EXTERIOR | F11: ISV - INSUMOS Y SANIDAD VETERINARIA SRL | G11: Diferencia en tipo de cambio de moneda | I11: USD | L11: 23.76 | M11: -23.76 | O11: MONTERO VILCAS, JOSE GORGE
A12: BCP03/2025/00495 | B12: BCP03/2025/00495 | C12: 46071 | E12: 1220003 ANTICIPOS CLIENTES DEL EXTERIOR | F12: ISV - INSUMOS Y SANIDAD VETERINARIA SRL | G12: saldo a favor | I12: USD | J12: -10744.36 | L12: 35972.12 | M12: -35972.12 | O12: MONTERO VILCAS, JOSE GORGE
A13: BCP03/2025/00489 | B13: BCP03/2025/00489 | C13: 46065 | E13: 1220003 ANTICIPOS CLIENTES DEL EXTERIOR | F13: MONTECO ANIMAL HEALTH S.A. DE C.V. | G13: saldo a favor | I13: USD | J13: -26.52 | L13: 89.18 | M13: -89.18 | N13: A150401 | O13: MONTERO VILCAS, JOSE GORGE
A14: BCP03/2025/00482 | B14: BCP03/2025/00482 | C14: 46059 | E14: 1220003 ANTICIPOS CLIENTES DEL EXTERIOR | F14: ISV - INSUMOS Y SANIDAD VETERINARIA SRL | G14: SALDO A FAVOR | I14: USD | J14: -10000 | L14: 33680 | M14: -33680 | O14: MONTERO VILCAS, JOSE GORGE
A15: BCP03/2025/00480 | B15: BCP03/2025/00480 | C15: 46059 | E15: 1220003 ANTICIPOS CLIENTES DEL EXTERIOR | F15: GANESHA AGROFARMA | G15: SALDO A AFAVOR | I15: USD | J15: -37500 | L15: 126300 | M15: -126300 | O15: MONTERO VILCAS, JOSE GORGE
A16: BCP03/2025/00476 | B16: BCP03/2025/00476 | C16: 46056 | E16: 1220003 ANTICIPOS CLIENTES DEL EXTERIOR | F16: QUALITY CO. FOR VET.MED. TRADE | G16: SALDO A FAVOR | I16: USD | J16: -23960 | L16: 80721.24 | M16: -80721.24 | O16: MONTERO VILCAS, JOSE GORGE
A17: BCP03/2025/00464 | B17: BCP03/2025/00464 | C17: 46051 | E17: 1220003 ANTICIPOS CLIENTES DEL EXTERIOR | F17: GANESHA AGROFARMA | G17: SALDO A FAVOR | I17: USD | J17: -38700 | L17: 129451.5 | M17: -129451.5 | O17: MONTERO VILCAS, JOSE GORGE
A18: BCP03/2025/00462 | B18: BCP03/2025/00462 | C18: 46051 | E18: 1220003 ANTICIPOS CLIENTES DEL EXTERIOR | F18: MINH HUNG AGRICULTURAL MATERIALS TRADING AND SERVICE CO., LTD. | G18: SALDO A FAVOR | I18: USD | J18: -49823.37 | L18: 166659.17 | M18: -166659.17 | O18: MONTERO VILCAS, JOSE GORGE
A19: BCP03/2025/00461 | B19: BCP03/2025/00461 | C19: 46051 | E19: 1220003 ANTICIPOS CLIENTES DEL EXTERIOR | F19: MINH HUNG AGRICULTURAL MATERIALS TRADING AND SERVICE CO., LTD. | G19: saldo a favor | I19: USD | J19: -69046.69 | L19: 230961.18 | M19: -230961.18 | O19: MONTERO VILCAS, JOSE GORGE
A20: BCP03/2025/00468 | B20: BCP03/2025/00468 | C20: 46050 | E20: 1220003 ANTICIPOS CLIENTES DEL EXTERIOR | F20: AL MASEELA PHARMACEUTICAL COMPANY W.L.L. | G20: saldo a favor | I20: USD | J20: -12070.36 | L20: 40459.84 | M20: -40459.84 | O20: MONTERO VILCAS, JOSE GORGE
A21: BCP03/2025/00466 | B21: BCP03/2025/00466 | C21: 46050 | E21: 1220003 ANTICIPOS CLIENTES DEL EXTERIOR | F21: ISV - INSUMOS Y SANIDAD VETERINARIA SRL | G21: saldo a favor | I21: USD | J21: -10000 | L21: 33520 | M21: -33520 | O21: MONTERO VILCAS, JOSE GORGE
A22: PAPANT/2025/06526 (F F15-00000321) | B22: PAPANT/2025/06526 | C22: 46044 | D22: 46044 | E22: 1220003 ANTICIPOS CLIENTES DEL EXTERIOR | F22: ISV - INSUMOS Y SANIDAD VETERINARIA SRL | G22: Pago de cliente $ 54,956.36 - ISV - INSUMOS Y SANIDAD VETERINARIA SRL - 22/01/2026 | H22: F F15-00000321 | I22: USD | J22: 54956.36 | K22: 184598.41 | M22: 184598.41 | O22: MONTERO VILCAS, JOSE GORGE
A23: CAMBI/2026/01/0711 | B23: CAMBI/2026/01/0711 | C23: 46044 | E23: 1220003 ANTICIPOS CLIENTES DEL EXTERIOR | F23: ISV - INSUMOS Y SANIDAD VETERINARIA SRL | G23: Diferencia en tipo de cambio de moneda | I23: USD | L23: 0.01 | M23: -0.01 | O23: MONTERO VILCAS, JOSE GORGE
A24: CAMBI/2026/01/0711 | B24: CAMBI/2026/01/0711 | C24: 46044 | E24: 1220003 ANTICIPOS CLIENTES DEL EXTERIOR | F24: ISV - INSUMOS Y SANIDAD VETERINARIA SRL | G24: Diferencia en tipo de cambio de moneda | I24: USD | K24: 2.98 | M24: 2.98 | O24: MONTERO VILCAS, JOSE GORGE
A25: CAMBI/2026/01/0710 | B25: CAMBI/2026/01/0710 | C25: 46044 | E25: 1220003 ANTICIPOS CLIENTES DEL EXTERIOR | F25: ISV - INSUMOS Y SANIDAD VETERINARIA SRL | G25: Diferencia en tipo de cambio de moneda | I25: USD | K25: 17.78 | M25: 17.78 | O25: MONTERO VILCAS, JOSE GORGE
A26: CAMBI/2026/01/0709 | B26: CAMBI/2026/01/0709 | C26: 46044 | E26: 1220003 ANTICIPOS CLIENTES DEL EXTERIOR | F26: ISV - INSUMOS Y SANIDAD VETERINARIA SRL | G26: Diferencia en tipo de cambio de moneda | I26: USD | K26: 183.21 | M26: 183.21 | O26: MONTERO VILCAS, JOSE GORGE
A27: CAMBI/2026/01/0708 | B27: CAMBI/2026/01/0708 | C27: 46044 | E27: 1220003 ANTICIPOS CLIENTES DEL EXTERIOR | F27: ISV - INSUMOS Y SANIDAD VETERINARIA SRL | G27: Diferencia en tipo de cambio de moneda | I27: USD | K27: 368.2 | M27: 368.2 | O27: MONTERO VILCAS, JOSE GORGE
A28: CAMBI/2026/01/0707 | B28: CAMBI/2026/01/0707 | C28: 46044 | E28: 1220003 ANTICIPOS CLIENTES DEL EXTERIOR | F28: ISV - INSUMOS Y SANIDAD VETERINARIA SRL | G28: Diferencia en tipo de cambio de moneda | I28: USD | K28: 159.43 | M28: 159.43 | O28: MONTERO VILCAS, JOSE GORGE
A29: BCP03/2025/00509 | B29: BCP03/2025/00509 | C29: 46044 | E29: 1220003 ANTICIPOS CLIENTES DEL EXTERIOR | F29: QUALITY CO. FOR VET.MED. TRADE | G29: saldo a favor | I29: USD | J29: -28195 | L29: 94707.01 | M29: -94707.01 | O29: MONTERO VILCAS, JOSE GORGE
A30: BCP03/2025/00447 | B30: BCP03/2025/00447 | C30: 46042 | E30: 1220003 ANTICIPOS CLIENTES DEL EXTERIOR | F30: ISV - INSUMOS Y SANIDAD VETERINARIA SRL | G30: saldo a favor | I30: USD | J30: -10000 | L30: 33660 | M30: -33660 | O30: MONTERO VILCAS, JOSE GORGE
A31: BCP03/2025/00438 | B31: BCP03/2025/00438 | C31: 46036 | E31: 1220003 ANTICIPOS CLIENTES DEL EXTERIOR | F31: ISV - INSUMOS Y SANIDAD VETERINARIA SRL | G31: saldo a favor | I31: USD | J31: -8887.25 | L31: 29870.05 | M31: -29870.05 | O31: MONTERO VILCAS, JOSE GORGE
A32: BCP03/2025/00436 | B32: BCP03/2025/00436 | C32: 46036 | E32: 1220003 ANTICIPOS CLIENTES DEL EXTERIOR | F32: ISV - INSUMOS Y SANIDAD VETERINARIA SRL | G32: Incoming payment From 8217725021, I.S.V. INSUMOS Y SANIDAD VETERINAR+ Reference 2026011400320299 | I32: USD | J32: -6241.3 | L32: 20977.01 | M32: -20977.01 | O32: MONTERO VILCAS, JOSE GORGE
A33: BCP02/2025/02041 | B33: BCP02/2025/02041 | C33: 46036 | E33: 1220003 ANTICIPOS CLIENTES DEL EXTERIOR | F33: DUGGAN VETERINARY | G33: saldo a favor | I33: USD | J33: -30159.08 | L33: 101364.67 | M33: -101364.67 | O33: MONTERO VILCAS, JOSE GORGE
A34: PAPANT/2025/06393 (F F15-00000295) | B34: PAPANT/2025/06393 | C34: 46021 | D34: 46021 | E34: 1220003 ANTICIPOS CLIENTES DEL EXTERIOR | F34: ARMSTRONG HEALTH CARE INC. | G34: Pago de cliente $ 47,562.04 - ARMSTRONG HEALTH CARE INC. - 30/12/2025 | H34: F F15-00000295 | I34: USD | J34: 47562.04 | K34: 160379.2 | M34: 160379.2 | O34: MONTERO VILCAS, JOSE GORGE
A35: CAMBI/2025/12/2043 | B35: CAMBI/2025/12/2043 | C35: 46021 | E35: 1220003 ANTICIPOS CLIENTES DEL EXTERIOR | F35: ARMSTRONG HEALTH CARE INC. | G35: Diferencia en tipo de cambio de moneda | I35: USD | K35: 2670.3 | M35: 2670.3 | O35: MONTERO VILCAS, JOSE GORGE
A36: CAMBI/2025/12/2042 | B36: CAMBI/2025/12/2042 | C36: 46021 | E36: 1220003 ANTICIPOS CLIENTES DEL EXTERIOR | F36: ARMSTRONG HEALTH CARE INC. | G36: Diferencia en tipo de cambio de moneda | I36: USD | K36: 3990.8 | M36: 3990.8 | O36: MONTERO VILCAS, JOSE GORGE
A37: CAMBI/2025/12/2041 | B37: CAMBI/2025/12/2041 | C37: 46021 | E37: 1220003 ANTICIPOS CLIENTES DEL EXTERIOR | F37: ARMSTRONG HEALTH CARE INC. | G37: Diferencia en tipo de cambio de moneda | I37: USD | K37: 161.81 | M37: 161.81 | O37: MONTERO VILCAS, JOSE GORGE
A38: BCP03/2025/00434 | B38: BCP03/2025/00434 | C38: 46020 | E38: 1220003 ANTICIPOS CLIENTES DEL EXTERIOR | F38: MINH HUNG AGRICULTURAL MATERIALS TRADING AND SERVICE CO., LTD. | G38: saldo a favor final al 13.01.26 | I38: USD | J38: -10620.85 | L38: 35781.66 | M38: -35781.66 | O38: MONTERO VILCAS, JOSE GORGE
A39: BCP02/2025/01941 | B39: BCP02/2025/01941 | C39: 46020 | E39: 1220003 ANTICIPOS CLIENTES DEL EXTERIOR | F39: AL FIAFY FOR VETERINARY CARE | G39: saldo a favor al dia 13.01 | I39: USD | J39: -36283.14 | L39: 122237.89 | M39: -122237.89 | O39: MONTERO VILCAS, JOSE GORGE
A40: PAPANT/2025/05847 (F F15-00000270) | B40: PAPANT/2025/05847 | C40: 46014 | D40: 46014 | E40: 1220003 ANTICIPOS CLIENTES DEL EXTERIOR | F40: GANESHA AGROFARMA | G40: Pago de cliente $ 102,175.92 - GANESHA AGROFARMA - 23/12/2025 | H40: F F15-00000270 | I40: USD | J40: 102175.92 | K40: 344537.2 | M40: 344537.2 | O40: MONTERO VILCAS, JOSE GORGE
A41: CAMBI/2025/12/0807 | B41: CAMBI/2025/12/0807 | C41: 46014 | E41: 1220003 ANTICIPOS CLIENTES DEL EXTERIOR | F41: GANESHA AGROFARMA | G41: Diferencia en tipo de cambio de moneda | I41: USD | L41: 15.05 | M41: -15.05 | O41: MONTERO VILCAS, JOSE GORGE
A42: CAMBI/2025/12/0806 | B42: CAMBI/2025/12/0806 | C42: 46014 | E42: 1220003 ANTICIPOS CLIENTES DEL EXTERIOR | F42: GANESHA AGROFARMA | G42: Diferencia en tipo de cambio de moneda | I42: USD | L42: 36 | M42: -36 | O42: MONTERO VILCAS, JOSE GORGE
A43: CAMBI/2025/12/0805 | B43: CAMBI/2025/12/0805 | C43: 46014 | E43: 1220003 ANTICIPOS CLIENTES DEL EXTERIOR | F43: GANESHA AGROFARMA | G43: Diferencia en tipo de cambio de moneda | I43: USD | K43: 2847 | M43: 2847 | O43: MONTERO VILCAS, JOSE GORGE
A44: CAMBI/2025/12/0804 | B44: CAMBI/2025/12/0804 | C44: 46014 | E44: 1220003 ANTICIPOS CLIENTES DEL EXTERIOR | F44: GANESHA AGROFARMA | G44: Diferencia en tipo de cambio de moneda | I44: USD | K44: 5199.3 | M44: 5199.3 | O44: MONTERO VILCAS, JOSE GORGE
A45: CAMBI/2025/12/0803 | B45: CAMBI/2025/12/0803 | C45: 46014 | E45: 1220003 ANTICIPOS CLIENTES DEL EXTERIOR | F45: GANESHA AGROFARMA | G45: Diferencia en tipo de cambio de moneda | I45: USD | K45: 1094.9 | M45: 1094.9 | O45: MONTERO VILCAS, JOSE GORGE
A46: SCT02/2025/00923 | B46: SCT02/2025/00923 | C46: 46010 | E46: 1220003 ANTICIPOS CLIENTES DEL EXTERIOR | F46: VETERMEX ANIMAL HEALTH HONDURAS SA | G46: saldo a favor | I46: USD | J46: -599900 | L46: 2022262.9 | M46: -2022262.9 | O46: MONTERO VILCAS, JOSE GORGE
A47: BCP03/2025/00424 | B47: BCP03/2025/00424 | C47: 46010 | E47: 1220003 ANTICIPOS CLIENTES DEL EXTERIOR | F47: ISV - INSUMOS Y SANIDAD VETERINARIA SRL | G47: saldo a favor | I47: USD | J47: -15267 | L47: 51465.06 | M47: -51465.06 | O47: MONTERO VILCAS, JOSE GORGE
A48: PAPANT/2025/05593 (F D15-00000034) | B48: PAPANT/2025/05593 | C48: 46007 | D48: 46007 | E48: 1220003 ANTICIPOS CLIENTES DEL EXTERIOR | F48: STICHTING ANIMAL HEALTH MISSION SURINAME (S.A.H.M.S) | G48: Pago de cliente $ 750.00 - STICHTING ANIMAL HEALTH MISSION SURINAME (S.A.H.M.S) - 16/12/2025 | H48: F D15-00000034 | I48: USD | J48: 750 | K48: 2531.25 | M48: 2531.25 | O48: MONTERO VILCAS, JOSE GORGE
A49: PAPANT/2025/05592 (F F15-00000261) | B49: PAPANT/2025/05592 | C49: 46007 | D49: 46007 | E49: 1220003 ANTICIPOS CLIENTES DEL EXTERIOR | F49: STICHTING ANIMAL HEALTH MISSION SURINAME (S.A.H.M.S) | G49: Pago de cliente $ 15,844.51 - STICHTING ANIMAL HEALTH MISSION SURINAME (S.A.H.M.S) - 16/12/2025 | H49: F F15-00000261 | I49: USD | J49: 15844.51 | K49: 53475.22 | M49: 53475.22 | O49: MONTERO VILCAS, JOSE GORGE
A50: CAMBI/2025/12/0532 | B50: CAMBI/2025/12/0532 | C50: 46007 | E50: 1220003 ANTICIPOS CLIENTES DEL EXTERIOR | F50: STICHTING ANIMAL HEALTH MISSION SURINAME (S.A.H.M.S) | G50: Diferencia en tipo de cambio de moneda | I50: USD | L50: 51.75 | M50: -51.75 | O50: MONTERO VILCAS, JOSE GORGE
A51: CAMBI/2025/12/0531 | B51: CAMBI/2025/12/0531 | C51: 46007 | E51: 1220003 ANTICIPOS CLIENTES DEL EXTERIOR | F51: STICHTING ANIMAL HEALTH MISSION SURINAME (S.A.H.M.S) | G51: Diferencia en tipo de cambio de moneda | I51: USD | K51: 637.36 | M51: 637.36 | O51: MONTERO VILCAS, JOSE GORGE
A52: CAMBI/2025/12/0530 | B52: CAMBI/2025/12/0530 | C52: 46007 | E52: 1220003 ANTICIPOS CLIENTES DEL EXTERIOR | F52: STICHTING ANIMAL HEALTH MISSION SURINAME (S.A.H.M.S) | G52: Diferencia en tipo de cambio de moneda | I52: USD | K52: 87 | M52: 87 | O52: MONTERO VILCAS, JOSE GORGE
A53: BCP02/2025/01841 | B53: BCP02/2025/01841 | C53: 46003 | E53: 1220003 ANTICIPOS CLIENTES DEL EXTERIOR | F53: STICHTING ANIMAL HEALTH MISSION SURINAME (S.A.H.M.S) | G53: SALDO A FAVOR | I53: USD | J53: -16528.46 | L53: 55700.91 | M53: -55700.91 | O53: MONTERO VILCAS, JOSE GORGE
A54: PAPANT/2025/05504 (F F15-00000256) | B54: PAPANT/2025/05504 | C54: 46002 | D54: 46002 | E54: 1220003 ANTICIPOS CLIENTES DEL EXTERIOR | F54: GANESHA AGROFARMA | G54: Pago de cliente $ 46,406.75 - GANESHA AGROFARMA - 11/12/2025 | H54: F F15-00000256 | I54: USD | J54: 46406.75 | K54: 156762 | M54: 156762 | O54: MONTERO VILCAS, JOSE GORGE
A55: CAMBI/2025/12/0378 | B55: CAMBI/2025/12/0378 | C55: 46002 | E55: 1220003 ANTICIPOS CLIENTES DEL EXTERIOR | F55: GANESHA AGROFARMA | G55: Diferencia en tipo de cambio de moneda | I55: USD | K55: 2470.34 | M55: 2470.34 | O55: MONTERO VILCAS, JOSE GORGE
A56: CAMBI/2025/12/0377 | B56: CAMBI/2025/12/0377 | C56: 46002 | E56: 1220003 ANTICIPOS CLIENTES DEL EXTERIOR | F56: GANESHA AGROFARMA | G56: Diferencia en tipo de cambio de moneda | I56: USD | K56: 4071 | M56: 4071 | O56: MONTERO VILCAS, JOSE GORGE
A57: CAMBI/2025/12/0376 | B57: CAMBI/2025/12/0376 | C57: 46002 | E57: 1220003 ANTICIPOS CLIENTES DEL EXTERIOR | F57: GANESHA AGROFARMA | G57: Diferencia en tipo de cambio de moneda | I57: USD | K57: 1427.16 | M57: 1427.16 | O57: MONTERO VILCAS, JOSE GORGE
A58: BCP03/2025/00408 | B58: BCP03/2025/00408 | C58: 45999 | E58: 1220003 ANTICIPOS CLIENTES DEL EXTERIOR | F58: GANESHA AGROFARMA | G58: Saldo a favor | I58: USD | J58: -43700 | L58: 147225.3 | M58: -147225.3 | O58: MONTERO VILCAS, JOSE GORGE
A59: BCP03/2025/00397 | B59: BCP03/2025/00397 | C59: 45993 | E59: 1220003 ANTICIPOS CLIENTES DEL EXTERIOR | F59: ISV - INSUMOS Y SANIDAD VETERINARIA SRL | G59: saldo a favor | I59: USD | J59: -20455 | L59: 69076.54 | M59: -69076.54 | O59: MONTERO VILCAS, JOSE GORGE
A60: BCP03/2025/00386 | B60: BCP03/2025/00386 | C60: 45989 | E60: 1220003 ANTICIPOS CLIENTES DEL EXTERIOR | F60: GANESHA AGROFARMA | G60: saldo a favor | I60: USD | J60: -36000 | L60: 121356 | M60: -121356 | O60: MONTERO VILCAS, JOSE GORGE
A61: PAPANT/2025/05065 (F F15-00000199) | B61: PAPANT/2025/05065 | C61: 45968 | D61: 45968 | E61: 1220003 ANTICIPOS CLIENTES DEL EXTERIOR | F61: ISV - INSUMOS Y SANIDAD VETERINARIA SRL | G61: Pago de cliente $ 5.00 - ISV - INSUMOS Y SANIDAD VETERINARIA SRL - 07/11/2025 | H61: F F15-00000199 | I61: USD | J61: 5 | K61: 16.89 | M61: 16.89 | O61: MONTERO VILCAS, JOSE GORGE
A62: PAPANT/2025/05064 (F F15-00000208) | B62: PAPANT/2025/05064 | C62: 45968 | D62: 45968 | E62: 1220003 ANTICIPOS CLIENTES DEL EXTERIOR | F62: ISV - INSUMOS Y SANIDAD VETERINARIA SRL | G62: Pago de cliente $ 60.00 - ISV - INSUMOS Y SANIDAD VETERINARIA SRL - 07/11/2025 | H62: F F15-00000208 | I62: USD | J62: 60 | K62: 202.62 | M62: 202.62 | O62: MONTERO VILCAS, JOSE GORGE
A63: CAMBI/2025/11/0739 | B63: CAMBI/2025/11/0739 | C63: 45968 | E63: 1220003 ANTICIPOS CLIENTES DEL EXTERIOR | F63: ISV - INSUMOS Y SANIDAD VETERINARIA SRL | G63: Diferencia en tipo de cambio de moneda | I63: USD | L63: 0.01 | M63: -0.01 | O63: MONTERO VILCAS, JOSE GORGE
A64: BCP03/2025/00364 | B64: BCP03/2025/00364 | C64: 45968 | E64: 1220003 ANTICIPOS CLIENTES DEL EXTERIOR | F64: ISV - INSUMOS Y SANIDAD VETERINARIA SRL | G64: SALDO A FAVOR | I64: USD | J64: -8921.7 | L64: 30128.58 | M64: -30128.58 | O64: MONTERO VILCAS, JOSE GORGE
A65: BCP02/2025/01571 | B65: BCP02/2025/01571 | C65: 45960 | E65: 1220003 ANTICIPOS CLIENTES DEL EXTERIOR | F65: AL SALWA GOLD PROJECTS JOINT PARTNERSHIP | G65: saldo a favor | I65: USD | J65: -24000 | L65: 81456 | M65: -81456 | O65: MONTERO VILCAS, JOSE GORGE
A66: PAPANT/2025/04750 (F F15-00000209) | B66: PAPANT/2025/04750 | C66: 45946 | D66: 45946 | E66: 1220003 ANTICIPOS CLIENTES DEL EXTERIOR | F66: QUALITY CO. FOR VET.MED. TRADE | G66: Pago de cliente $ 80,942.19 - QUALITY CO. FOR VET.MED. TRADE - 16/10/2025 | H66: F F15-00000209 | I66: USD | J66: 80942.19 | K66: 276498.52 | M66: 276498.52 | O66: MONTERO VILCAS, JOSE GORGE
A67: CAMBI/2025/10/1220 | B67: CAMBI/2025/10/1220 | C67: 45946 | E67: 1220003 ANTICIPOS CLIENTES DEL EXTERIOR | F67: QUALITY CO. FOR VET.MED. TRADE | G67: Diferencia en tipo de cambio de moneda | I67: USD | K67: 2913.92 | M67: 2913.92 | O67: MONTERO VILCAS, JOSE GORGE
A68: PAPANT/2025/04530 (F F15-00000200) | B68: PAPANT/2025/04530 | C68: 45940 | D68: 45940 | E68: 1220003 ANTICIPOS CLIENTES DEL EXTERIOR | F68: ARMSTRONG HEALTH CARE INC. | G68: Pago de cliente $ 44,119.14 - ARMSTRONG HEALTH CARE INC. - 10/10/2025 | H68: F F15-00000200 | I68: USD | J68: 44119.14 | K68: 151902.2 | M68: 151902.2 | O68: MONTERO VILCAS, JOSE GORGE
A69: CAMBI/2025/10/0634 | B69: CAMBI/2025/10/0634 | C69: 45940 | E69: 1220003 ANTICIPOS CLIENTES DEL EXTERIOR | F69: ARMSTRONG HEALTH CARE INC. | G69: Diferencia en tipo de cambio de moneda | I69: USD | K69: 7101.99 | M69: 7101.99 | O69: MONTERO VILCAS, JOSE GORGE
A70: CAMBI/2025/10/0633 | B70: CAMBI/2025/10/0633 | C70: 45940 | E70: 1220003 ANTICIPOS CLIENTES DEL EXTERIOR | F70: ARMSTRONG HEALTH CARE INC. | G70: Diferencia en tipo de cambio de moneda | I70: USD | K70: 3213.96 | M70: 3213.96 | O70: MONTERO VILCAS, JOSE GORGE
A71: PAPANT/2025/07945 (F F15-00000348) | B71: PAPANT/2025/07945 | C71: 46100 | D71: 46100 | E71: 1220003 ANTICIPOS CLIENTES DEL EXTERIOR | F71: BAROVET CO., LTD. | G71: Pago de cliente $ 30,164.40 - BAROVET CO., LTD. - 19/03/2026 | H71: F F15-00000348 | I71: USD | J71: 30164.4 | K71: 103614.71 | M71: 103614.71 | N71: A142946 | O71: MONTERO VILCAS, JOSE GORGE
A72: CAMBI/2026/03/0632 | B72: CAMBI/2026/03/0632 | C72: 46100 | E72: 1220003 ANTICIPOS CLIENTES DEL EXTERIOR | F72: BAROVET CO., LTD. | G72: Diferencia en tipo de cambio de moneda | I72: USD | K72: 10.47 | M72: 10.47 | N72: A142946 | O72: MONTERO VILCAS, JOSE GORGE
A73: CAMBI/2026/03/0631 | B73: CAMBI/2026/03/0631 | C73: 46100 | E73: 1220003 ANTICIPOS CLIENTES DEL EXTERIOR | F73: BAROVET CO., LTD. | G73: Diferencia en tipo de cambio de moneda | I73: USD | L73: 1055.76 | M73: -1055.76 | N73: A142946 | O73: MONTERO VILCAS, JOSE GORGE
A74: CAMBI/2026/03/0630 | B74: CAMBI/2026/03/0630 | C74: 46100 | E74: 1220003 ANTICIPOS CLIENTES DEL EXTERIOR | F74: BAROVET CO., LTD. | G74: Diferencia en tipo de cambio de moneda | I74: USD | L74: 623.24 | M74: -623.24 | N74: A142946 | O74: MONTERO VILCAS, JOSE GORGE
A75: BCP03/2025/00519 | B75: BCP03/2025/00519 | C75: 46098 | E75: 1220003 ANTICIPOS CLIENTES DEL EXTERIOR | F75: BAROVET CO., LTD. | G75: saldo a favor | I75: USD | J75: -15082.2 | L75: 51867.69 | M75: -51867.69 | N75: A142946 | O75: MONTERO VILCAS, JOSE GORGE
A76: BCP03/2025/00428 | B76: BCP03/2025/00428 | C76: 46034 | E76: 1220003 ANTICIPOS CLIENTES DEL EXTERIOR | F76: BAROVET CO., LTD. | G76: saldo a favor | I76: USD | J76: -15082.2 | L76: 50751.6 | M76: -50751.6 | N76: A142946 | O76: MONTERO VILCAS, JOSE GORGE
A77: BCP03/2025/00378 | B77: BCP03/2025/00378 | C77: 45982 | E77: 1220003 ANTICIPOS CLIENTES DEL EXTERIOR | F77: BAROVET CO., LTD. | G77: saldo a favor | I77: USD | J77: -12465 | L77: 42194.03 | M77: -42194.03 | N77: A142946 | O77: MONTERO VILCAS, JOSE GORGE
A78: BCP03/2025/00267 | B78: BCP03/2025/00267 | C78: 45938 | E78: 1220003 ANTICIPOS CLIENTES DEL EXTERIOR | F78: QUALITY CO. FOR VET.MED. TRADE | G78: Saldo a FAVOR | I78: USD | J78: -97069.6 | L78: 335084.26 | M78: -335084.26 | O78: MONTERO VILCAS, JOSE GORGE
A79: BCP03/2025/00252 | B79: BCP03/2025/00252 | C79: 45931 | E79: 1220003 ANTICIPOS CLIENTES DEL EXTERIOR | F79: MULTIPLE CHOICE FOR GENERAL TRADING | G79: Saldo a Favor | I79: USD | J79: -608.97 | L79: 2116.78 | M79: -2116.78 | O79: MONTERO VILCAS, JOSE GORGE
A80: BCP03/2025/00245 | B80: BCP03/2025/00245 | C80: 45929 | E80: 1220003 ANTICIPOS CLIENTES DEL EXTERIOR | F80: GANESHA AGROFARMA | G80: saldo a favor | I80: USD | J80: -21900 | L80: 76693.8 | M80: -76693.8 | O80: MONTERO VILCAS, JOSE GORGE
A81: BCP02/2025/01308 | B81: BCP02/2025/01308 | C81: 45919 | E81: 1220003 ANTICIPOS CLIENTES DEL EXTERIOR | F81: STICHTING ANIMAL HEALTH MISSION SURINAME (S.A.H.M.S) | G81: saldo a favor | I81: USD | J81: -6244.58 | L81: 21799.82 | M81: -21799.82 | O81: MONTERO VILCAS, JOSE GORGE
A82: BCP03/2025/00234 | B82: BCP03/2025/00234 | C82: 45917 | E82: 1220003 ANTICIPOS CLIENTES DEL EXTERIOR | F82: ARMSTRONG HEALTH CARE INC. | G82: saldo a favor | I82: USD | J82: -30380.64 | L82: 105998.05 | M82: -105998.05 | O82: MONTERO VILCAS, JOSE GORGE
A83: PAPANT/2025/03922 (F F15-00000156) | B83: PAPANT/2025/03922 | C83: 45901 | D83: 45901 | E83: 1220003 ANTICIPOS CLIENTES DEL EXTERIOR | F83: GANESHA AGROFARMA | G83: Pago de cliente $ 43,776.00 - GANESHA AGROFARMA - 01/09/2025 | H83: F F15-00000156 | I83: USD | J83: 43776 | K83: 154967.04 | M83: 154967.04 | O83: MONTERO VILCAS, JOSE GORGE
A84: CAMBI/2025/09/0144 | B84: CAMBI/2025/09/0144 | C84: 45901 | E84: 1220003 ANTICIPOS CLIENTES DEL EXTERIOR | F84: GANESHA AGROFARMA | G84: Diferencia en tipo de cambio de moneda | I84: USD | K84: 119.05 | M84: 119.05 | O84: MONTERO VILCAS, JOSE GORGE
A85: CAMBI/2025/09/0143 | B85: CAMBI/2025/09/0143 | C85: 45901 | E85: 1220003 ANTICIPOS CLIENTES DEL EXTERIOR | F85: GANESHA AGROFARMA | G85: Diferencia en tipo de cambio de moneda | I85: USD | K85: 480 | M85: 480 | O85: MONTERO VILCAS, JOSE GORGE
A86: CAMBI/2025/09/0142 | B86: CAMBI/2025/09/0142 | C86: 45901 | E86: 1220003 ANTICIPOS CLIENTES DEL EXTERIOR | F86: GANESHA AGROFARMA | G86: Diferencia en tipo de cambio de moneda | I86: USD | K86: 718.21 | M86: 718.21 | O86: MONTERO VILCAS, JOSE GORGE
A87: BCP03/2025/00201 | B87: BCP03/2025/00201 | C87: 45895 | E87: 1220003 ANTICIPOS CLIENTES DEL EXTERIOR | F87: GANESHA AGROFARMA | G87: Saldo a favor Ganesha | I87: USD | J87: -32700 | L87: 115463.7 | M87: -115463.7 | O87: MONTERO VILCAS, JOSE GORGE
A88: BCP03/2025/00192 | B88: BCP03/2025/00192 | C88: 45890 | E88: 1220003 ANTICIPOS CLIENTES DEL EXTERIOR | F88: GANESHA AGROFARMA | G88: saldo a favor | I88: USD | J88: -21900 | L88: 77504.1 | M88: -77504.1 | O88: MONTERO VILCAS, JOSE GORGE
A89: PAPANT/2025/03520 (F F15-00000137) | B89: PAPANT/2025/03520 | C89: 45889 | D89: 45889 | E89: 1220003 ANTICIPOS CLIENTES DEL EXTERIOR | F89: GANESHA AGROFARMA | G89: Pago de cliente $ 42,944.94 - GANESHA AGROFARMA - 20/08/2025 | H89: F F15-00000137 | I89: USD | J89: 42944.94 | K89: 151939.2 | M89: 151939.2 | O89: MONTERO VILCAS, JOSE GORGE
A90: CAMBI/2025/08/0602 | B90: CAMBI/2025/08/0602 | C90: 45889 | E90: 1220003 ANTICIPOS CLIENTES DEL EXTERIOR | F90: GANESHA AGROFARMA | G90: Diferencia en tipo de cambio de moneda | I90: USD | K90: 1556.74 | M90: 1556.74 | O90: MONTERO VILCAS, JOSE GORGE
A91: CAMBI/2025/08/0601 | B91: CAMBI/2025/08/0601 | C91: 45889 | E91: 1220003 ANTICIPOS CLIENTES DEL EXTERIOR | F91: GANESHA AGROFARMA | G91: Diferencia en tipo de cambio de moneda | I91: USD | K91: 2715.6 | M91: 2715.6 | O91: MONTERO VILCAS, JOSE GORGE
A92: CAMBI/2025/08/0600 | B92: CAMBI/2025/08/0600 | C92: 45889 | E92: 1220003 ANTICIPOS CLIENTES DEL EXTERIOR | F92: GANESHA AGROFARMA | G92: Diferencia en tipo de cambio de moneda | I92: USD | K92: 1314.42 | M92: 1314.42 | O92: MONTERO VILCAS, JOSE GORGE
A93: BCP03/2025/00186 | B93: BCP03/2025/00186 | C93: 45884 | E93: 1220003 ANTICIPOS CLIENTES DEL EXTERIOR | F93: GANESHA AGROFARMA | G93: Saldo a favor | I93: USD | J93: -23000 | L93: 81765 | M93: -81765 | O93: MONTERO VILCAS, JOSE GORGE
A94: BCP03/2025/00179 | B94: BCP03/2025/00179 | C94: 45881 | E94: 1220003 ANTICIPOS CLIENTES DEL EXTERIOR | F94: ARMSTRONG HEALTH CARE INC. | G94: Saldo a Favor S05602 | I94: USD | J94: -24186.67 | L94: 85548.25 | M94: -85548.25 | O94: MONTERO VILCAS, JOSE GORGE
A95: BCP03/2025/00164 | B95: BCP03/2025/00164 | C95: 45863 | E95: 1220003 ANTICIPOS CLIENTES DEL EXTERIOR | F95: GANESHA AGROFARMA | G95: saldo a favor | I95: USD | J95: -16000 | L95: 56880 | M95: -56880 | O95: MONTERO VILCAS, JOSE GORGE
A96: BCP03/2025/00155 | B96: BCP03/2025/00155 | C96: 45856 | E96: 1220003 ANTICIPOS CLIENTES DEL EXTERIOR | F96: GANESHA AGROFARMA | G96: Saldo a favor de Ganesha enviada por Brama | I96: USD | J96: -30000 | L96: 106680 | M96: -106680 | O96: MONTERO VILCAS, JOSE GORGE
A97: BCP03/2025/00107 | B97: BCP03/2025/00107 | C97: 45804 | E97: 1220003 ANTICIPOS CLIENTES DEL EXTERIOR | F97: ARMSTRONG HEALTH CARE INC. | G97: SALDO A FAVOR | I97: USD | J97: -32543.22 | L97: 119270.9 | M97: -119270.9 | O97: MONTERO VILCAS, JOSE GORGE
A98: PAPANT/2025/02123 (F F15-00000039) | B98: PAPANT/2025/02123 | C98: 45793 | D98: 45793 | E98: 1220003 ANTICIPOS CLIENTES DEL EXTERIOR | F98: GANESHA AGROFARMA | G98: Pago de cliente $ 37,224.04 - GANESHA AGROFARMA - 16/05/2025 | H98: F F15-00000039 | I98: USD | J98: 37224.04 | K98: 137207.81 | M98: 137207.81 | O98: MONTERO VILCAS, JOSE GORGE
A99: CAMBI/2025/05/0361 | B99: CAMBI/2025/05/0361 | C99: 45793 | E99: 1220003 ANTICIPOS CLIENTES DEL EXTERIOR | F99: GANESHA AGROFARMA | G99: Diferencia en tipo de cambio de moneda | I99: USD | K99: 62.05 | M99: 62.05 | O99: MONTERO VILCAS, JOSE GORGE
A100: CAMBI/2025/05/0360 | B100: CAMBI/2025/05/0360 | C100: 45793 | E100: 1220003 ANTICIPOS CLIENTES DEL EXTERIOR | F100: GANESHA AGROFARMA | G100: Diferencia en tipo de cambio de moneda | I100: USD | K100: 1600.5 | M100: 1600.5 | O100: MONTERO VILCAS, JOSE GORGE
...

Sheet 122xx4
A1: Asiento contable | B1: Número | C1: Fecha | D1: Fecha de vencimiento | E1: Cuenta | F1: Socio | G1: Etiqueta | H1: Referencia | I1: Moneda | J1: Importe en moneda | K1: Debe | L1: Haber | M1: Saldo | N1: Conciliación | O1: Creado por
A2: 1220004 ANTICIPOS VENTA DE DEPARTAMENTO PROY SB (173)
A3: BBVA1/2025/05050 | B3: BBVA1/2025/05050 | C3: 46082 | E3: 1220004 ANTICIPOS VENTA DE DEPARTAMENTO PROY SB | F3: VARIOS | G3: SB | I3: PEN | J3: -1555.15 | L3: 1555.15 | M3: -1555.15 | O3: BARCENA BRAGA, KATTYA ADELAIDA
A4: BBVA1/2025/05048 | B4: BBVA1/2025/05048 | C4: 46081 | E4: 1220004 ANTICIPOS VENTA DE DEPARTAMENTO PROY SB | F4: VARIOS | G4: SB | I4: PEN | J4: -4561.49 | L4: 4561.49 | M4: -4561.49 | O4: BARCENA BRAGA, KATTYA ADELAIDA
A5: BBVA1/2025/04988 | B5: BBVA1/2025/04988 | C5: 46078 | E5: 1220004 ANTICIPOS VENTA DE DEPARTAMENTO PROY SB | F5: VARIOS | G5: SB | I5: PEN | J5: -1815.3 | L5: 1815.3 | M5: -1815.3 | O5: BARCENA BRAGA, KATTYA ADELAIDA
A6: BBVA1/2025/04868 | B6: BBVA1/2025/04868 | C6: 46075 | E6: 1220004 ANTICIPOS VENTA DE DEPARTAMENTO PROY SB | F6: VARIOS | G6: SB | I6: PEN | J6: -1441.84 | L6: 1441.84 | M6: -1441.84 | O6: BARCENA BRAGA, KATTYA ADELAIDA
A7: BBVA1/2025/04866 | B7: BBVA1/2025/04866 | C7: 46074 | E7: 1220004 ANTICIPOS VENTA DE DEPARTAMENTO PROY SB | F7: VARIOS | G7: SB | I7: PEN | J7: -972.91 | L7: 972.91 | M7: -972.91 | O7: BARCENA BRAGA, KATTYA ADELAIDA
A8: PAPANT/2025/07036 (B B01-00006585) | B8: PAPANT/2025/07036 | C8: 46073 | D8: 46073 | E8: 1220004 ANTICIPOS VENTA DE DEPARTAMENTO PROY SB | F8: MARROQUIN CARBAJAL, ALEJANDRA | G8: Pago de cliente S/ 1,327.35 - MARROQUIN CARBAJAL, ALEJANDRA - 20/02/2026 | H8: B B01-00006585 | I8: PEN | J8: 1327.35 | K8: 1327.35 | M8: 1327.35 | N8: A126210 | O8: BARCENA BRAGA, KATTYA ADELAIDA
A9: PAPANT/2025/07035 (B B01-00006584) | B9: PAPANT/2025/07035 | C9: 46073 | D9: 46073 | E9: 1220004 ANTICIPOS VENTA DE DEPARTAMENTO PROY SB | F9: DEXTRE BAZALAR, RICARDO | G9: Pago de cliente S/ 1,889.53 - DEXTRE BAZALAR, RICARDO - 20/02/2026 | H9: B B01-00006584 | I9: PEN | J9: 1889.53 | K9: 1889.53 | M9: 1889.53 | N9: A126210 | O9: BARCENA BRAGA, KATTYA ADELAIDA
A10: PAPANT/2025/07034 (B B01-00006583) | B10: PAPANT/2025/07034 | C10: 46073 | D10: 46073 | E10: 1220004 ANTICIPOS VENTA DE DEPARTAMENTO PROY SB | F10: MARROQUIN CARBAJAL, ALEJANDRA | G10: Pago de cliente S/ 1,815.29 - MARROQUIN CARBAJAL, ALEJANDRA - 20/02/2026 | H10: B B01-00006583 | I10: PEN | J10: 1815.29 | K10: 1815.29 | M10: 1815.29 | N10: A126210 | O10: BARCENA BRAGA, KATTYA ADELAIDA
A11: PAPANT/2025/07033 (B B01-00006581) | B11: PAPANT/2025/07033 | C11: 46073 | D11: 46073 | E11: 1220004 ANTICIPOS VENTA DE DEPARTAMENTO PROY SB | F11: MARROQUIN CARBAJAL, ALEJANDRA | G11: Pago de cliente S/ 1,327.38 - MARROQUIN CARBAJAL, ALEJANDRA - 20/02/2026 | H11: B B01-00006581 | I11: PEN | J11: 1327.38 | K11: 1327.38 | M11: 1327.38 | N11: A126210 | O11: BARCENA BRAGA, KATTYA ADELAIDA
A12: PAPANT/2025/07032 (B B01-00006580) | B12: PAPANT/2025/07032 | C12: 46073 | D12: 46073 | E12: 1220004 ANTICIPOS VENTA DE DEPARTAMENTO PROY SB | F12: MARROQUIN CARBAJAL, ALEJANDRA | G12: Pago de cliente S/ 972.91 - MARROQUIN CARBAJAL, ALEJANDRA - 20/02/2026 | H12: B B01-00006580 | I12: PEN | J12: 972.91 | K12: 972.91 | M12: 972.91 | N12: A126210 | O12: BARCENA BRAGA, KATTYA ADELAIDA
A13: PAPANT/2025/07031 (B B01-00006575) | B13: PAPANT/2025/07031 | C13: 46073 | D13: 46073 | E13: 1220004 ANTICIPOS VENTA DE DEPARTAMENTO PROY SB | F13: MARROQUIN CARBAJAL, ALEJANDRA | G13: Pago de cliente S/ 3,268.29 - MARROQUIN CARBAJAL, ALEJANDRA - 20/02/2026 | H13: B B01-00006575 | I13: PEN | J13: 3268.29 | K13: 3268.29 | M13: 3268.29 | N13: A126210 | O13: BARCENA BRAGA, KATTYA ADELAIDA
A14: PAPANT/2025/07030 (B B01-00006573) | B14: PAPANT/2025/07030 | C14: 46073 | D14: 46073 | E14: 1220004 ANTICIPOS VENTA DE DEPARTAMENTO PROY SB | F14: REYES LOPEZ, GIANIRA GLADYS DEL CARMEN | G14: Pago de cliente S/ 1,327.38 - REYES LOPEZ, GIANIRA GLADYS DEL CARMEN - 20/02/2026 | H14: B B01-00006573 | I14: PEN | J14: 1327.38 | K14: 1327.38 | M14: 1327.38 | N14: A126210 | O14: BARCENA BRAGA, KATTYA ADELAIDA
A15: PAPANT/2025/07029 (B B01-00006576) | B15: PAPANT/2025/07029 | C15: 46073 | D15: 46073 | E15: 1220004 ANTICIPOS VENTA DE DEPARTAMENTO PROY SB | F15: MARROQUIN CARBAJAL, ALEJANDRA | G15: Pago de cliente S/ 5,325.62 - MARROQUIN CARBAJAL, ALEJANDRA - 20/02/2026 | H15: B B01-00006576 | I15: PEN | J15: 5325.62 | K15: 5325.62 | M15: 5325.62 | N15: A126210 | O15: BARCENA BRAGA, KATTYA ADELAIDA
A16: PAPANT/2025/07028 (B B01-00006574) | B16: PAPANT/2025/07028 | C16: 46073 | D16: 46073 | E16: 1220004 ANTICIPOS VENTA DE DEPARTAMENTO PROY SB | F16: MARROQUIN CARBAJAL, ALEJANDRA | G16: Pago de cliente S/ 3,204.67 - MARROQUIN CARBAJAL, ALEJANDRA - 20/02/2026 | H16: B B01-00006574 | I16: PEN | J16: 3204.67 | K16: 3204.67 | M16: 3204.67 | N16: A126210 | O16: BARCENA BRAGA, KATTYA ADELAIDA
A17: PAPANT/2025/07027 (B B01-00006582) | B17: PAPANT/2025/07027 | C17: 46073 | D17: 46073 | E17: 1220004 ANTICIPOS VENTA DE DEPARTAMENTO PROY SB | F17: AYULO CRIBILLERO, CESAR KELVIN | G17: Pago de cliente S/ 1,929.11 - AYULO CRIBILLERO, CESAR KELVIN - 20/02/2026 | H17: B B01-00006582 | I17: PEN | J17: 1929.11 | K17: 1929.11 | M17: 1929.11 | N17: A126210 | O17: BARCENA BRAGA, KATTYA ADELAIDA
A18: PAPANT/2025/07026 (B B01-00006577) | B18: PAPANT/2025/07026 | C18: 46073 | D18: 46073 | E18: 1220004 ANTICIPOS VENTA DE DEPARTAMENTO PROY SB | F18: MARROQUIN CARBAJAL, ALEJANDRA | G18: Pago de cliente S/ 3,032.98 - MARROQUIN CARBAJAL, ALEJANDRA - 20/02/2026 | H18: B B01-00006577 | I18: PEN | J18: 3032.98 | K18: 3032.98 | M18: 3032.98 | N18: A126210 | O18: BARCENA BRAGA, KATTYA ADELAIDA
A19: PAPANT/2025/07025 (B B01-00006579) | B19: PAPANT/2025/07025 | C19: 46073 | D19: 46073 | E19: 1220004 ANTICIPOS VENTA DE DEPARTAMENTO PROY SB | F19: MARROQUIN CARBAJAL, ALEJANDRA | G19: Pago de cliente S/ 1,777.36 - MARROQUIN CARBAJAL, ALEJANDRA - 20/02/2026 | H19: B B01-00006579 | I19: PEN | J19: 1777.36 | K19: 1777.36 | M19: 1777.36 | N19: A126210 | O19: BARCENA BRAGA, KATTYA ADELAIDA
... A41: PAPANT/2025/07003 (B B01-00006637) | B41: PAPANT/2025/07003 | C41: 46073 | D41: 46073 | E41: 1220004 ANTICIPOS VENTA DE DEPARTAMENTO PROY SB | F41: PINEDA REATEGUI, DOMINICK JOAQUIN | G41: Pago de cliente S/ 1,070.66 - PINEDA REATEGUI, DOMINICK JOAQUIN - 20/02/2026 | H41: B B01-00006637 | I41: PEN | J41: 1070.66 | K41: 1070.66 | M41: 1070.66 | N41: A126210 | O41: BARCENA BRAGA, KATTYA ADELAIDA
A42: BBVA1/2025/04865 | B42: BBVA1/2025/04865 | C42: 46073 | E42: 1220004 ANTICIPOS VENTA DE DEPARTAMENTO PROY SB | F42: VARIOS | G42: SB | I42: PEN | J42: -3027.57 | L42: 3027.57 | M42: -3027.57 | O42: BARCENA BRAGA, KATTYA ADELAIDA
A43: BBVA1/2025/04916 | B43: BBVA1/2025/04916 | C43: 46072 | E43: 1220004 ANTICIPOS VENTA DE DEPARTAMENTO PROY SB | F43: VARIOS | G43: SB | I43: PEN | J43: -3718.6 | L43: 3718.6 | M43: -3718.6 | O43: BARCENA BRAGA, KATTYA ADELAIDA
A44: BBVA1/2025/04915 | B44: BBVA1/2025/04915 | C44: 46072 | E44: 1220004 ANTICIPOS VENTA DE DEPARTAMENTO PROY SB | F44: VARIOS | G44: SB | I44: PEN | J44: -857.31 | L44: 857.31 | M44: -857.31 | O44: BARCENA BRAGA, KATTYA ADELAIDA
A45: BBVA1/2025/04831 | B45: BBVA1/2025/04831 | C45: 46068 | E45: 1220004 ANTICIPOS VENTA DE DEPARTAMENTO PROY SB | F45: VARIOS | G45: SB | I45: PEN | J45: -2398.02 | L45: 2398.02 | M45: -2398.02 | N45: A126210 | O45: BARCENA BRAGA, KATTYA ADELAIDA
A46: BBVA1/2025/04829 | B46: BBVA1/2025/04829 | C46: 46067 | E46: 1220004 ANTICIPOS VENTA DE DEPARTAMENTO PROY SB | F46: VARIOS | G46: SB | I46: PEN | J46: -972.92 | L46: 972.92 | M46: -972.92 | N46: A126210 | O46: BARCENA BRAGA, KATTYA ADELAIDA
A47: BBVA1/2025/04826 | B47: BBVA1/2025/04826 | C47: 46066 | E47: 1220004 ANTICIPOS VENTA DE DEPARTAMENTO PROY SB | F47: VARIOS | G47: SB | I47: PEN | J47: -355.64 | L47: 355.64 | M47: -355.64 | N47: A126210 | O47: BARCENA BRAGA, KATTYA ADELAIDA
A48: BBVA1/2025/04803 | B48: BBVA1/2025/04803 | C48: 46065 | E48: 1220004 ANTICIPOS VENTA DE DEPARTAMENTO PROY SB | F48: VARIOS | G48: SB | I48: PEN | J48: -4176.43 | L48: 4176.43 | M48: -4176.43 | N48: A126210 | O48: BARCENA BRAGA, KATTYA ADELAIDA
A49: BBVA1/2025/04761 | B49: BBVA1/2025/04761 | C49: 46063 | E49: 1220004 ANTICIPOS VENTA DE DEPARTAMENTO PROY SB | F49: VARIOS | G49: SB | I49: PEN | J49: -1815.28 | L49: 1815.28 | M49: -1815.28 | N49: A126210 | O49: BARCENA BRAGA, KATTYA ADELAIDA
A50: BBVA1/2025/04752 | B50: BBVA1/2025/04752 | C50: 46062 | E50: 1220004 ANTICIPOS VENTA DE DEPARTAMENTO PROY SB | F50: VARIOS | G50: SB | I50: PEN | J50: -2501.45 | L50: 2501.45 | M50: -2501.45 | N50: A126210 | O50: BARCENA BRAGA, KATTYA ADELAIDA
A51: BBVA1/2025/04751 | B51: BBVA1/2025/04751 | C51: 46062 | E51: 1220004 ANTICIPOS VENTA DE DEPARTAMENTO PROY SB | F51: VARIOS | G51: SB | I51: PEN | J51: -1441.8 | L51: 1441.8 | M51: -1441.8 | N51: A126210 | O51: BARCENA BRAGA, KATTYA ADELAIDA
A52: BBVA1/2025/04726 | B52: BBVA1/2025/04726 | C52: 46059 | E52: 1220004 ANTICIPOS VENTA DE DEPARTAMENTO PROY SB | F52: VARIOS | G52: SB | I52: PEN | J52: -4532.05 | L52: 4532.05 | M52: -4532.05 | N52: A126210 | O52: BARCENA BRAGA, KATTYA ADELAIDA
A53: BBVA1/2025/04694 | B53: BBVA1/2025/04694 | C53: 46057 | E53: 1220004 ANTICIPOS VENTA DE DEPARTAMENTO PROY SB | F53: VARIOS | G53: SB | I53: PEN | J53: -469.29 | L53: 469.29 | M53: -469.29 | N53: A126210 | O53: BARCENA BRAGA, KATTYA ADELAIDA
A54: BBVA1/2025/04656 | B54: BBVA1/2025/04656 | C54: 46056 | E54: 1220004 ANTICIPOS VENTA DE DEPARTAMENTO PROY SB | F54: VARIOS | G54: SB | I54: PEN | J54: -1815.3 | L54: 1815.3 | M54: -1815.3 | N54: A126210 | O54: BARCENA BRAGA, KATTYA ADELAIDA
A55: BBVA1/2025/04616 | B55: BBVA1/2025/04616 | C55: 46054 | E55: 1220004 ANTICIPOS VENTA DE DEPARTAMENTO PROY SB | F55: VARIOS | G55: SB | I55: PEN | J55: -2512.48 | L55: 2512.48 | M55: -2512.48 | N55: A126210 | O55: BARCENA BRAGA, KATTYA ADELAIDA
A56: BBVA1/2025/04613 | B56: BBVA1/2025/04613 | C56: 46053 | E56: 1220004 ANTICIPOS VENTA DE DEPARTAMENTO PROY SB | F56: VARIOS | G56: ABONO INMEDIATO 922 LOCALPA | I56: PEN | J56: -2806.34 | L56: 2806.34 | M56: -2806.34 | N56: A126210 | O56: BARCENA BRAGA, KATTYA ADELAIDA
... A70: BBVA1/2025/04208 | B70: BBVA1/2025/04208 | C70: 46022 | E70: 1220004 ANTICIPOS VENTA DE DEPARTAMENTO PROY SB | F70: VARIOS | G70: ABONO INMEDIATO 922 LOCALPA | I70: PEN | J70: -3268.29 | L70: 3268.29 | M70: -3268.29 | N70: A126210 | O70: BARCENA BRAGA, KATTYA ADELAIDA
A71: BBVA1/2025/04140 | B71: BBVA1/2025/04140 | C71: 46020 | E71: 1220004 ANTICIPOS VENTA DE DEPARTAMENTO PROY SB | F71: VARIOS | G71: ABONO INMEDIATO 922 LOCALPA | I71: PEN | J71: -4238.25 | L71: 4238.25 | M71: -4238.25 | O71: BARCENA BRAGA, KATTYA ADELAIDA
A72: BBVA1/2025/04112 | B72: BBVA1/2025/04112 | C72: 46018 | E72: 1220004 ANTICIPOS VENTA DE DEPARTAMENTO PROY SB | F72: VARIOS | G72: ABONO INMEDIATO 922 LOCALPA | I72: PEN | J72: -1271.29 | L72: 1271.29 | M72: -1271.29 | O72: BARCENA BRAGA, KATTYA ADELAIDA
A73: BBVA1/2025/03891 | B73: BBVA1/2025/03891 | C73: 46001 | E73: 1220004 ANTICIPOS VENTA DE DEPARTAMENTO PROY SB | F73: VARIOS | G73: ABONO INMEDIATO 922 LOCALPA | I73: PEN | J73: -3437.85 | L73: 3437.85 | M73: -3437.85 | O73: BARCENA BRAGA, KATTYA ADELAIDA
A74: BBVA1/2025/03889 | B74: BBVA1/2025/03889 | C74: 46001 | E74: 1220004 ANTICIPOS VENTA DE DEPARTAMENTO PROY SB | F74: VARIOS | G74: ABONO INMEDIATO 922 LOCALPA | I74: PEN | J74: -1042.37 | L74: 1042.37 | M74: -1042.37 | O74: BARCENA BRAGA, KATTYA ADELAIDA
A75: PAPANT/2025/02275 (B B01-00001822) | B75: PAPANT/2025/02275 | C75: 45806 | D75: 45806 | E75: 1220004 ANTICIPOS VENTA DE DEPARTAMENTO PROY SB | F75: MARROQUIN CARBAJAL, ALEJANDRA | G75: Pago de cliente S/ 1,708.40 - MARROQUIN CARBAJAL, ALEJANDRA - 29/05/2025 | H75: B B01-00001822 | I75: PEN | J75: 1708.4 | K75: 1708.4 | M75: 1708.4 | N75: A31591 | O75: BARCENA BRAGA, KATTYA ADELAIDA
A76: PAPANT/2025/02274 (B B01-00001818) | B76: PAPANT/2025/02274 | C76: 45806 | D76: 45806 | E76: 1220004 ANTICIPOS VENTA DE DEPARTAMENTO PROY SB | F76: MARROQUIN CARBAJAL, ALEJANDRA | G76: Pago de cliente S/ 862.50 - MARROQUIN CARBAJAL, ALEJANDRA - 29/05/2025 | H76: B B01-00001818 | I76: PEN | J76: 862.5 | K76: 862.5 | M76: 862.5 | N76: A31591 | O76: BARCENA BRAGA, KATTYA ADELAIDA
A77: PAPANT/2025/02290 (B B01-00001812) | B77: PAPANT/2025/02290 | C77: 45805 | D77: 45805 | E77: 1220004 ANTICIPOS VENTA DE DEPARTAMENTO PROY SB | F77: DELFIN BEIZAGA, ALAN GABRIEL DARIO | G77: Pago de cliente S/ 1,277.51 - DELFIN BEIZAGA, ALAN GABRIEL DARIO - 28/05/2025 | H77: B B01-00001812 | I77: PEN | J77: 1277.51 | K77: 1277.51 | M77: 1277.51 | N77: A57839 | O77: BARCENA BRAGA, KATTYA ADELAIDA
A78: PAPANT/2025/02289 (B B01-00001832) | B78: PAPANT/2025/02289 | C78: 45805 | D78: 45805 | E78: 1220004 ANTICIPOS VENTA DE DEPARTAMENTO PROY SB | F78: LIMACO GARCIA, ASTRID KAROLYN | G78: Pago de cliente S/ 1,362.25 - LIMACO GARCIA, ASTRID KAROLYN - 28/05/2025 | H78: B B01-00001832 | I78: PEN | J78: 1362.25 | K78: 1362.25 | M78: 1362.25 | N78: A31623 | O78: BARCENA BRAGA, KATTYA ADELAIDA
A79: PAPANT/2025/02288 (B B01-00001851) | B79: PAPANT/2025/02288 | C79: 45805 | D79: 45805 | E79: 1220004 ANTICIPOS VENTA DE DEPARTAMENTO PROY SB | F79: VARGAS RUIZ, DAVID RICARDO NICOLAS | G79: Pago de cliente S/ 1,326.02 - VARGAS RUIZ, DAVID RICARDO NICOLAS - 28/05/2025 | H79: B B01-00001851 | I79: PEN | J79: 1326.02 | K79: 1326.02 | M79: 1326.02 | N79: A57839 | O79: BARCENA BRAGA, KATTYA ADELAIDA
A80: PAPANT/2025/02286 (B B01-00001852) | B80: PAPANT/2025/02286 | C80: 45805 | D80: 45805 | E80: 1220004 ANTICIPOS VENTA DE DEPARTAMENTO PROY SB | F80: VILLACORTA PASTOR, ALESSIA | G80: Pago de cliente S/ 2,131.02 - VILLACORTA PASTOR, ALESSIA - 28/05/2025 | H80: B B01-00001852 | I80: PEN | J80: 2131.02 | K80: 2131.02 | M80: 2131.02 | N80: A31609 | O80: BARCENA BRAGA, KATTYA ADELAIDA
A81: PAPANT/2025/02285 (B B01-00001853) | B81: PAPANT/2025/02285 | C81: 45805 | D81: 45805 | E81: 1220004 ANTICIPOS VENTA DE DEPARTAMENTO PROY SB | F81: CABRERA RIVERO, JOSE LUIS | G81: Pago de cliente S/ 3,971.00 - CABRERA RIVERO, JOSE LUIS - 28/05/2025 | H81: B B01-00001853 | I81: PEN | J81: 3971 | K81: 3971 | M81: 3971 | N81: A31607 | O81: BARCENA BRAGA, KATTYA ADELAIDA
A82: PAPANT/2025/02284 (B B01-00001814) | B82: PAPANT/2025/02284 | C82: 45805 | D82: 45805 | E82: 1220004 ANTICIPOS VENTA DE DEPARTAMENTO PROY SB | F82: MARROQUIN CARBAJAL, ALEJANDRA | G82: Pago de cliente S/ 1,737.50 - MARROQUIN CARBAJAL, ALEJANDRA - 28/05/2025 | H82: B B01-00001814 | I82: PEN | J82: 1737.5 | K82: 1737.5 | M82: 1737.5 | N82: A31605 | O82: BARCENA BRAGA, KATTYA ADELAIDA
A83: PAPANT/2025/02283 (B B01-00001820) | B83: PAPANT/2025/02283 | C83: 45805 | D83: 45805 | E83: 1220004 ANTICIPOS VENTA DE DEPARTAMENTO PROY SB | F83: MARROQUIN CARBAJAL, ALEJANDRA | G83: Pago de cliente S/ 1,708.40 - MARROQUIN CARBAJAL, ALEJANDRA - 28/05/2025 | H83: B B01-00001820 | I83: PEN | J83: 1708.4 | K83: 1708.4 | M83: 1708.4 | N83: A31605 | O83: BARCENA BRAGA, KATTYA ADELAIDA
A84: PAPANT/2025/02282 (B B01-00001821) | B84: PAPANT/2025/02282 | C84: 45805 | D84: 45805 | E84: 1220004 ANTICIPOS VENTA DE DEPARTAMENTO PROY SB | F84: ESPINOZA MUÑOZ, RINA MAGALY | G84: Pago de cliente S/ 1,651.60 - ESPINOZA MUÑOZ, RINA MAGALY - 28/05/2025 | H84: B B01-00001821 | I84: PEN | J84: 1651.6 | K84: 1651.6 | M84: 1651.6 | N84: A31602 | O84: BARCENA BRAGA, KATTYA ADELAIDA
A85: PAPANT/2025/02281 (B B01-00001816) | B85: PAPANT/2025/02281 | C85: 45805 | D85: 45805 | E85: 1220004 ANTICIPOS VENTA DE DEPARTAMENTO PROY SB | F85: MARROQUIN CARBAJAL, ALEJANDRA | G85: Pago de cliente S/ 862.50 - MARROQUIN CARBAJAL, ALEJANDRA - 28/05/2025 | H85: B B01-00001816 | I85: PEN | J85: 862.5 | K85: 862.5 | M85: 862.5 | N85: A31600 | O85: BARCENA BRAGA, KATTYA ADELAIDA
A86: PAPANT/2025/02280 (B B01-00001811) | B86: PAPANT/2025/02280 | C86: 45805 | D86: 45805 | E86: 1220004 ANTICIPOS VENTA DE DEPARTAMENTO PROY SB | F86: EUGENIO SARMIENTO, LEYLA GERALDINE | G86: Pago de cliente S/ 1,967.50 - EUGENIO SARMIENTO, LEYLA GERALDINE - 28/05/2025 | H86: B B01-00001811 | I86: PEN | J86: 1967.5 | K86: 1967.5 | M86: 1967.5 | O86: BARCENA BRAGA, KATTYA ADELAIDA
A87: PAPANT/2025/02278 (B B01-00001855) | B87: PAPANT/2025/02278 | C87: 45805 | D87: 45805 | E87: 1220004 ANTICIPOS VENTA DE DEPARTAMENTO PROY SB | F87: SOTELO BUENO, GLADIS TEO | G87: Pago de cliente S/ 1,939.09 - SOTELO BUENO, GLADIS TEO - 28/05/2025 | H87: B B01-00001855 | I87: PEN | J87: 1939.09 | K87: 1939.09 | M87: 1939.09 | N87: A31594 | O87: BARCENA BRAGA, KATTYA ADELAIDA
A88: PAPANT/2025/02277 (B B01-00001859) | B88: PAPANT/2025/02277 | C88: 45805 | D88: 45805 | E88: 1220004 ANTICIPOS VENTA DE DEPARTAMENTO PROY SB | F88: MARROQUIN CARBAJAL, ALEJANDRA | G88: Pago de cliente S/ 1,450.00 - MARROQUIN CARBAJAL, ALEJANDRA - 28/05/2025 | H88: B B01-00001859 | I88: PEN | J88: 1450 | K88: 1450 | M88: 1450 | N88: A31594 | O88: BARCENA BRAGA, KATTYA ADELAIDA
A89: PAPANT/2025/02276 (B B01-00001823) | B89: PAPANT/2025/02276 | C89: 45805 | D89: 45805 | E89: 1220004 ANTICIPOS VENTA DE DEPARTAMENTO PROY SB | F89: BECERRA STOCK, YANIRA DEL ROCIO | G89: Pago de cliente S/ 2,226.60 - BECERRA STOCK, YANIRA DEL ROCIO - 28/05/2025 | H89: B B01-00001823 | I89: PEN | J89: 2226.6 | K89: 2226.6 | M89: 2226.6 | N89: A31591 | O89: BARCENA BRAGA, KATTYA ADELAIDA
A90: PAPANT/2025/02273 (B B01-00001854) | B90: PAPANT/2025/02273 | C90: 45805 | D90: 45805 | E90: 1220004 ANTICIPOS VENTA DE DEPARTAMENTO PROY SB | F90: PORTURAS INGUNZA, MARIA DEL ROSARIO | G90: Pago de cliente S/ 2,591.01 - PORTURAS INGUNZA, MARIA DEL ROSARIO - 28/05/2025 | H90: B B01-00001854 | I90: PEN | J90: 2591.01 | K90: 2591.01 | M90: 2591.01 | N90: A31587 | O90: BARCENA BRAGA, KATTYA ADELAIDA
A91: PAPANT/2025/02272 (B B01-00001857) | B91: PAPANT/2025/02272 | C91: 45805 | D91: 45805 | E91: 1220004 ANTICIPOS VENTA DE DEPARTAMENTO PROY SB | F91: MARROQUIN CARBAJAL, ALEJANDRA | G91: Pago de cliente S/ 3,625.99 - MARROQUIN CARBAJAL, ALEJANDRA - 28/05/2025 | H91: B B01-00001857 | I91: PEN | J91: 3625.99 | K91: 3625.99 | M91: 3625.99 | N91: A31585 | O91: BARCENA BRAGA, KATTYA ADELAIDA
A92: PAPANT/2025/02271 (B B01-00001849) | B92: PAPANT/2025/02271 | C92: 45805 | D92: 45805 | E92: 1220004 ANTICIPOS VENTA DE DEPARTAMENTO PROY SB | F92: OSORIO ISHIKAWA, KIOMI MERCEDES | G92: Pago de cliente S/ 3,261.59 - OSORIO ISHIKAWA, KIOMI MERCEDES - 28/05/2025 | H92: B B01-00001849 | I92: PEN | J92: 3261.59 | K92: 3261.59 | M92: 3261.59 | N92: A31583 | O92: BARCENA BRAGA, KATTYA ADELAIDA
A93: PAPANT/2025/02270 (B B01-00001843) | B93: PAPANT/2025/02270 | C93: 45805 | D93: 45805 | E93: 1220004 ANTICIPOS VENTA DE DEPARTAMENTO PROY SB | F93: MARQUINA TORRES, PIERINA ELVA | G93: Pago de cliente S/ 2,936.00 - MARQUINA TORRES, PIERINA ELVA - 28/05/2025 | H93: B B01-00001843 | I93: PEN | J93: 2936 | K93: 2936 | M93: 2936 | N93: A31581 | O93: BARCENA BRAGA, KATTYA ADELAIDA
A94: PAPANT/2025/02269 (B B01-00001845) | B94: PAPANT/2025/02269 | C94: 45805 | D94: 45805 | E94: 1220004 ANTICIPOS VENTA DE DEPARTAMENTO PROY SB | F94: LEON CACHAY, YSMAEL ANTONIO | G94: Pago de cliente S/ 2,361.00 - LEON CACHAY, YSMAEL ANTONIO - 28/05/2025 | H94: B B01-00001845 | I94: PEN | J94: 2361 | K94: 2361 | M94: 2361 | N94: A31579 | O94: BARCENA BRAGA, KATTYA ADELAIDA
A95: PAPANT/2025/02266 (B B01-00001834) | B95: PAPANT/2025/02266 | C95: 45805 | D95: 45805 | E95: 1220004 ANTICIPOS VENTA DE DEPARTAMENTO PROY SB | F95: PINILLOS RUIZ, FRANCISCO JOSE | G95: Pago de cliente S/ 2,303.50 - PINILLOS RUIZ, FRANCISCO JOSE - 28/05/2025 | H95: B B01-00001834 | I95: PEN | J95: 2303.5 | K95: 2303.5 | M95: 2303.5 | N95: A31574 | O95: BARCENA BRAGA, KATTYA ADELAIDA
A96: PAPANT/2025/02265 (B B01-00001817) | B96: PAPANT/2025/02265 | C96: 45805 | D96: 45805 | E96: 1220004 ANTICIPOS VENTA DE DEPARTAMENTO PROY SB | F96: ARIAS CABRERA, VICTOR JAIME | G96: Pago de cliente S/ 1,943.51 - ARIAS CABRERA, VICTOR JAIME - 28/05/2025 | H96: B B01-00001817 | I96: PEN | J96: 1943.51 | K96: 1943.51 | M96: 1943.51 | N96: A31569 | O96: BARCENA BRAGA, KATTYA ADELAIDA
A97: PAPANT/2025/02264 (B B01-00001837) | B97: PAPANT/2025/02264 | C97: 45805 | D97: 45805 | E97: 1220004 ANTICIPOS VENTA DE DEPARTAMENTO PROY SB | F97: PRIETO ABASOLO, LUIS FERNANDO | G97: Pago de cliente S/ 1,737.52 - PRIETO ABASOLO, LUIS FERNANDO - 28/05/2025 | H97: B B01-00001837 | I97: PEN | J97: 1737.52 | K97: 1737.52 | M97: 1737.52 | N97: A31545 | O97: BARCENA BRAGA, KATTYA ADELAIDA
A98: PAPANT/2025/02262 (B B01-00001825) | B98: PAPANT/2025/02262 | C98: 45805 | D98: 45805 | E98: 1220004 ANTICIPOS VENTA DE DEPARTAMENTO PROY SB | F98: CERVANTES PERALTA, JOHANN SEBASTHIAN | G98: Pago de cliente S/ 1,671.00 - CERVANTES PERALTA, JOHANN SEBASTHIAN - 28/05/2025 | H98: B B01-00001825 | I98: PEN | J98: 1671 | K98: 1671 | M98: 1671 | N98: A31520 | O98: BARCENA BRAGA, KATTYA ADELAIDA
... A113: PAPANT/2025/02247 (B B01-00001847) | B113: PAPANT/2025/02247 | C113: 45805 | D113: 45805 | E113: 1220004 ANTICIPOS VENTA DE DEPARTAMENTO PROY SB | F113: PORTAL ZARABIA, ALEJANDRO SEGUNDO | G113: Pago de cliente S/ 748.50 - PORTAL ZARABIA, ALEJANDRO SEGUNDO - 28/05/2025 | H113: B B01-00001847 | I113: PEN | J113: 748.5 | K113: 748.5 | M113: 748.5 | N113: A31477 | O113: BARCENA BRAGA, KATTYA ADELAIDA
A114: MISC/2025/05/0250 | B114: MISC/2025/05/0250 | C114: 45805 | E114: 1220004 ANTICIPOS VENTA DE DEPARTAMENTO PROY SB | F114: VARGAS RUIZ, DAVID RICARDO NICOLAS | G114: REDONDEO | I114: PEN | J114: -0.01 | L114: 0.01 | M114: -0.01 | N114: A57839 | O114: BARCENA BRAGA, KATTYA ADELAIDA
A115: BBVA1/2025/01238 | B115: BBVA1/2025/01238 | C115: 45782 | E115: 1220004 ANTICIPOS VENTA DE DEPARTAMENTO PROY SB | F115: VARIOS | G115: SB | I115: PEN | J115: -1139.5 | L115: 1139.5 | M115: -1139.5 | O115: BARCENA BRAGA, KATTYA ADELAIDA
A116: BBVA1/2025/01055 | B116: BBVA1/2025/01055 | C116: 45768 | E116: 1220004 ANTICIPOS VENTA DE DEPARTAMENTO PROY SB | F116: VARIOS | G116: SB | I116: PEN | J116: -3971 | L116: 3971 | M116: -3971 | N116: A31607 | O116: BARCENA BRAGA, KATTYA ADELAIDA
A117: BBVA1/2025/00983 | B117: BBVA1/2025/00983 | C117: 45758 | E117: 1220004 ANTICIPOS VENTA DE DEPARTAMENTO PROY SB | F117: VARIOS | G117: SB | I117: PEN | J117: -2131.02 | L117: 2131.02 | M117: -2131.02 | N117: A31609 | O117: BARCENA BRAGA, KATTYA ADELAIDA
A118: BBVA1/2025/00914 | B118: BBVA1/2025/00914 | C118: 45754 | E118: 1220004 ANTICIPOS VENTA DE DEPARTAMENTO PROY SB | F118: VARIOS | G118: SB | I118: PEN | J118: -2603.52 | L118: 2603.52 | M118: -2603.52 | N118: A57839 | O118: BARCENA BRAGA, KATTYA ADELAIDA
A119: BBVA1/2025/00848 | B119: BBVA1/2025/00848 | C119: 45747 | E119: 1220004 ANTICIPOS VENTA DE DEPARTAMENTO PROY SB | F119: VARIOS | G119: SB | I119: PEN | J119: -2670 | L119: 2670 | M119: -2670 | O119: BARCENA BRAGA, KATTYA ADELAIDA
A120: BBVA1/2025/00745 | B120: BBVA1/2025/00745 | C120: 45740 | E120: 1220004 ANTICIPOS VENTA DE DEPARTAMENTO PROY SB | F120: VARIOS | G120: SB | I120: PEN | J120: -3389.09 | L120: 3389.09 | M120: -3389.09 | N120: A31594 | O120: BARCENA BRAGA, KATTYA ADELAIDA
A121: BBVA1/2025/00744 | B121: BBVA1/2025/00744 | C121: 45740 | E121: 1220004 ANTICIPOS VENTA DE DEPARTAMENTO PROY SB | F121: VARIOS | G121: SB | I121: PEN | J121: -1671 | L121: 1671 | M121: -1671 | N121: A31520 | O121: BARCENA BRAGA, KATTYA ADELAIDA
A122: BBVA1/2025/00681 | B122: BBVA1/2025/00681 | C122: 45733 | E122: 1220004 ANTICIPOS VENTA DE DEPARTAMENTO PROY SB | F122: VARIOS | G122: SB | I122: PEN | J122: -1507.49 | L122: 1507.49 | M122: -1507.49 | N122: A31507 | O122: BARCENA BRAGA, KATTYA ADELAIDA
A123: BBVA1/2025/00680 | B123: BBVA1/2025/00680 | C123: 45733 | E123: 1220004 ANTICIPOS VENTA DE DEPARTAMENTO PROY SB | F123: VARIOS | G123: SB | I123: PEN | J123: -1277.5 | L123: 1277.5 | M123: -1277.5 | N123: A31489 | O123: BARCENA BRAGA, KATTYA ADELAIDA
A124: BBVA1/2025/00679 | B124: BBVA1/2025/00679 | C124: 45733 | E124: 1220004 ANTICIPOS VENTA DE DEPARTAMENTO PROY SB | F124: VARIOS | G124: SB | I124: PEN | J124: -402.5 | L124: 402.5 | M124: -402.5 | N124: A31623 | O124: BARCENA BRAGA, KATTYA ADELAIDA
A125: BBVA1/2025/00621 | B125: BBVA1/2025/00621 | C125: 45730 | E125: 1220004 ANTICIPOS VENTA DE DEPARTAMENTO PROY SB | F125: VARIOS | G125: SB | I125: PEN | J125: -959.75 | L125: 959.75 | M125: -959.75 | N125: A31623 | O125: BARCENA BRAGA, KATTYA ADELAIDA
A126: BBVA1/2025/00603 | B126: BBVA1/2025/00603 | C126: 45728 | E126: 1220004 ANTICIPOS VENTA DE DEPARTAMENTO PROY SB | F126: VARIOS | G126: SB | I126: PEN | J126: -2361 | L126: 2361 | M126: -2361 | O126: BARCENA BRAGA, KATTYA ADELAIDA
A127: BBVA1/2025/00583 | B127: BBVA1/2025/00583 | C127: 45726 | E127: 1220004 ANTICIPOS VENTA DE DEPARTAMENTO PROY SB | F127: VARIOS | G127: SB | I127: PEN | J127: -2361 | L127: 2361 | M127: -2361 | N127: A31579 | O127: BARCENA BRAGA, KATTYA ADELAIDA
A128: BBVA1/2025/00550 | B128: BBVA1/2025/00550 | C128: 45720 | E128: 1220004 ANTICIPOS VENTA DE DEPARTAMENTO PROY SB | F128: VARIOS | G128: SB | I128: PEN | J128: -2591.01 | L128: 2591.01 | M128: -2591.01 | N128: A31587 | O128: BARCENA BRAGA, KATTYA ADELAIDA
A129: BBVA1/2025/00537 | B129: BBVA1/2025/00537 | C129: 45719 | E129: 1220004 ANTICIPOS VENTA DE DEPARTAMENTO PROY SB | F129: VARIOS | G129: SB | I129: PEN | J129: -1534.75 | L129: 1534.75 | M129: -1534.75 | N129: A31509 | O129: BARCENA BRAGA, KATTYA ADELAIDA
A130: BBVA1/2025/00498 | B130: BBVA1/2025/00498 | C130: 45716 | E130: 1220004 ANTICIPOS VENTA DE DEPARTAMENTO PROY SB | F130: VARIOS | G130: SB | I130: PEN | J130: -3261.59 | L130: 3261.59 | M130: -3261.59 | N130: A31583 | O130: BARCENA BRAGA, KATTYA ADELAIDA
A131: BBVA1/2025/00497 | B131: BBVA1/2025/00497 | C131: 45716 | E131: 1220004 ANTICIPOS VENTA DE DEPARTAMENTO PROY SB | F131: VARIOS | G131: SB | I131: PEN | J131: -2936 | L131: 2936 | M131: -2936 | N131: A31581 | O131: BARCENA BRAGA, KATTYA ADELAIDA
A132: BBVA1/2025/00441 | B132: BBVA1/2025/00441 | C132: 45713 | E132: 1220004 ANTICIPOS VENTA DE DEPARTAMENTO PROY SB | F132: VARIOS | G132: SB | I132: PEN | J132: -1369.49 | L132: 1369.49 | M132: -1369.49 | N132: A31496 | O132: BARCENA BRAGA, KATTYA ADELAIDA
A133: BBVA1/2025/00423 | B133: BBVA1/2025/00423 | C133: 45712 | E133: 1220004 ANTICIPOS VENTA DE DEPARTAMENTO PROY SB | F133: VARIOS | G133: DIF. 4,787.91 ( en el excel) Maria revisando | I133: PEN | J133: -4199.93 | L133: 4199.93 | M133: -4199.93 | O133: BARCENA BRAGA, KATTYA ADELAIDA
A134: BBVA1/2025/00422 | B134: BBVA1/2025/00422 | C134: 45712 | E134: 1220004 ANTICIPOS VENTA DE DEPARTAMENTO PROY SB | F134: VARIOS | G134: SB | I134: PEN | J134: -1311.02 | L134: 1311.02 | M134: -1311.02 | N134: A31491 | O134: BARCENA BRAGA, KATTYA ADELAIDA
A135: BBVA1/2025/00409 | B135: BBVA1/2025/00409 | C135: 45709 | E135: 1220004 ANTICIPOS VENTA DE DEPARTAMENTO PROY SB | F135: VARIOS | G135: ABONO SAN BARTOLO | I135: PEN | J135: -4192.2 | L135: 4192.2 | M135: -4192.2 | O135: BARCENA BRAGA, KATTYA ADELAIDA
A136: BBVA1/2025/00408 | B136: BBVA1/2025/00408 | C136: 45709 | E136: 1220004 ANTICIPOS VENTA DE DEPARTAMENTO PROY SB | F136: VARIOS | G136: SB | I136: PEN | J136: -2514.11 | L136: 2514.11 | M136: -2514.11 | O136: BARCENA BRAGA, KATTYA ADELAIDA
A137: BBVA1/2025/00397 | B137: BBVA1/2025/00397 | C137: 45708 | E137: 1220004 ANTICIPOS VENTA DE DEPARTAMENTO PROY SB | F137: VARIOS | G137: SB | I137: PEN | J137: -1622.51 | L137: 1622.51 | M137: -1622.51 | N137: A31515 | O137: BARCENA BRAGA, KATTYA ADELAIDA
A138: BBVA1/2025/00374 | B138: BBVA1/2025/00374 | C138: 45706 | E138: 1220004 ANTICIPOS VENTA DE DEPARTAMENTO PROY SB | F138: VARIOS | G138: SB | I138: PEN | J138: -1622.5 | L138: 1622.5 | M138: -1622.5 | N138: A31513 | O138: BARCENA BRAGA, KATTYA ADELAIDA
A139: BBVA1/2025/00368 | B139: BBVA1/2025/00368 | C139: 45705 | E139: 1220004 ANTICIPOS VENTA DE DEPARTAMENTO PROY SB | F139: VARIOS | G139: SB | I139: PEN | J139: -5220.1 | L139: 5220.1 | M139: -5220.1 | O139: BARCENA BRAGA, KATTYA ADELAIDA
A140: BBVA1/2025/00350 | B140: BBVA1/2025/00350 | C140: 45702 | E140: 1220004 ANTICIPOS VENTA DE DEPARTAMENTO PROY SB | F140: VARIOS | G140: SB | I140: PEN | J140: -1943.51 | L140: 1943.51 | M140: -1943.51 | N140: A31569 | O140: BARCENA BRAGA, KATTYA ADELAIDA
A141: BBVA1/2025/00319 | B141: BBVA1/2025/00319 | C141: 45700 | E141: 1220004 ANTICIPOS VENTA DE DEPARTAMENTO PROY SB | F141: VARIOS | G141: SB | I141: PEN | J141: -1878 | L141: 1878 | M141: -1878 | O141: BARCENA BRAGA, KATTYA ADELAIDA
A142: BBVA1/2025/00283 | B142: BBVA1/2025/00283 | C142: 45698 | E142: 1220004 ANTICIPOS VENTA DE DEPARTAMENTO PROY SB | F142: VARIOS | G142: SB | I142: PEN | J142: -4107.49 | L142: 4107.49 | M142: -4107.49 | O142: BARCENA BRAGA, KATTYA ADELAIDA
A143: BBVA1/2025/00273 | B143: BBVA1/2025/00273 | C143: 45695 | E143: 1220004 ANTICIPOS VENTA DE DEPARTAMENTO PROY SB | F143: VARIOS | G143: SB | I143: PEN | J143: -748.5 | L143: 748.5 | M143: -748.5 | N143: A31477 | O143: BARCENA BRAGA, KATTYA ADELAIDA
A144: BBVA1/2025/00268 | B144: BBVA1/2025/00268 | C144: 45694 | E144: 1220004 ANTICIPOS VENTA DE DEPARTAMENTO PROY SB | F144: VARIOS | G144: SB | I144: PEN | J144: -3625.99 | L144: 3625.99 | M144: -3625.99 | N144: A31585 | O144: BARCENA BRAGA, KATTYA ADELAIDA
A145: BBVA1/2025/00233 | B145: BBVA1/2025/00233 | C145: 45692 | E145: 1220004 ANTICIPOS VENTA DE DEPARTAMENTO PROY SB | F145: VARIOS | G145: SB | I145: PEN | J145: -1651.6 | L145: 1651.6 | M145: -1651.6 | N145: A31602 | O145: BARCENA BRAGA, KATTYA ADELAIDA
A146: BBVA1/2025/00210 | B146: BBVA1/2025/00210 | C146: 45691 | E146: 1220004 ANTICIPOS VENTA DE DEPARTAMENTO PROY SB | F146: VARIOS | G146: SB | I146: PEN | J146: -1737.52 | L146: 1737.52 | M146: -1737.52 | N146: A31545 | O146: BARCENA BRAGA, KATTYA ADELAIDA
A147: BBVA1/2025/00209 | B147: BBVA1/2025/00209 | C147: 45691 | E147: 1220004 ANTICIPOS VENTA DE DEPARTAMENTO PROY SB | F147: VARIOS | G147: SB | I147: PEN | J147: -966 | L147: 966 | M147: -966 | N147: A31486 | O147: BARCENA BRAGA, KATTYA ADELAIDA
A148: BBVA1/2025/00200 | B148: BBVA1/2025/00200 | C148: 45688 | E148: 1220004 ANTICIPOS VENTA DE DEPARTAMENTO PROY SB | F148: VARIOS | G148: SB | I148: PEN | J148: -4797.5 | L148: 4797.5 | M148: -4797.5 | N148: A31591 | O148: BARCENA BRAGA, KATTYA ADELAIDA
...

Sheet 122xx5
A1: Asiento contable | B1: Número | C1: Fecha | D1: Fecha de vencimiento | E1: Cuenta | F1: Socio | G1: Etiqueta | H1: Referencia | I1: Moneda | J1: Importe en moneda | K1: Debe | L1: Haber | M1: Saldo | N1: Conciliación | O1: Creado por
A2: 1220005 ANTICIPOS VENTA - MARKETPLACE (962)
A3: SCT01/2025/02561 | B3: SCT01/2025/02561 | C3: 46112 | E3: 1220005 ANTICIPOS VENTA - MARKETPLACE | F3: VARIOS | G3: INTERCORP | I3: PEN | J3: -419.99 | L3: 419.99 | M3: -419.99 | O3: BARCENA BRAGA, KATTYA ADELAIDA
A4: SCT01/2025/02558 | B4: SCT01/2025/02558 | C4: 46112 | E4: 1220005 ANTICIPOS VENTA - MARKETPLACE | F4: VARIOS | G4: MERCADO PAGO | I4: PEN | J4: -2930.79 | L4: 2930.79 | M4: -2930.79 | O4: BARCENA BRAGA, KATTYA ADELAIDA
A5: PAPANT/2025/09691 (B B01-00006384) | B5: PAPANT/2025/09691 | C5: 46112 | D5: 46112 | E5: 1220005 ANTICIPOS VENTA - MARKETPLACE | F5: TORRES GUZMAN, ALEX RODRIGO | G5: Pago de cliente S/ 452.00 - TORRES GUZMAN, ALEX RODRIGO - 31/03/2026 | H5: B B01-00006384 | I5: PEN | J5: 452 | K5: 452 | M5: 452 | O5: BARCENA BRAGA, KATTYA ADELAIDA
A6: PAPANT/2025/09690 (B B01-00006375) | B6: PAPANT/2025/09690 | C6: 46112 | D6: 46112 | E6: 1220005 ANTICIPOS VENTA - MARKETPLACE | F6: SANTOS ARIAS, IVONNE GISELA | G6: Pago de cliente S/ 128.04 - SANTOS ARIAS, IVONNE GISELA - 31/03/2026 | H6: B B01-00006375 | I6: PEN | J6: 128.04 | K6: 128.04 | M6: 128.04 | O6: BARCENA BRAGA, KATTYA ADELAIDA
A7: PAPANT/2025/09689 (B B01-00006357) | B7: PAPANT/2025/09689 | C7: 46112 | D7: 46112 | E7: 1220005 ANTICIPOS VENTA - MARKETPLACE | F7: HINOJOSA ALCAZAR, MARCO ANTONIO | G7: Pago de cliente S/ 53.91 - HINOJOSA ALCAZAR, MARCO ANTONIO - 31/03/2026 | H7: B B01-00006357 | I7: PEN | J7: 53.91 | K7: 53.91 | M7: 53.91 | O7: BARCENA BRAGA, KATTYA ADELAIDA
A8: PAPANT/2025/09688 (B B01-00006317) | B8: PAPANT/2025/09688 | C8: 46112 | D8: 46112 | E8: 1220005 ANTICIPOS VENTA - MARKETPLACE | F8: ALOR RIVAS, GUSTAVO ADOLFO | G8: Pago de cliente S/ 155.00 - ALOR RIVAS, GUSTAVO ADOLFO - 31/03/2026 | H8: B B01-00006317 | I8: PEN | J8: 155 | K8: 155 | M8: 155 | O8: BARCENA BRAGA, KATTYA ADELAIDA
A9: PAPANT/2025/09687 (B B01-00006318) | B9: PAPANT/2025/09687 | C9: 46112 | D9: 46112 | E9: 1220005 ANTICIPOS VENTA - MARKETPLACE | F9: LAOS PAREDES, PAMELA DENYS | G9: Pago de cliente S/ 130.81 - LAOS PAREDES, PAMELA DENYS - 31/03/2026 | H9: B B01-00006318 | I9: PEN | J9: 130.81 | K9: 130.81 | M9: 130.81 | O9: BARCENA BRAGA, KATTYA ADELAIDA
A10: PAPANT/2025/09686 (B B01-00006321) | B10: PAPANT/2025/09686 | C10: 46112 | D10: 46112 | E10: 1220005 ANTICIPOS VENTA - MARKETPLACE | F10: PEREZ GAMBINI, MIGUEL HUMBERTO | G10: Pago de cliente S/ 284.23 - PEREZ GAMBINI, MIGUEL HUMBERTO - 31/03/2026 | H10: B B01-00006321 | I10: PEN | J10: 284.23 | K10: 284.23 | M10: 284.23 | O10: BARCENA BRAGA, KATTYA ADELAIDA
A11: PAPANT/2025/09685 (B B01-00006322) | B11: PAPANT/2025/09685 | C11: 46112 | D11: 46112 | E11: 1220005 ANTICIPOS VENTA - MARKETPLACE | F11: RODRIGUEZ SIFUENTES, DANAE ASTRYD RAFAELA | G11: Pago de cliente S/ 335.47 - RODRIGUEZ SIFUENTES, DANAE ASTRYD RAFAELA - 31/03/2026 | H11: B B01-00006322 | I11: PEN | J11: 335.47 | K11: 335.47 | M11: 335.47 | O11: BARCENA BRAGA, KATTYA ADELAIDA
A12: PAPANT/2025/09684 (B B01-00006323) | B12: PAPANT/2025/09684 | C12: 46112 | D12: 46112 | E12: 1220005 ANTICIPOS VENTA - MARKETPLACE | F12: HURTADO BOCANEGRA, ALEXANDRA JIMENA | G12: Pago de cliente S/ 41.31 - HURTADO BOCANEGRA, ALEXANDRA JIMENA - 31/03/2026 | H12: B B01-00006323 | I12: PEN | J12: 41.31 | K12: 41.31 | M12: 41.31 | O12: BARCENA BRAGA, KATTYA ADELAIDA
A13: PAPANT/2025/09683 (B B01-00006328) | B13: PAPANT/2025/09683 | C13: 46112 | D13: 46112 | E13: 1220005 ANTICIPOS VENTA - MARKETPLACE | F13: ÑAUPA PACHECO, DEISY | G13: Pago de cliente S/ 147.60 - ÑAUPA PACHECO, DEISY - 31/03/2026 | H13: B B01-00006328 | I13: PEN | J13: 147.6 | K13: 147.6 | M13: 147.6 | O13: BARCENA BRAGA, KATTYA ADELAIDA
A14: PAPANT/2025/09682 (B B01-00006329) | B14: PAPANT/2025/09682 | C14: 46112 | D14: 46112 | E14: 1220005 ANTICIPOS VENTA - MARKETPLACE | F14: SALAZAR VERGARA, KATHERINE MILAGROS | G14: Pago de cliente S/ 251.25 - SALAZAR VERGARA, KATHERINE MILAGROS - 31/03/2026 | H14: B B01-00006329 | I14: PEN | J14: 251.25 | K14: 251.25 | M14: 251.25 | O14: BARCENA BRAGA, KATTYA ADELAIDA
A15: PAPANT/2025/09681 (B B01-00006330) | B15: PAPANT/2025/09681 | C15: 46112 | D15: 46112 | E15: 1220005 ANTICIPOS VENTA - MARKETPLACE | F15: PRADO AGUILAR, JAVIER | G15: Pago de cliente S/ 172.80 - PRADO AGUILAR, JAVIER - 31/03/2026 | H15: B B01-00006330 | I15: PEN | J15: 172.8 | K15: 172.8 | M15: 172.8 | O15: BARCENA BRAGA, KATTYA ADELAIDA
A16: PAPANT/2025/09680 (B B01-00006332) | B16: PAPANT/2025/09680 | C16: 46112 | D16: 46112 | E16: 1220005 ANTICIPOS VENTA - MARKETPLACE | F16: CORONADO HILARIO, NICOLE MELANY | G16: Pago de cliente S/ 315.99 - CORONADO HILARIO, NICOLE MELANY - 31/03/2026 | H16: B B01-00006332 | I16: PEN | J16: 315.99 | K16: 315.99 | M16: 315.99 | O16: BARCENA BRAGA, KATTYA ADELAIDA
... A90: PAPANT/2025/09593 (B B01-00004147) | B90: PAPANT/2025/09593 | C90: 46112 | D90: 46112 | E90: 1220005 ANTICIPOS VENTA - MARKETPLACE | F90: VELASQUEZ CARRERA, MARIA DEL CARMEN | G90: Pago de cliente S/ 90.90 - VELASQUEZ CARRERA, MARIA DEL CARMEN - 31/03/2026 | H90: B B01-00004147 | I90: PEN | J90: 90.9 | K90: 90.9 | M90: 90.9 | O90: BARCENA BRAGA, KATTYA ADELAIDA
A91: SCT01/2025/02533 | B91: SCT01/2025/02533 | C91: 46108 | E91: 1220005 ANTICIPOS VENTA - MARKETPLACE | F91: VARIOS | G91: MERCADO PAGO | I91: PEN | J91: -21089.45 | L91: 21089.45 | M91: -21089.45 | O91: BARCENA BRAGA, KATTYA ADELAIDA
A92: SCT01/2025/02509 | B92: SCT01/2025/02509 | C92: 46106 | E92: 1220005 ANTICIPOS VENTA - MARKETPLACE | F92: VARIOS | G92: RIPLEY | I92: PEN | J92: -451.76 | L92: 451.76 | M92: -451.76 | O92: BARCENA BRAGA, KATTYA ADELAIDA
A93: SCT01/2025/02489 | B93: SCT01/2025/02489 | C93: 46105 | E93: 1220005 ANTICIPOS VENTA - MARKETPLACE | F93: VARIOS | G93: INTERCORP | I93: PEN | J93: -46.18 | L93: 46.18 | M93: -46.18 | O93: BARCENA BRAGA, KATTYA ADELAIDA
A94: SCT01/2025/02456 | B94: SCT01/2025/02456 | C94: 46100 | E94: 1220005 ANTICIPOS VENTA - MARKETPLACE | F94: VARIOS | G94: JUNTOZ | I94: PEN | J94: -173.04 | L94: 173.04 | M94: -173.04 | O94: BARCENA BRAGA, KATTYA ADELAIDA
A95: SCT01/2025/02431 | B95: SCT01/2025/02431 | C95: 46094 | E95: 1220005 ANTICIPOS VENTA - MARKETPLACE | F95: VARIOS | G95: JUNTOZ | I95: PEN | J95: -100.48 | L95: 100.48 | M95: -100.48 | O95: BARCENA BRAGA, KATTYA ADELAIDA
A96: SCT01/2025/02366 | B96: SCT01/2025/02366 | C96: 46091 | E96: 1220005 ANTICIPOS VENTA - MARKETPLACE | F96: VARIOS | G96: RIPLEY | I96: PEN | J96: -270.02 | L96: 270.02 | M96: -270.02 | O96: BARCENA BRAGA, KATTYA ADELAIDA
A97: SCT01/2025/02393 | B97: SCT01/2025/02393 | C97: 46086 | E97: 1220005 ANTICIPOS VENTA - MARKETPLACE | F97: VARIOS | G97: JUNTOZ | I97: PEN | J97: -537.73 | L97: 537.73 | M97: -537.73 | O97: BARCENA BRAGA, KATTYA ADELAIDA
A98: SCT01/2025/02355 | B98: SCT01/2025/02355 | C98: 46084 | E98: 1220005 ANTICIPOS VENTA - MARKETPLACE | F98: VARIOS | G98: INTERCORP | I98: PEN | J98: -138.78 | L98: 138.78 | M98: -138.78 | O98: BARCENA BRAGA, KATTYA ADELAIDA
A99: SCT01/2025/02311 | B99: SCT01/2025/02311 | C99: 46079 | E99: 1220005 ANTICIPOS VENTA - MARKETPLACE | F99: VARIOS | G99: JUNTOZ | I99: PEN | J99: -359.14 | L99: 359.14 | M99: -359.14 | O99: BARCENA BRAGA, KATTYA ADELAIDA
A100: SCT01/2025/02325 | B100: SCT01/2025/02325 | C100: 46078 | E100: 1220005 ANTICIPOS VENTA - MARKETPLACE | F100: VARIOS | G100: RIPLEY | I100: PEN | J100: -125.46 | L100: 125.46 | M100: -125.46 | O100: BARCENA BRAGA, KATTYA ADELAIDA
A101: SCT01/2025/02310 | B101: SCT01/2025/02310 | C101: 46077 | E101: 1220005 ANTICIPOS VENTA - MARKETPLACE | F101: VARIOS | G101: INTERCORP | I101: PEN | J101: -38.88 | L101: 38.88 | M101: -38.88 | O101: BARCENA BRAGA, KATTYA ADELAIDA
A102: SCT01/2025/02264 | B102: SCT01/2025/02264 | C102: 46072 | E102: 1220005 ANTICIPOS VENTA - MARKETPLACE | F102: VARIOS | G102: JUNTOZ | I102: PEN | J102: -92.87 | L102: 92.87 | M102: -92.87 | O102: BARCENA BRAGA, KATTYA ADELAIDA
... A117: SCT01/2025/02042 | B117: SCT01/2025/02042 | C117: 46030 | E117: 1220005 ANTICIPOS VENTA - MARKETPLACE | F117: VARIOS | G117: MERCADO PAGO | I117: PEN | J117: -2050 | L117: 2050 | M117: -2050 | O117: BARCENA BRAGA, KATTYA ADELAIDA
A118: PAPANT/2025/08345 (B B01-00005949) | B118: PAPANT/2025/08345 | C118: 46030 | D118: 46030 | E118: 1220005 ANTICIPOS VENTA - MARKETPLACE | F118: PINO, MAXIMO | G118: Pago de cliente S/ 112.27 - PINO, MAXIMO - 08/01/2026 | H118: B B01-00005949 | I118: PEN | J118: 112.27 | K118: 112.27 | M118: 112.27 | O118: BARCENA BRAGA, KATTYA ADELAIDA
A119: PAPANT/2025/08344 (B B01-00005896) | B119: PAPANT/2025/08344 | C119: 46030 | D119: 46030 | E119: 1220005 ANTICIPOS VENTA - MARKETPLACE | F119: YANCE ECHEGARAY, MIGUEL ANGEL | G119: Pago de cliente S/ 413.72 - YANCE ECHEGARAY, MIGUEL ANGEL - 08/01/2026 | H119: B B01-00005896 | I119: PEN | J119: 413.72 | K119: 413.72 | M119: 413.72 | O119: BARCENA BRAGA, KATTYA ADELAIDA
A120: PAPANT/2025/08343 (B B01-00005897) | B120: PAPANT/2025/08343 | C120: 46030 | D120: 46030 | E120: 1220005 ANTICIPOS VENTA - MARKETPLACE | F120: GARCIA NOLI, YILAM ROXANA | G120: Pago de cliente S/ 304.64 - GARCIA NOLI, YILAM ROXANA - 08/01/2026 | H120: B B01-00005897 | I120: PEN | J120: 304.64 | K120: 304.64 | M120: 304.64 | O120: BARCENA BRAGA, KATTYA ADELAIDA
A121: PAPANT/2025/08342 (B B01-00005918) | B121: PAPANT/2025/08342 | C121: 46030 | D121: 46030 | E121: 1220005 ANTICIPOS VENTA - MARKETPLACE | F121: AVALOS SARAS, LUCIA MAGALY | G121: Pago de cliente S/ 238.99 - AVALOS SARAS, LUCIA MAGALY - 08/01/2026 | H121: B B01-00005918 | I121: PEN | J121: 238.99 | K121: 238.99 | M121: 238.99 | O121: BARCENA BRAGA, KATTYA ADELAIDA
A122: PAPANT/2025/08341 (B B01-00005919) | B122: PAPANT/2025/08341 | C122: 46030 | D122: 46030 | E122: 1220005 ANTICIPOS VENTA - MARKETPLACE | F122: BAZALAR CHAVARRIA, MARCIA MIRELLA | G122: Pago de cliente S/ 178.92 - BAZALAR CHAVARRIA, MARCIA MIRELLA - 08/01/2026 | H122: B B01-00005919 | I122: PEN | J122: 178.92 | K122: 178.92 | M122: 178.92 | O122: BARCENA BRAGA, KATTYA ADELAIDA
A123: PAPANT/2025/08340 (B B01-00005923) | B123: PAPANT/2025/08340 | C123: 46030 | D123: 46030 | E123: 1220005 ANTICIPOS VENTA - MARKETPLACE | F123: FRANCISCO FIGUEROA, CHRISTIAN FRANCO | G123: Pago de cliente S/ 35.99 - FRANCISCO FIGUEROA, CHRISTIAN FRANCO - 08/01/2026 | H123: B B01-00005923 | I123: PEN | J123: 35.99 | K123: 35.99 | M123: 35.99 | O123: BARCENA BRAGA, KATTYA ADELAIDA
A124: PAPANT/2025/08338 (B B01-00005715) | B124: PAPANT/2025/08338 | C124: 46030 | D124: 46030 | E124: 1220005 ANTICIPOS VENTA - MARKETPLACE | F124: BALDEON REYES, CHRISTIAN JESUS | G124: Pago de cliente S/ 99.90 - BALDEON REYES, CHRISTIAN JESUS - 08/01/2026 | H124: B B01-00005715 | I124: PEN | J124: 99.9 | K124: 99.9 | M124: 99.9 | O124: BARCENA BRAGA, KATTYA ADELAIDA
A125: PAPANT/2025/08336 (B B01-00005777) | B125: PAPANT/2025/08336 | C125: 46030 | D125: 46030 | E125: 1220005 ANTICIPOS VENTA - MARKETPLACE | F125: PLASENCIA CAVERO, GRECIA LORENA | G125: Pago de cliente S/ 137.20 - PLASENCIA CAVERO, GRECIA LORENA - 08/01/2026 | H125: B B01-00005777 | I125: PEN | J125: 137.2 | K125: 137.2 | M125: 137.2 | O125: BARCENA BRAGA, KATTYA ADELAIDA
A126: PAPANT/2025/08335 (F F01-00003963) | B126: PAPANT/2025/08335 | C126: 46030 | D126: 46030 | E126: 1220005 ANTICIPOS VENTA - MARKETPLACE | F126: COORPORACION LA GRANJA SOCIEDAD ANONIMA CERRADA | G126: Pago de cliente S/ 209.40 - COORPORACION LA GRANJA SOCIEDAD ANONIMA CERRADA - 08/01/2026 | H126: F F01-00003963 | I126: PEN | J126: 209.4 | K126: 209.4 | M126: 209.4 | O126: BARCENA BRAGA, KATTYA ADELAIDA
A127: SCT01/2025/02010 | B127: SCT01/2025/02010 | C127: 46027 | E127: 1220005 ANTICIPOS VENTA - MARKETPLACE | F127: VARIOS | G127: JUNTOZ | I127: PEN | J127: -187.83 | L127: 187.83 | M127: -187.83 | O127: BARCENA BRAGA, KATTYA ADELAIDA
A128: PAPANT/2025/08339 (B B01-00005709) | B128: PAPANT/2025/08339 | C128: 46023 | D128: 46023 | E128: 1220005 ANTICIPOS VENTA - MARKETPLACE | F128: SALAZAR BALBIN, IRWIN FRANK | G128: Pago de cliente S/ 104.50 - SALAZAR BALBIN, IRWIN FRANK - 01/01/2026 | H128: B B01-00005709 | I128: PEN | J128: 104.5 | K128: 104.5 | M128: 104.5 | O128: BARCENA BRAGA, KATTYA ADELAIDA
A129: PAPANT/2025/08334 (B B01-00005876) | B129: PAPANT/2025/08334 | C129: 46023 | D129: 46023 | E129: 1220005 ANTICIPOS VENTA - MARKETPLACE | F129: MACHADO CASTRO, GLORIA ANDREA | G129: Pago de cliente S/ 191.20 - MACHADO CASTRO, GLORIA ANDREA - 01/01/2026 | H129: B B01-00005876 | I129: PEN | J129: 191.2 | K129: 191.2 | M129: 191.2 | O129: BARCENA BRAGA, KATTYA ADELAIDA
A130: PAPANT/2025/08333 (B B01-00005850) | B130: PAPANT/2025/08333 | C130: 46023 | D130: 46023 | E130: 1220005 ANTICIPOS VENTA - MARKETPLACE | F130: GUZMAN BIANCHI, CONSUELO CECILIA | G130: Pago de cliente S/ 98.83 - GUZMAN BIANCHI, CONSUELO CECILIA - 01/01/2026 | H130: B B01-00005850 | I130: PEN | J130: 98.83 | K130: 98.83 | M130: 98.83 | O130: BARCENA BRAGA, KATTYA ADELAIDA
A131: PAPANT/2025/08332 (B B01-00005711) | B131: PAPANT/2025/08332 | C131: 46023 | D131: 46023 | E131: 1220005 ANTICIPOS VENTA - MARKETPLACE | F131: SALAZAR VERGARA, KATHERINE MILAGROS | G131: Pago de cliente S/ 149.73 - SALAZAR VERGARA, KATHERINE MILAGROS - 01/01/2026 | H131: B B01-00005711 | I131: PEN | J131: 149.73 | K131: 149.73 | M131: 149.73 | O131: BARCENA BRAGA, KATTYA ADELAIDA
A132: PAPANT/2025/08331 (B B01-00005714) | B132: PAPANT/2025/08331 | C132: 46023 | D132: 46023 | E132: 1220005 ANTICIPOS VENTA - MARKETPLACE | F132: TOMAS MAMANI, SALVADOR ISAI | G132: Pago de cliente S/ 140.49 - TOMAS MAMANI, SALVADOR ISAI - 01/01/2026 | H132: B B01-00005714 | I132: PEN | J132: 140.49 | K132: 140.49 | M132: 140.49 | O132: BARCENA BRAGA, KATTYA ADELAIDA
A133: PAPANT/2025/08330 (B B01-00005755) | B133: PAPANT/2025/08330 | C133: 46023 | D133: 46023 | E133: 1220005 ANTICIPOS VENTA - MARKETPLACE | F133: VASQUEZ PEÑA, JAKELINNE ANGELICA | G133: Pago de cliente S/ 274.40 - VASQUEZ PEÑA, JAKELINNE ANGELICA - 01/01/2026 | H133: B B01-00005755 | I133: PEN | J133: 274.4 | K133: 274.4 | M133: 274.4 | O133: BARCENA BRAGA, KATTYA ADELAIDA
A134: PAPANT/2025/08329 (F F01-00003892) | B134: PAPANT/2025/08329 | C134: 46023 | D134: 46023 | E134: 1220005 ANTICIPOS VENTA - MARKETPLACE | F134: DIABERT SALUD EMPRESA INDIVIDUAL DE RESPONSABILIDAD LIMITADA | G134: Pago de cliente S/ 232.57 - DIABERT SALUD EMPRESA INDIVIDUAL DE RESPONSABILIDAD LIMITADA - 01/01/2026 | H134: F F01-00003892 | I134: PEN | J134: 232.57 | K134: 232.57 | M134: 232.57 | O134: BARCENA BRAGA, KATTYA ADELAIDA
A135: PAPANT/2025/08328 (B B01-00005497) | B135: PAPANT/2025/08328 | C135: 46023 | D135: 46023 | E135: 1220005 ANTICIPOS VENTA - MARKETPLACE | F135: DIAZ PASQUALIC, CINTYA LOURDES | G135: Pago de cliente S/ 95.12 - DIAZ PASQUALIC, CINTYA LOURDES - 01/01/2026 | H135: B B01-00005497 | I135: PEN | J135: 95.12 | K135: 95.12 | M135: 95.12 | O135: BARCENA BRAGA, KATTYA ADELAIDA
A136: PAPANT/2025/08327 (B B01-00005447) | B136: PAPANT/2025/08327 | C136: 46023 | D136: 46023 | E136: 1220005 ANTICIPOS VENTA - MARKETPLACE | F136: BENITO AVILA, MIRIAM INES | G136: Pago de cliente S/ 382.42 - BENITO AVILA, MIRIAM INES - 01/01/2026 | H136: B B01-00005447 | I136: PEN | J136: 382.42 | K136: 382.42 | M136: 382.42 | O136: BARCENA BRAGA, KATTYA ADELAIDA
A137: PAPANT/2025/08326 (B B01-00005448) | B137: PAPANT/2025/08326 | C137: 46023 | D137: 46023 | E137: 1220005 ANTICIPOS VENTA - MARKETPLACE | F137: CERVANTES YRIGOYEN, FABRICIO | G137: Pago de cliente S/ 137.95 - CERVANTES YRIGOYEN, FABRICIO - 01/01/2026 | H137: B B01-00005448 | I137: PEN | J137: 137.95 | K137: 137.95 | M137: 137.95 | O137: BARCENA BRAGA, KATTYA ADELAIDA
A138: PAPANT/2025/08325 (F F01-00003788) | B138: PAPANT/2025/08325 | C138: 46023 | D138: 46023 | E138: 1220005 ANTICIPOS VENTA - MARKETPLACE | F138: DIABERT SALUD EMPRESA INDIVIDUAL DE RESPONSABILIDAD LIMITADA | G138: Pago de cliente S/ 90.81 - DIABERT SALUD EMPRESA INDIVIDUAL DE RESPONSABILIDAD LIMITADA - 01/01/2026 | H138: F F01-00003788 | I138: PEN | J138: 90.81 | K138: 90.81 | M138: 90.81 | O138: BARCENA BRAGA, KATTYA ADELAIDA
A139: PAPANT/2025/08324 (B B01-00005359) | B139: PAPANT/2025/08324 | C139: 46023 | D139: 46023 | E139: 1220005 ANTICIPOS VENTA - MARKETPLACE | F139: RIVAS LOAIZA, CONNY | G139: Pago de cliente S/ 66.50 - RIVAS LOAIZA, CONNY - 01/01/2026 | H139: B B01-00005359 | I139: PEN | J139: 66.5 | K139: 66.5 | M139: 66.5 | O139: BARCENA BRAGA, KATTYA ADELAIDA
... A798: PAPANT/2025/07413 (B B01-00002427) | B798: PAPANT/2025/07413 | C798: 46023 | D798: 46023 | E798: 1220005 ANTICIPOS VENTA - MARKETPLACE | F798: BOCCHIO ZERECEDA, SOFIA MARIA | G798: Pago de cliente S/ 9.55 - BOCCHIO ZERECEDA, SOFIA MARIA - 01/01/2026 | H798: B B01-00002427 | I798: PEN | J798: 9.55 | K798: 9.55 | M798: 9.55 | O798: BARCENA BRAGA, KATTYA ADELAIDA
A799: SCT01/2025/01944 | B799: SCT01/2025/01944 | C799: 46020 | E799: 1220005 ANTICIPOS VENTA - MARKETPLACE | F799: VARIOS | G799: MERCADO PAGO | I799: PEN | J799: -1524.31 | L799: 1524.31 | M799: -1524.31 | O799: BARCENA BRAGA, KATTYA ADELAIDA
A800: SCT01/2025/01931 | B800: SCT01/2025/01931 | C800: 46020 | E800: 1220005 ANTICIPOS VENTA - MARKETPLACE | F800: VARIOS | G800: JUNTOZ | I800: PEN | J800: -138.32 | L800: 138.32 | M800: -138.32 | O800: BARCENA BRAGA, KATTYA ADELAIDA
A801: SCT01/2025/02137 | B801: SCT01/2025/02137 | C801: 46014 | E801: 1220005 ANTICIPOS VENTA - MARKETPLACE | F801: VARIOS | G801: RIPLEY | I801: PEN | J801: -376.91 | L801: 376.91 | M801: -376.91 | O801: BARCENA BRAGA, KATTYA ADELAIDA
A802: SCT01/2025/01841 | B802: SCT01/2025/01841 | C802: 46007 | E802: 1220005 ANTICIPOS VENTA - MARKETPLACE | F802: VARIOS | G802: MERCADO PAGO | I802: PEN | J802: -2167 | L802: 2167 | M802: -2167 | O802: BARCENA BRAGA, KATTYA ADELAIDA
A803: SCT01/2025/01694 | B803: SCT01/2025/01694 | C803: 45989 | E803: 1220005 ANTICIPOS VENTA - MARKETPLACE | F803: VARIOS | G803: JUNTOZ | I803: PEN | J803: -300.93 | L803: 300.93 | M803: -300.93 | O803: BARCENA BRAGA, KATTYA ADELAIDA
A804: SCT01/2025/01686 | B804: SCT01/2025/01686 | C804: 45987 | E804: 1220005 ANTICIPOS VENTA - MARKETPLACE | F804: VARIOS | G804: INTERCORP | I804: PEN | J804: -282.38 | L804: 282.38 | M804: -282.38 | O804: BARCENA BRAGA, KATTYA ADELAIDA
A805: SCT01/2025/02535 | B805: SCT01/2025/02535 | C805: 46108 | E805: 1220005 ANTICIPOS VENTA - MARKETPLACE | F805: VARIOS | G805: FPAY | I805: PEN | J805: -7318.8 | L805: 7318.8 | M805: -7318.8 | N805: A159460 | O805: BARCENA BRAGA, KATTYA ADELAIDA
A806: SCT01/2025/02391 | B806: SCT01/2025/02391 | C806: 46087 | E806: 1220005 ANTICIPOS VENTA - MARKETPLACE | F806: VARIOS | G806: FPAY | I806: PEN | J806: -3616.6 | L806: 3616.6 | M806: -3616.6 | N806: A159460 | O806: BARCENA BRAGA, KATTYA ADELAIDA
A807: SCT01/2025/02343 | B807: SCT01/2025/02343 | C807: 46080 | E807: 1220005 ANTICIPOS VENTA - MARKETPLACE | F807: VARIOS | G807: FPAY | I807: PEN | J807: -1660.72 | L807: 1660.72 | M807: -1660.72 | N807: A159460 | O807: BARCENA BRAGA, KATTYA ADELAIDA
A808: SCT01/2025/02287 | B808: SCT01/2025/02287 | C808: 46076 | E808: 1220005 ANTICIPOS VENTA - MARKETPLACE | F808: VARIOS | G808: FPAY | I808: PEN | J808: -1471.9 | L808: 1471.9 | M808: -1471.9 | N808: A159460 | O808: BARCENA BRAGA, KATTYA ADELAIDA
A809: SCT01/2025/01646 | B809: SCT01/2025/01646 | C809: 45979 | E809: 1220005 ANTICIPOS VENTA - MARKETPLACE | F809: VARIOS | G809: INTERCORP | I809: PEN | J809: -25.2 | L809: 25.2 | M809: -25.2 | O809: BARCENA BRAGA, KATTYA ADELAIDA
A810: SCT01/2025/01643 | B810: SCT01/2025/01643 | C810: 45978 | E810: 1220005 ANTICIPOS VENTA - MARKETPLACE | F810: VARIOS | G810: MERCADO PAGO | I810: PEN | J810: -8790.72 | L810: 8790.72 | M810: -8790.72 | O810: BARCENA BRAGA, KATTYA ADELAIDA
A811: SCT01/2025/02255 | B811: SCT01/2025/02255 | C811: 46069 | E811: 1220005 ANTICIPOS VENTA - MARKETPLACE | F811: VARIOS | G811: FPAY | I811: PEN | J811: -1274.57 | L811: 1274.57 | M811: -1274.57 | N811: A159460 | O811: BARCENA BRAGA, KATTYA ADELAIDA
A812: SCT01/2025/02202 | B812: SCT01/2025/02202 | C812: 46062 | E812: 1220005 ANTICIPOS VENTA - MARKETPLACE | F812: VARIOS | G812: FPAY | I812: PEN | J812: -1732.25 | L812: 1732.25 | M812: -1732.25 | N812: A159460 | O812: BARCENA BRAGA, KATTYA ADELAIDA
A813: SCT01/2025/02174 | B813: SCT01/2025/02174 | C813: 46055 | E813: 1220005 ANTICIPOS VENTA - MARKETPLACE | F813: VARIOS | G813: FPAY | I813: PEN | J813: -923.48 | L813: 923.48 | M813: -923.48 | N813: A159460 | O813: BARCENA BRAGA, KATTYA ADELAIDA
A814: SCT01/2025/01612 | B814: SCT01/2025/01612 | C814: 45974 | E814: 1220005 ANTICIPOS VENTA - MARKETPLACE | F814: VARIOS | G814: JUNTOS | I814: PEN | J814: -149.93 | L814: 149.93 | M814: -149.93 | O814: BARCENA BRAGA, KATTYA ADELAIDA
A815: SCT01/2025/01589 | B815: SCT01/2025/01589 | C815: 45973 | E815: 1220005 ANTICIPOS VENTA - MARKETPLACE | F815: VARIOS | G815: INYERCORP | I815: PEN | J815: -225.62 | L815: 225.62 | M815: -225.62 | O815: BARCENA BRAGA, KATTYA ADELAIDA
A816: SCT01/2025/02129 | B816: SCT01/2025/02129 | C816: 46048 | E816: 1220005 ANTICIPOS VENTA - MARKETPLACE | F816: VARIOS | G816: FPAY | I816: PEN | J816: -2165.48 | L816: 2165.48 | M816: -2165.48 | N816: A159460 | O816: BARCENA BRAGA, KATTYA ADELAIDA
A817: SCT01/2025/02113 | B817: SCT01/2025/02113 | C817: 46045 | E817: 1220005 ANTICIPOS VENTA - MARKETPLACE | F817: VARIOS | G817: FPAY | I817: PEN | J817: -1962.56 | L817: 1962.56 | M817: -1962.56 | N817: A159460 | O817: BARCENA BRAGA, KATTYA ADELAIDA
A818: SCT01/2025/02045 | B818: SCT01/2025/02045 | C818: 46029 | E818: 1220005 ANTICIPOS VENTA - MARKETPLACE | F818: VARIOS | G818: FPAY | I818: PEN | J818: -723.58 | L818: 723.58 | M818: -723.58 | N818: A159460 | O818: BARCENA BRAGA, KATTYA ADELAIDA
A819: SCT01/2025/02009 | B819: SCT01/2025/02009 | C819: 46028 | E819: 1220005 ANTICIPOS VENTA - MARKETPLACE | F819: VARIOS | G819: FPAY | I819: PEN | J819: -267.58 | L819: 267.58 | M819: -267.58 | N819: A159460 | O819: BARCENA BRAGA, KATTYA ADELAIDA
A820: SCT01/2025/02011 | B820: SCT01/2025/02011 | C820: 46027 | E820: 1220005 ANTICIPOS VENTA - MARKETPLACE | F820: VARIOS | G820: FPAY | I820: PEN | J820: -1236.9 | L820: 1236.9 | M820: -1236.9 | N820: A159460 | O820: BARCENA BRAGA, KATTYA ADELAIDA
A821: SCT01/2025/01887 | B821: SCT01/2025/01887 | C821: 46010 | E821: 1220005 ANTICIPOS VENTA - MARKETPLACE | F821: VARIOS | G821: FPAY | I821: PEN | J821: -752.83 | L821: 752.83 | M821: -752.83 | N821: A159460 | O821: BARCENA BRAGA, KATTYA ADELAIDA
A822: SCT01/2025/01878 | B822: SCT01/2025/01878 | C822: 46009 | E822: 1220005 ANTICIPOS VENTA - MARKETPLACE | F822: VARIOS | G822: FPAY | I822: PEN | J822: -1198.74 | L822: 1198.74 | M822: -1198.74 | N822: A159460 | O822: BARCENA BRAGA, KATTYA ADELAIDA
A823: SCT01/2025/01581 | B823: SCT01/2025/01581 | C823: 45967 | E823: 1220005 ANTICIPOS VENTA - MARKETPLACE | F823: VARIOS | G823: JUNTOZ | I823: PEN | J823: -151.05 | L823: 151.05 | M823: -151.05 | O823: BARCENA BRAGA, KATTYA ADELAIDA
A824: SCT01/2025/01556 | B824: SCT01/2025/01556 | C824: 45965 | E824: 1220005 ANTICIPOS VENTA - MARKETPLACE | F824: VARIOS | G824: INTERCORP | I824: PEN | J824: -557.95 | L824: 557.95 | M824: -557.95 | O824: BARCENA BRAGA, KATTYA ADELAIDA
A825: SCT01/2025/01876 | B825: SCT01/2025/01876 | C825: 46009 | E825: 1220005 ANTICIPOS VENTA - MARKETPLACE | F825: VARIOS | G825: FPAY | I825: PEN | J825: -692.32 | L825: 692.32 | M825: -692.32 | N825: A159460 | O825: BARCENA BRAGA, KATTYA ADELAIDA
A826: SCT01/2025/01533 | B826: SCT01/2025/01533 | C826: 45964 | E826: 1220005 ANTICIPOS VENTA - MARKETPLACE | F826: VARIOS | G826: MERCADO PAGO | I826: PEN | J826: -837.61 | L826: 837.61 | M826: -837.61 | O826: BARCENA BRAGA, KATTYA ADELAIDA
A827: SCT01/2025/01840 | B827: SCT01/2025/01840 | C827: 46007 | E827: 1220005 ANTICIPOS VENTA - MARKETPLACE | F827: VARIOS | G827: FPAY | I827: PEN | J827: -484.56 | L827: 484.56 | M827: -484.56 | N827: A159460 | O827: BARCENA BRAGA, KATTYA ADELAIDA
A828: SCT01/2025/01517 | B828: SCT01/2025/01517 | C828: 45961 | E828: 1220005 ANTICIPOS VENTA - MARKETPLACE | F828: VARIOS | G828: MERCADO PAGO | I828: PEN | J828: -3369.57 | L828: 3369.57 | M828: -3369.57 | O828: BARCENA BRAGA, KATTYA ADELAIDA
A829: SCT01/2025/01495 | B829: SCT01/2025/01495 | C829: 45960 | E829: 1220005 ANTICIPOS VENTA - MARKETPLACE | F829: VARIOS | G829: INTERCORP | I829: PEN | J829: -253.8 | L829: 253.8 | M829: -253.8 | O829: BARCENA BRAGA, KATTYA ADELAIDA
A830: SCT01/2025/01456 | B830: SCT01/2025/01456 | C830: 45958 | E830: 1220005 ANTICIPOS VENTA - MARKETPLACE | F830: VARIOS | G830: MERCADO PAGO | I830: PEN | J830: -4513.35 | L830: 4513.35 | M830: -4513.35 | O830: BARCENA BRAGA, KATTYA ADELAIDA
A831: SCT01/2025/01385 | B831: SCT01/2025/01385 | C831: 45951 | E831: 1220005 ANTICIPOS VENTA - MARKETPLACE | F831: VARIOS | G831: INTERCORP | I831: PEN | J831: -199.29 | L831: 199.29 | M831: -199.29 | O831: BARCENA BRAGA, KATTYA ADELAIDA
A832: SCT01/2025/01392 | B832: SCT01/2025/01392 | C832: 45950 | E832: 1220005 ANTICIPOS VENTA - MARKETPLACE | F832: VARIOS | G832: MERCADO PAGO | I832: PEN | J832: -3494.06 | L832: 3494.06 | M832: -3494.06 | O832: BARCENA BRAGA, KATTYA ADELAIDA
A833: SCT01/2025/01429 | B833: SCT01/2025/01429 | C833: 45944 | E833: 1220005 ANTICIPOS VENTA - MARKETPLACE | F833: VARIOS | G833: INTERCORP | I833: PEN | J833: -238.82 | L833: 238.82 | M833: -238.82 | O833: BARCENA BRAGA, KATTYA ADELAIDA
A834: SCT01/2025/01379 | B834: SCT01/2025/01379 | C834: 45943 | E834: 1220005 ANTICIPOS VENTA - MARKETPLACE | F834: VARIOS | G834: MERCADOPAGO PERU SRL | I834: PEN | J834: -2179.12 | L834: 2179.12 | M834: -2179.12 | O834: BARCENA BRAGA, KATTYA ADELAIDA
A835: SCT01/2025/01355 | B835: SCT01/2025/01355 | C835: 45931 | E835: 1220005 ANTICIPOS VENTA - MARKETPLACE | F835: VARIOS | G835: MERCADO PAGO | I835: PEN | J835: -2382.2 | L835: 2382.2 | M835: -2382.2 | O835: BARCENA BRAGA, KATTYA ADELAIDA
A836: SCT01/2025/01276 | B836: SCT01/2025/01276 | C836: 45925 | E836: 1220005 ANTICIPOS VENTA - MARKETPLACE | F836: VARIOS | G836: INTERCORP | I836: PEN | J836: -40.87 | L836: 40.87 | M836: -40.87 | O836: BARCENA BRAGA, KATTYA ADELAIDA
A837: SCT01/2025/01233 | B837: SCT01/2025/01233 | C837: 45924 | E837: 1220005 ANTICIPOS VENTA - MARKETPLACE | F837: VARIOS | G837: MERCADO PAGO | I837: PEN | J837: -2063.62 | L837: 2063.62 | M837: -2063.62 | O837: BARCENA BRAGA, KATTYA ADELAIDA
A838: SCT01/2025/01236 | B838: SCT01/2025/01236 | C838: 45923 | E838: 1220005 ANTICIPOS VENTA - MARKETPLACE | F838: VARIOS | G838: INTERCORP | I838: PEN | J838: -190.1 | L838: 190.1 | M838: -190.1 | O838: BARCENA BRAGA, KATTYA ADELAIDA
A839: SCT01/2025/01223 | B839: SCT01/2025/01223 | C839: 45919 | E839: 1220005 ANTICIPOS VENTA - MARKETPLACE | F839: VARIOS | G839: MERCDO PAGO | I839: PEN | J839: -1323.27 | L839: 1323.27 | M839: -1323.27 | O839: BARCENA BRAGA, KATTYA ADELAIDA
... A841: SCT01/2025/01155 | B841: SCT01/2025/01155 | C841: 45916 | E841: 1220005 ANTICIPOS VENTA - MARKETPLACE | F841: VARIOS | G841: MERCADO PAGO | I841: PEN | J841: -3354.21 | L841: 3354.21 | M841: -3354.21 | O841: BARCENA BRAGA, KATTYA ADELAIDA
A842: SCT01/2025/01711 | B842: SCT01/2025/01711 | C842: 45992 | E842: 1220005 ANTICIPOS VENTA - MARKETPLACE | F842: VARIOS | G842: FPAY | I842: PEN | J842: -780.85 | L842: 780.85 | M842: -780.85 | N842: A159460 | O842: BARCENA BRAGA, KATTYA ADELAIDA
A843: SCT01/2025/01585 | B843: SCT01/2025/01585 | C843: 45972 | E843: 1220005 ANTICIPOS VENTA - MARKETPLACE | F843: VARIOS | G843: FPAY | I843: PEN | J843: -2.28 | L843: 2.28 | M843: -2.28 | N843: A159460 | O843: BARCENA BRAGA, KATTYA ADELAIDA
A844: SCT01/2025/01578 | B844: SCT01/2025/01578 | C844: 45971 | E844: 1220005 ANTICIPOS VENTA - MARKETPLACE | F844: VARIOS | G844: FPAY | I844: PEN | J844: -1.28 | L844: 1.28 | M844: -1.28 | N844: A159460 | O844: BARCENA BRAGA, KATTYA ADELAIDA
A845: SCT01/2025/01538 | B845: SCT01/2025/01538 | C845: 45964 | E845: 1220005 ANTICIPOS VENTA - MARKETPLACE | F845: VARIOS | G845: FPAY | I845: PEN | J845: -565.03 | L845: 565.03 | M845: -565.03 | N845: A159460 | O845: BARCENA BRAGA, KATTYA ADELAIDA
A846: SCT01/2025/01188 | B846: SCT01/2025/01188 | C846: 45912 | E846: 1220005 ANTICIPOS VENTA - MARKETPLACE | F846: VARIOS | G846: MERCADO PAGO | I846: PEN | J846: -4271.01 | L846: 4271.01 | M846: -4271.01 | O846: BARCENA BRAGA, KATTYA ADELAIDA
...

Sheet 1232xx1
A1: Asiento contable | B1: Número | C1: Fecha | D1: Fecha de vencimiento | E1: Cuenta | F1: Socio | G1: Etiqueta | H1: Referencia | I1: Moneda | J1: Importe en moneda | K1: Debe | L1: Haber | M1: Saldo | N1: Conciliación | O1: Creado por
A2: 1232001 LETRAS EN CARTERA NACIONAL M.N. (14087) | C2: 2025-01-01 | K2: 43581619.89000025 | L2: 42326585.610000215 | M2: 1255034.2800000035
A3: LT RCB-00013630 (202601096) | B3: LT RCB-00013630 | C3: 46108 | D3: 46195 | E3: 1232001 LETRAS EN CARTERA NACIONAL M.N. | F3: CORPORACION FARMACEUTICA VETERINARIA SOCIEDAD ANONIMA CERRADA | H3: 202601096 | I3: PEN | J3: 5026.01 | K3: 5026.01 | M3: 5026.01 | N3: A140550 | O3: MATTO ASTETE, AUGUSTO WALTER
A4: LT RCB-00013629 (202601095) | B4: LT RCB-00013629 | C4: 46108 | D4: 46178 | E4: 1232001 LETRAS EN CARTERA NACIONAL M.N. | F4: CORPORACION FARMACEUTICA VETERINARIA SOCIEDAD ANONIMA CERRADA | H4: 202601095 | I4: PEN | J4: 5026.04 | K4: 5026.04 | M4: 5026.04 | N4: A140542 | O4: MATTO ASTETE, AUGUSTO WALTER
A5: LT RCB-00013628 (202601094) | B5: LT RCB-00013628 | C5: 46108 | D5: 46171 | E5: 1232001 LETRAS EN CARTERA NACIONAL M.N. | F5: CORPORACION FARMACEUTICA VETERINARIA SOCIEDAD ANONIMA CERRADA | H5: 202601094 | I5: PEN | J5: 5026.04 | K5: 5026.04 | M5: 5026.04 | N5: A140539 | O5: MATTO ASTETE, AUGUSTO WALTER
A6: LT RCB-00013627 (202601093) | B6: LT RCB-00013627 | C6: 46108 | D6: 46164 | E6: 1232001 LETRAS EN CARTERA NACIONAL M.N. | F6: CORPORACION FARMACEUTICA VETERINARIA SOCIEDAD ANONIMA CERRADA | H6: 202601093 | I6: PEN | J6: 5026.04 | K6: 5026.04 | M6: 5026.04 | N6: A140526 | O6: MATTO ASTETE, AUGUSTO WALTER
A7: LT RCB-00013626 (202601092) | B7: LT RCB-00013626 | C7: 46108 | D7: 46157 | E7: 1232001 LETRAS EN CARTERA NACIONAL M.N. | F7: CORPORACION FARMACEUTICA VETERINARIA SOCIEDAD ANONIMA CERRADA | H7: 202601092 | I7: PEN | J7: 5026.04 | K7: 5026.04 | M7: 5026.04 | N7: A140516 | O7: MATTO ASTETE, AUGUSTO WALTER
A8: LT RCB-00013625 (202601091) | B8: LT RCB-00013625 | C8: 46108 | D8: 46150 | E8: 1232001 LETRAS EN CARTERA NACIONAL M.N. | F8: CORPORACION FARMACEUTICA VETERINARIA SOCIEDAD ANONIMA CERRADA | H8: 202601091 | I8: PEN | J8: 5026.04 | K8: 5026.04 | M8: 5026.04 | N8: A140503 | O8: MATTO ASTETE, AUGUSTO WALTER
A9: LT RCB-00013624 (202601054) | B9: LT RCB-00013624 | C9: 46108 | D9: 46181 | E9: 1232001 LETRAS EN CARTERA NACIONAL M.N. | F9: CORPORACION FARMACEUTICA VETERINARIA SOCIEDAD ANONIMA CERRADA | H9: 202601054 | I9: PEN | J9: 1714.1 | K9: 1714.1 | M9: 1714.1 | N9: A140543 | O9: MATTO ASTETE, AUGUSTO WALTER
A10: LT RCB-00013623 (202601053) | B10: LT RCB-00013623 | C10: 46108 | D10: 46170 | E10: 1232001 LETRAS EN CARTERA NACIONAL M.N. | F10: CORPORACION FARMACEUTICA VETERINARIA SOCIEDAD ANONIMA CERRADA | H10: 202601053 | I10: PEN | J10: 1714.1 | K10: 1714.1 | M10: 1714.1 | N10: A140536 | O10: MATTO ASTETE, AUGUSTO WALTER
A11: LT RCB-00013622 (202601052) | B11: LT RCB-00013622 | C11: 46108 | D11: 46160 | E11: 1232001 LETRAS EN CARTERA NACIONAL M.N. | F11: CORPORACION FARMACEUTICA VETERINARIA SOCIEDAD ANONIMA CERRADA | H11: 202601052 | I11: PEN | J11: 1714.1 | K11: 1714.1 | M11: 1714.1 | N11: A140520 | O11: MATTO ASTETE, AUGUSTO WALTER
A12: LT RCB-00013621 (202601051) | B12: LT RCB-00013621 | C12: 46108 | D12: 46150 | E12: 1232001 LETRAS EN CARTERA NACIONAL M.N. | F12: CORPORACION FARMACEUTICA VETERINARIA SOCIEDAD ANONIMA CERRADA | H12: 202601051 | I12: PEN | J12: 1714.1 | K12: 1714.1 | M12: 1714.1 | N12: A140504 | O12: MATTO ASTETE, AUGUSTO WALTER
A13: LT RCB-00013620 (202601017) | B13: LT RCB-00013620 | C13: 46108 | D13: 46181 | E13: 1232001 LETRAS EN CARTERA NACIONAL M.N. | F13: CORPORACION FARMACEUTICA VETERINARIA SOCIEDAD ANONIMA CERRADA | H13: 202601017 | I13: PEN | J13: 1917.25 | K13: 1917.25 | M13: 1917.25 | N13: A140544 | O13: MATTO ASTETE, AUGUSTO WALTER
A14: LT RCB-00013619 (202601016) | B14: LT RCB-00013619 | C14: 46108 | D14: 46169 | E14: 1232001 LETRAS EN CARTERA NACIONAL M.N. | F14: CORPORACION FARMACEUTICA VETERINARIA SOCIEDAD ANONIMA CERRADA | H14: 202601016 | I14: PEN | J14: 1917.27 | K14: 1917.27 | M14: 1917.27 | N14: A140535 | O14: MATTO ASTETE, AUGUSTO WALTER
... A98: LT RCB-00013375 (202600958) | B98: LT RCB-00013375 | C98: 46104 | D98: 46174 | E98: 1232001 LETRAS EN CARTERA NACIONAL M.N. | F98: H & P DISTRIBUCIONES Y REPRESENTACIONES SOCIEDAD ANONIMA CERRADA | H98: 202600958 | I98: PEN | J98: 60614.74 | K98: 60614.74 | M98: 60614.74 | N98: A158406 | O98: MATTO ASTETE, AUGUSTO WALTER
A99: LT RCB-00013374 (202600957) | B99: LT RCB-00013374 | C99: 46104 | D99: 46157 | E99: 1232001 LETRAS EN CARTERA NACIONAL M.N. | F99: H & P DISTRIBUCIONES Y REPRESENTACIONES SOCIEDAD ANONIMA CERRADA | H99: 202600957 | I99: PEN | J99: 60614.77 | K99: 60614.77 | M99: 60614.77 | O99: MATTO ASTETE, AUGUSTO WALTER
